Workbook

Sheet 総括PL_実績(MA前合算)
B2: グループ簡易合算 | F2: 46113 | G2: 46143 | H2: 46174 | I2: 46204 | J2: 46235 | K2: 46266 | L2: 46296 | M2: 46327 | N2: 46357 | O2: 46388 | P2: 46419 | Q2: 46447
B3: 売上高 | D3: Revenue | F3: =F80 -> 1934128209
B4: 商品売上原価 | D4: COGS | F4: =F81
B5: 売上総利益 | D5: Gross Profit | F5: =F3-F4
B6: SGA | D6: SGA | F6: =F83
B7: 営業損益 | D7: Operating Profit | F7: =F5-F6
B8: 営業外損益 | D8: Non-Operating Profit | F8: =F85-F86+F73
B9: 経常損益 | D9: Ordinary Profit | F9: =F7+F8
B12: 代々木アニメーショングループ | D12: UTAITE | F12: 46113
B13: 売上高 | D13: Revenue | F13: =F99 -> 43119318
B14: 商品売上原価 | D14: COGS | F14: =F100 -> 6959949
B15: 売上総利益 | D15: Gross Profit | F15: =F13-F14 -> 36159369
B16: SGA | D16: SGA | F16: =F102 -> 34449924
B17: 営業損益 | D17: Operating Profit | F17: =F15-F16 -> 1709445
B18: 営業外損益 | D18: Non-Operating Profit | F18: =F104-F105 -> -42191841
B19: 経常損益 | D19: Ordinary Profit | F19: =F17+F18 -> -40482396
B22: Cynra | D22: Cynra | F22: 46113
B23: 売上高 | D23: Revenue | F23: =F117 -> 21265200
B24: 商品売上原価 | D24: COGS | F24: =F118 -> 13187465
B25: 売上総利益 | D25: Gross Profit | F25: =F119 -> 8077735
B26: SGA | D26: SGA | F26: =F120 -> 2532557
B27: 営業損益 | D27: Operating Profit | F27: =F121 -> 5545178
B28: 営業外損益 | D28: Non-Operating Profit | F28: =F122-F123 -> -7238
B29: 経常損益 | D29: Ordinary Profit | F29: =F124 -> 5537940
B32: V社G | D32: VOISING | F32: 46113
B33: 売上高 | D33: Revenue | F33: =F135 -> 136063159
B34: 商品売上原価 | D34: COGS | F34: =F136 -> 157236848
B35: 売上総利益 | D35: Gross Profit | F35: =F137 -> -21173689
B36: SGA | D36: SGA | F36: =F138
B37: 営業損益 | D37: Operating Profit | F37: =F139
B38: 営業外損益 | D38: Non-Operating Profit | F38: =F140-F141
B39: 経常損益 | D39: Ordinary Profit | F39: =F142
B42: 英字)UTAITE | F42: 46113
B43: 売上高 | D43: Revenue | F43: =F160 -> 0
B44: 商品売上原価 | D44: COGS | F44: =F161
B45: 売上総利益 | D45: Gross Profit | F45: =F162
B46: SGA | D46: SGA | F46: =F163
B47: 営業損益 | D47: Operating Profit | F47: =F164
B48: 営業外損益 | D48: Non-Operating Profit | F48: =F165-F166
B49: 経常損益 | D49: Ordinary Profit | F49: =F167
B52: MD1 | F52: 46113
B53: 売上高 | D53: Revenue | F53: =F194 -> 0
B54: 商品売上原価 | D54: COGS | F54: =F195 -> 0
B55: 売上総利益 | D55: Gross Profit | F55: =F196 -> 0
B56: SGA | D56: SGA | F56: =F197 -> 0
B57: 営業損益 | D57: Operating Profit | F57: =F198 -> 0
B58: 営業外損益 | D58: Non-Operating Profit | F58: =F199-F200 -> 0
B59: 経常損益 | D59: Ordinary Profit | F59: =F201 -> 0
B62: 代々木アニメーション学院 | F62: 46113
B63: 売上高 | D63: Revenue | F63: =F177 -> 1733680532
B64: 商品売上原価 | D64: COGS | F64: =F178
B65: 売上総利益 | D65: Gross Profit | F65: =F179 -> 1733680532
B66: SGA | D66: SGA | F66: =F180
B67: 営業損益 | D67: Operating Profit | F67: =F181 -> 1733680532
B68: 営業外損益 | D68: Non-Operating Profit | F68: =F182-F183 -> 0
B69: 経常損益 | D69: Ordinary Profit | F69: =F184 -> 1733680532
B72: UTAGE(持分法30% | F72: 46113
B73: 当期純利益*30% | F73: =F210 -> 0
B76: 以下、試算表元データ ※グループin順
B77: ■G連結PL（簡易合算）
B78: PL/税抜：円 | D78: PL/Tax-Excluded: JPY
F79: =F$2 -> 46113
B80: 売上高 | D80: Revenue | F80: =SUM(F99,F117,F135,F160,F177,F194) -> 1934128209
B81: 売上原価 | D81: COGS | F81: =SUM(F136,F118,F100,F161,F178,F195)
B82: 売上総利益 | D82: Gross Profit | F82: =SUM(F137,F119,F101,F162,F179,F196)
B83: 販売費及び一般管理費 | D83: SG&A | F83: =SUM(F138,F120,F102,F163,F180,F197)
B84: 営業利益 | D84: Operating Profit | F84: =SUM(F139,F121,F103,F164,F181,F198)
B85: 営業外収益 | D85: Non-Operating Income | F85: =SUM(F140,F122,F104,F165,F182,F199)
B86: 営業外費用 | D86: Non-Operating Expenses | F86: =SUM(F141,F123,F105,F166,F183,F200)
B87: 経常利益 | D87: Ordinary Profit | F87: =SUM(F142,F124,F106,F167,F184,F201)
B88: 特別利益 | D88: Extraordinary Income | F88: =SUM(F143,F125,F107,F168,F185,F202)
B89: 特別損失 | D89: Extraordinary loss | F89: =SUM(F144,F126,F108,F169,F186,F203)
B90: 税引前当期純利益 | D90: EBIT | F90: =SUM(F145,F127,F109,F170,F1993,F187,F204)
B91: 法人税等 | F91: =SUM(F146,F128,F110,F171,F1994,F188,F205)
B92: 当期純利益 | D92: Net Profit | F92: =F90-F91+F210
F93: =AVERAGE(D90:F90)
C94: ▼23年12月-24年3月迄はウタイテ各事業別PLがないため、全社PL(下記試算表)から抽出
C95: https://docs.google.com/spreadsheets/d/1ltEmuWGNHgPV1QcLSeuyr_7tN3PQC_V6gztPxafvUtQ/edit?usp=sharing
B96: ■ウタイテ社PL | C96: https://docs.google.com/spreadsheets/d/1EZ187PR9Qoi2FmIUcZ-fmtCE_zLJFrfcxMTaAlDrBGo/edit?gid=93262643#gid=93262643
B97: PL/税抜き：円 | C97: ※24年4-5月は既に合算されたものを記載。6月より事業按分されている状態。 | D97: PL/Tax-Excluded: JPY
F98: =F$2 -> 46113
B99: 売上高 | D99: Revenue | F99: =F217 -> 43119318
B100: 売上原価 | D100: COGS | F100: =F223 -> 6959949
B101: 売上総利益 | D101: Gross Profit | F101: =F224 -> 36159369
B102: 販売費及び一般管理費 | D102: SG&A | F102: =F256 -> 34449924
B103: 営業利益 | D103: Operating Profit | F103: =F257 -> 1709445
B104: 営業外収益 | D104: Non-Operating Income | F104: =F258 -> 1392416
B105: 営業外費用 | D105: Non-Operating Expenses | F105: =F265 -> 43584257
B106: 経常利益 | D106: Ordinary Profit | F106: =F269 -> -40482396
B107: 特別利益 | D107: Extraordinary Income | F107: =F270 -> 0
B108: 特別損失 | D108: Extraordinary loss | F108: =F273 -> 0
B109: 税引前当期純利益 | D109: EBIT | F109: =F277 -> -40482396
B110: 法人税等 | F110: =F278+F279 -> 0
B111: 当期純利益 | D111: Net Profit | F111: =F280 -> -40482396
B114: ■Cynra社PL | C114: https://docs.google.com/spreadsheets/d/11y8kXGsJFPXUOI0bYrqwmpKJb96p53GMVCPo7pmnq4w/edit?gid=1658084189#gid=1658084189
B115: PL/税抜き：円 | D115: PL/Tax-Excluded: JPY
F116: =F$2 -> 46113
B117: 売上高 | D117: Revenue | F117: =F1277 -> 21265200
B118: 売上原価 | D118: COGS | F118: =F1283 -> 13187465
B119: 売上総利益 | D119: Gross Profit | F119: =F117-F118 -> 8077735
...

Sheet YGR_PL
B1: ②マスタ結びつけ | C1: ① | D1: 月次推移：損益計算書_株式会社代々木アニメーショングループ（期間：2026年04月〜2027年03月、表示単位：円）
J2: 46113 | K2: 46143 | L2: 46174 | M2: 46204 | N2: 46235 | O2: 46266 | P2: 46296 | Q2: 46327 | R2: 46357 | S2: 46388 | T2: 46419 | U2: 46447 | V2: 期間累計
D3: 売上高
A4: {=XLOOKUP(C4, 'マスタ'!$C$2:$C$312, 'マスタ'!$D$2:$D$312, "マスタ未登録")} -> 売上高 | B4: =IF(AND(C4<>"", COUNTIF('マスタ'!$C:$C, C4)=0), "マスタ未登録", "") | C4: =D4&D109&E4&F4&G4&H4 -> 売上高 | E4: 売上高 | J4: 43119318 | K4: 53884627 | L4: 43374767 | M4: 43380000 | N4: 43380000 | O4: 43380000 | P4: 0 | Q4: 0 | R4: 0 | S4: 0 | T4: 0 | U4: 0 | V4: 270518712
A5: {=XLOOKUP(C5, 'マスタ'!$C$2:$C$312, 'マスタ'!$D$2:$D$312, "マスタ未登録")} -> マスタ未登録 | B5: =IF(AND(C5<>"", COUNTIF('マスタ'!$C:$C, C5)=0), "マスタ未登録", "") -> マスタ未登録 | C5: =D5&D110&E5&F5&G5&H5 -> 売上高 計 | D5: 売上高 計 | J5: 43119318 | K5: 53884627 | L5: 43374767 | M5: 43380000 | N5: 43380000 | O5: 43380000 | P5: 0 | Q5: 0 | R5: 0 | S5: 0 | T5: 0 | U5: 0 | V5: 270518712
A6: {=XLOOKUP(C6, 'マスタ'!$C$2:$C$312, 'マスタ'!$D$2:$D$312, "マスタ未登録")} -> マスタ未登録 | B6: =IF(AND(C6<>"", COUNTIF('マスタ'!$C:$C, C6)=0), "マスタ未登録", "") -> マスタ未登録 | C6: =D6&D111&E6&F6&G6&H6 -> 売上原価 | E6: 売上原価
A7: {=XLOOKUP(C7, 'マスタ'!$C$2:$C$312, 'マスタ'!$D$2:$D$312, "マスタ未登録")} -> マスタ未登録 | B7: =IF(AND(C7<>"", COUNTIF('マスタ'!$C:$C, C7)=0), "マスタ未登録", "") -> マスタ未登録 | C7: =D7&D112&E7&F7&G7&H7 -> 売上原価 | E7: 売上原価 | J7: 6959949 | K7: 2620001 | L7: 0 | M7: 0 | N7: 0 | O7: 0 | P7: 0 | Q7: 0 | R7: 0 | S7: 0 | T7: 0 | U7: 0 | V7: 9579950
A8: {=XLOOKUP(C8, 'マスタ'!$C$2:$C$312, 'マスタ'!$D$2:$D$312, "マスタ未登録")} -> 期首商品棚卸高 | B8: =IF(AND(C8<>"", COUNTIF('マスタ'!$C:$C, C8)=0), "マスタ未登録", "") | C8: =D8&D113&E8&F8&G8&H8 -> 期首商品棚卸 | G8: 期首商品棚卸 | J8: 1886546 | K8: 0 | L8: 0 | M8: 0 | N8: 0 | O8: 0 | P8: 0 | Q8: 0 | R8: 0 | S8: 0 | T8: 0 | U8: 0 | V8: 1886546
A9: {=XLOOKUP(C9, 'マスタ'!$C$2:$C$312, 'マスタ'!$D$2:$D$312, "マスタ未登録")} -> 期首商品棚卸高 | B9: =IF(AND(C9<>"", COUNTIF('マスタ'!$C:$C, C9)=0), "マスタ未登録", "") | C9: =D9&D114&E9&F9&G9&H9 -> 期首商品棚卸高 | H9: 期首商品棚卸高 | J9: 1886546 | K9: 0 | L9: 0 | M9: 0 | N9: 0 | O9: 0 | P9: 0 | Q9: 0 | R9: 0 | S9: 0 | T9: 0 | U9: 0 | V9: 1886546
A10: {=XLOOKUP(C10, 'マスタ'!$C$2:$C$312, 'マスタ'!$D$2:$D$312, "マスタ未登録")} -> 当期商品仕入高 | B10: =IF(AND(C10<>"", COUNTIF('マスタ'!$C:$C, C10)=0), "マスタ未登録", "") | C10: =D10&D115&E10&F10&G10&H10 -> 当期商品仕入 | G10: 当期商品仕入 | J10: 5788844 | K10: 2620001 | L10: 0 | M10: 0 | N10: 0 | O10: 0 | P10: 0 | Q10: 0 | R10: 0 | S10: 0 | T10: 0 | U10: 0 | V10: 8408845
A11: {=XLOOKUP(C11, 'マスタ'!$C$2:$C$312, 'マスタ'!$D$2:$D$312, "マスタ未登録")} -> 当期商品仕入高 | B11: =IF(AND(C11<>"", COUNTIF('マスタ'!$C:$C, C11)=0), "マスタ未登録", "") | C11: =D11&D116&E11&F11&G11&H11 -> 給料手当(原) | H11: 給料手当(原) | J11: 3666203 | K11: 1915784 | L11: 0 | M11: 0 | N11: 0 | O11: 0 | P11: 0 | Q11: 0 | R11: 0 | S11: 0 | T11: 0 | U11: 0 | V11: 5581987
A12: {=XLOOKUP(C12, 'マスタ'!$C$2:$C$312, 'マスタ'!$D$2:$D$312, "マスタ未登録")} -> 当期商品仕入高 | B12: =IF(AND(C12<>"", COUNTIF('マスタ'!$C:$C, C12)=0), "マスタ未登録", "") | C12: =D12&D117&E12&F12&G12&H12 -> 法定福利費(原) | H12: 法定福利費(原) | J12: 574947 | K12: 274625 | L12: 0 | M12: 0 | N12: 0 | O12: 0 | P12: 0 | Q12: 0 | R12: 0 | S12: 0 | T12: 0 | U12: 0 | V12: 849572
A13: {=XLOOKUP(C13, 'マスタ'!$C$2:$C$312, 'マスタ'!$D$2:$D$312, "マスタ未登録")} -> 当期商品仕入高 | B13: =IF(AND(C13<>"", COUNTIF('マスタ'!$C:$C, C13)=0), "マスタ未登録", "") | C13: =D13&D118&E13&F13&G13&H13 -> 外注費(原) | H13: 外注費(原) | J13: 1173000 | K13: 380000 | L13: 0 | M13: 0 | N13: 0 | O13: 0 | P13: 0 | Q13: 0 | R13: 0 | S13: 0 | T13: 0 | U13: 0 | V13: 1553000
A14: {=XLOOKUP(C14, 'マスタ'!$C$2:$C$312, 'マスタ'!$D$2:$D$312, "マスタ未登録")} -> 当期商品仕入高 | B14: =IF(AND(C14<>"", COUNTIF('マスタ'!$C:$C, C14)=0), "マスタ未登録", "") | C14: =D14&D119&E14&F14&G14&H14 -> 業務委託費(原) | H14: 業務委託費(原) | J14: 269139 | K14: 1 | L14: 0 | M14: 0 | N14: 0 | O14: 0 | P14: 0 | Q14: 0 | R14: 0 | S14: 0 | T14: 0 | U14: 0 | V14: 269140
A15: {=XLOOKUP(C15, 'マスタ'!$C$2:$C$312, 'マスタ'!$D$2:$D$312, "マスタ未登録")} -> 当期商品仕入高 | B15: =IF(AND(C15<>"", COUNTIF('マスタ'!$C:$C, C15)=0), "マスタ未登録", "") | C15: =D15&D120&E15&F15&G15&H15 -> 旅費交通費(原) | H15: 旅費交通費(原) | J15: 105355 | K15: 49591 | L15: 0 | M15: 0 | N15: 0 | O15: 0 | P15: 0 | Q15: 0 | R15: 0 | S15: 0 | T15: 0 | U15: 0 | V15: 154946
A16: {=XLOOKUP(C16, 'マスタ'!$C$2:$C$312, 'マスタ'!$D$2:$D$312, "マスタ未登録")} -> 当期商品仕入高 | B16: =IF(AND(C16<>"", COUNTIF('マスタ'!$C:$C, C16)=0), "マスタ未登録", "") | C16: =D16&D121&E16&F16&G16&H16 -> 消耗品費(原) | H16: 消耗品費(原) | J16: 200 | K16: 0 | L16: 0 | M16: 0 | N16: 0 | O16: 0 | P16: 0 | Q16: 0 | R16: 0 | S16: 0 | T16: 0 | U16: 0 | V16: 200
A17: {=XLOOKUP(C17, 'マスタ'!$C$2:$C$312, 'マスタ'!$D$2:$D$312, "マスタ未登録")} -> 他勘定振替高 | B17: =IF(AND(C17<>"", COUNTIF('マスタ'!$C:$C, C17)=0), "マスタ未登録", "") | C17: =D17&D122&E17&F17&G17&H17 -> 他勘定振替高(商) | G17: 他勘定振替高(商) | J17: 0 | K17: 0 | L17: 0 | M17: 0 | N17: 0 | O17: 0 | P17: 0 | Q17: 0 | R17: 0 | S17: 0 | T17: 0 | U17: 0 | V17: 0
A18: {=XLOOKUP(C18, 'マスタ'!$C$2:$C$312, 'マスタ'!$D$2:$D$312, "マスタ未登録")} -> 期末商品棚卸高 | B18: =IF(AND(C18<>"", COUNTIF('マスタ'!$C:$C, C18)=0), "マスタ未登録", "") | C18: =D18&D123&E18&F18&G18&H18 -> 期末商品棚卸 | G18: 期末商品棚卸 | J18: 715441 | K18: 0 | L18: 0 | M18: 0 | N18: 0 | O18: 0 | P18: 0 | Q18: 0 | R18: 0 | S18: 0 | T18: 0 | U18: 0 | V18: 715441
A19: {=XLOOKUP(C19, 'マスタ'!$C$2:$C$312, 'マスタ'!$D$2:$D$312, "マスタ未登録")} -> 期末商品棚卸高 | B19: =IF(AND(C19<>"", COUNTIF('マスタ'!$C:$C, C19)=0), "マスタ未登録", "") | C19: =D19&D124&E19&F19&G19&H19 -> 期末商品棚卸高 | H19: 期末商品棚卸高 | J19: 715441 | K19: 0 | L19: 0 | M19: 0 | N19: 0 | O19: 0 | P19: 0 | Q19: 0 | R19: 0 | S19: 0 | T19: 0 | U19: 0 | V19: 715441
A20: {=XLOOKUP(C20, 'マスタ'!$C$2:$C$312, 'マスタ'!$D$2:$D$312, "マスタ未登録")} -> マスタ未登録 | B20: =IF(AND(C20<>"", COUNTIF('マスタ'!$C:$C, C20)=0), "マスタ未登録", "") -> マスタ未登録 | C20: =D20&D125&E20&F20&G20&H20 -> 商品売上原価 | F20: 商品売上原価 | J20: 6959949 | K20: 2620001 | L20: 0 | M20: 0 | N20: 0 | O20: 0 | P20: 0 | Q20: 0 | R20: 0 | S20: 0 | T20: 0 | U20: 0 | V20: 9579950
A21: {=XLOOKUP(C21, 'マスタ'!$C$2:$C$312, 'マスタ'!$D$2:$D$312, "マスタ未登録")} -> マスタ未登録 | B21: =IF(AND(C21<>"", COUNTIF('マスタ'!$C:$C, C21)=0), "マスタ未登録", "") -> マスタ未登録 | C21: =D21&D126&E21&F21&G21&H21 -> 売上総損益金額 | D21: 売上総損益金額 | J21: 36159369 | K21: 51264626 | L21: 43374767 | M21: 43380000 | N21: 43380000 | O21: 43380000 | P21: 0 | Q21: 0 | R21: 0 | S21: 0 | T21: 0 | U21: 0 | V21: 260938762
A22: {=XLOOKUP(C22, 'マスタ'!$C$2:$C$312, 'マスタ'!$D$2:$D$312, "マスタ未登録")} -> マスタ未登録 | B22: =IF(AND(C22<>"", COUNTIF('マスタ'!$C:$C, C22)=0), "マスタ未登録", "") -> マスタ未登録 | C22: =D22&D127&E22&F22&G22&H22 -> 販売管理費 | E22: 販売管理費
A23: {=XLOOKUP(C23, 'マスタ'!$C$2:$C$312, 'マスタ'!$D$2:$D$312, "マスタ未登録")} -> 役員報酬 | B23: =IF(AND(C23<>"", COUNTIF('マスタ'!$C:$C, C23)=0), "マスタ未登録", "") | C23: =D23&D128&E23&F23&G23&H23 -> 役員報酬 | F23: 役員報酬 | J23: 3650000 | K23: 3650000 | L23: 3650000 | M23: 0 | N23: 0 | O23: 0 | P23: 0 | Q23: 0 | R23: 0 | S23: 0 | T23: 0 | U23: 0 | V23: 10950000
A24: {=XLOOKUP(C24, 'マスタ'!$C$2:$C$312, 'マスタ'!$D$2:$D$312, "マスタ未登録")} -> 給料手当 | B24: =IF(AND(C24<>"", COUNTIF('マスタ'!$C:$C, C24)=0), "マスタ未登録", "") | C24: =D24&D129&E24&F24&G24&H24 -> 給料手当 | F24: 給料手当 | J24: 1906725 | K24: 1073609 | L24: 0 | M24: 0 | N24: 0 | O24: 0 | P24: 0 | Q24: 0 | R24: 0 | S24: 0 | T24: 0 | U24: 0 | V24: 2980334
A25: {=XLOOKUP(C25, 'マスタ'!$C$2:$C$312, 'マスタ'!$D$2:$D$312, "マスタ未登録")} -> 法定福利費 | B25: =IF(AND(C25<>"", COUNTIF('マスタ'!$C:$C, C25)=0), "マスタ未登録", "") | C25: =D25&D130&E25&F25&G25&H25 -> 法定福利費 | F25: 法定福利費 | J25: 688384 | K25: 378471 | L25: 409505 | M25: 0 | N25: 0 | O25: 0 | P25: 0 | Q25: 0 | R25: 0 | S25: 0 | T25: 0 | U25: 0 | V25: 1476360
A26: {=XLOOKUP(C26, 'マスタ'!$C$2:$C$312, 'マスタ'!$D$2:$D$312, "マスタ未登録")} -> 株式報酬費用 | B26: =IF(AND(C26<>"", COUNTIF('マスタ'!$C:$C, C26)=0), "マスタ未登録", "") | C26: =D26&D131&E26&F26&G26&H26 -> 株式報酬費用 | F26: 株式報酬費用 | J26: 17395635 | K26: 17395635 | L26: 17395635 | M26: 16543881 | N26: 16543881 | O26: 16543881 | P26: 16543881 | Q26: 16543881 | R26: 16543881 | S26: 16543881 | T26: 16543881 | U26: 16543874 | V26: 201081827
A27: {=XLOOKUP(C27, 'マスタ'!$C$2:$C$312, 'マスタ'!$D$2:$D$312, "マスタ未登録")} -> 旅費交通費 | B27: =IF(AND(C27<>"", COUNTIF('マスタ'!$C:$C, C27)=0), "マスタ未登録", "") | C27: =D27&D132&E27&F27&G27&H27 -> 旅費交通費 | F27: 旅費交通費 | J27: 1009055 | K27: 302890 | L27: 17846 | M27: 0 | N27: 0 | O27: 0 | P27: 0 | Q27: 0 | R27: 0 | S27: 0 | T27: 0 | U27: 0 | V27: 1329791
A28: {=XLOOKUP(C28, 'マスタ'!$C$2:$C$312, 'マスタ'!$D$2:$D$312, "マスタ未登録")} -> 通信費 | B28: =IF(AND(C28<>"", COUNTIF('マスタ'!$C:$C, C28)=0), "マスタ未登録", "") | C28: =D28&D133&E28&F28&G28&H28 -> 通信費 | F28: 通信費 | J28: 394197 | K28: 1521086 | L28: 43630 | M28: 0 | N28: 0 | O28: 0 | P28: 0 | Q28: 0 | R28: 0 | S28: 0 | T28: 0 | U28: 0 | V28: 1958913
A29: {=XLOOKUP(C29, 'マスタ'!$C$2:$C$312, 'マスタ'!$D$2:$D$312, "マスタ未登録")} -> 採用教育費 | B29: =IF(AND(C29<>"", COUNTIF('マスタ'!$C:$C, C29)=0), "マスタ未登録", "") | C29: =D29&D134&E29&F29&G29&H29 -> 採用教育費 | F29: 採用教育費 | J29: 1155634 | K29: 755634 | L29: 700634 | M29: 700634 | N29: 590634 | O29: 590634 | P29: 423967 | Q29: 423967 | R29: 296467 | S29: 296467 | T29: 296470 | U29: 61169 | V29: 6292311
A30: {=XLOOKUP(C30, 'マスタ'!$C$2:$C$312, 'マスタ'!$D$2:$D$312, "マスタ未登録")} -> 業務委託費 | B30: =IF(AND(C30<>"", COUNTIF('マスタ'!$C:$C, C30)=0), "マスタ未登録", "") | C30: =D30&D135&E30&F30&G30&H30 -> 業務委託費 | F30: 業務委託費 | J30: 2015176 | K30: 1218548 | L30: 0 | M30: 0 | N30: 0 | O30: 0 | P30: 0 | Q30: 0 | R30: 0 | S30: 0 | T30: 0 | U30: 0 | V30: 3233724
A31: {=XLOOKUP(C31, 'マスタ'!$C$2:$C$312, 'マスタ'!$D$2:$D$312, "マスタ未登録")} -> 支払報酬 | B31: =IF(AND(C31<>"", COUNTIF('マスタ'!$C:$C, C31)=0), "マスタ未登録", "") | C31: =D31&D136&E31&F31&G31&H31 -> 支払報酬料 | F31: 支払報酬料 | J31: 2275000 | K31: 2585000 | L31: 250000 | M31: 0 | N31: 0 | O31: 0 | P31: 0 | Q31: 0 | R31: 0 | S31: 0 | T31: 0 | U31: 0 | V31: 5110000
A32: {=XLOOKUP(C32, 'マスタ'!$C$2:$C$312, 'マスタ'!$D$2:$D$312, "マスタ未登録")} -> 荷造運賃 | B32: =IF(AND(C32<>"", COUNTIF('マスタ'!$C:$C, C32)=0), "マスタ未登録", "") | C32: =D32&D137&E32&F32&G32&H32 -> 荷造運賃 | F32: 荷造運賃 | J32: 20359 | K32: 33608 | L32: 0 | M32: 0 | N32: 0 | O32: 0 | P32: 0 | Q32: 0 | R32: 0 | S32: 0 | T32: 0 | U32: 0 | V32: 53967
A33: {=XLOOKUP(C33, 'マスタ'!$C$2:$C$312, 'マスタ'!$D$2:$D$312, "マスタ未登録")} -> 支払手数料 | B33: =IF(AND(C33<>"", COUNTIF('マスタ'!$C:$C, C33)=0), "マスタ未登録", "") | C33: =D33&D138&E33&F33&G33&H33 -> 支払手数料 | F33: 支払手数料 | J33: 28224 | K33: 251913 | L33: 4000 | M33: 0 | N33: 0 | O33: 0 | P33: 0 | Q33: 0 | R33: 0 | S33: 0 | T33: 0 | U33: 0 | V33: 284137
A34: {=XLOOKUP(C34, 'マスタ'!$C$2:$C$312, 'マスタ'!$D$2:$D$312, "マスタ未登録")} -> 地代家賃 | B34: =IF(AND(C34<>"", COUNTIF('マスタ'!$C:$C, C34)=0), "マスタ未登録", "") | C34: =D34&D139&E34&F34&G34&H34 -> 地代家賃 | F34: 地代家賃 | J34: 625659 | K34: 0 | L34: 0 | M34: 0 | N34: 0 | O34: 0 | P34: 0 | Q34: 0 | R34: 0 | S34: 0 | T34: 0 | U34: 0 | V34: 625659
... A41: {=XLOOKUP(C41, 'マスタ'!$C$2:$C$312, 'マスタ'!$D$2:$D$312, "マスタ未登録")} -> 減価償却費 | B41: =IF(AND(C41<>"", COUNTIF('マスタ'!$C:$C, C41)=0), "マスタ未登録", "") | C41: =D41&D146&E41&F41&G41&H41 -> 減価償却費 | F41: 減価償却費 | J41: 254649 | K41: 246513 | L41: 250174 | M41: 250174 | N41: 250174 | O41: 250174 | P41: 250174 | Q41: 250174 | R41: 250174 | S41: 250174 | T41: 250174 | U41: 250499 | V41: 3003227
A42: {=XLOOKUP(C42, 'マスタ'!$C$2:$C$312, 'マスタ'!$D$2:$D$312, "マスタ未登録")} -> マスタ未登録 | B42: =IF(AND(C42<>"", COUNTIF('マスタ'!$C:$C, C42)=0), "マスタ未登録", "") -> マスタ未登録 | C42: =D42&D147&E42&F42&G42&H42 -> 販売管理費 計 | E42: 販売管理費 計 | J42: 34449924 | K42: 29900156 | L42: 22779878 | M42: 17494689 | N42: 17384689 | O42: 17384689 | P42: 17218022 | Q42: 17218022 | R42: 17090522 | S42: 17090522 | T42: 17090525 | U42: 16855542 | V42: 241957180
A43: {=XLOOKUP(C43, 'マスタ'!$C$2:$C$312, 'マスタ'!$D$2:$D$312, "マスタ未登録")} -> マスタ未登録 | B43: =IF(AND(C43<>"", COUNTIF('マスタ'!$C:$C, C43)=0), "マスタ未登録", "") -> マスタ未登録 | C43: =D43&D148&E43&F43&G43&H43 -> 営業損益金額 | D43: 営業損益金額 | J43: 1709445 | K43: 21364470 | L43: 20594889 | M43: 25885311 | N43: 25995311 | O43: 25995311 | P43: -17218022 | Q43: -17218022 | R43: -17090522 | S43: -17090522 | T43: -17090525 | U43: -16855542 | V43: 18981582
A44: {=XLOOKUP(C44, 'マスタ'!$C$2:$C$312, 'マスタ'!$D$2:$D$312, "マスタ未登録")} -> マスタ未登録 | B44: =IF(AND(C44<>"", COUNTIF('マスタ'!$C:$C, C44)=0), "マスタ未登録", "") -> マスタ未登録 | C44: =D44&D149&E44&F44&G44&H44 -> 営業外収益 | E44: 営業外収益 | J44: 1392416 | K44: 23741 | L44: 11342 | M44: 0 | N44: 0 | O44: 0 | P44: 0 | Q44: 0 | R44: 0 | S44: 0 | T44: 0 | U44: 0 | V44: 1427499
A45: {=XLOOKUP(C45, 'マスタ'!$C$2:$C$312, 'マスタ'!$D$2:$D$312, "マスタ未登録")} -> 受取利息 | B45: =IF(AND(C45<>"", COUNTIF('マスタ'!$C:$C, C45)=0), "マスタ未登録", "") | C45: =D45&D150&E45&F45&G45&H45 -> 受取利息 | F45: 受取利息 | J45: 12583 | K45: 11063 | L45: 11342 | M45: 0 | N45: 0 | O45: 0 | P45: 0 | Q45: 0 | R45: 0 | S45: 0 | T45: 0 | U45: 0 | V45: 34988
A46: {=XLOOKUP(C46, 'マスタ'!$C$2:$C$312, 'マスタ'!$D$2:$D$312, "マスタ未登録")} -> 雑収入 | B46: =IF(AND(C46<>"", COUNTIF('マスタ'!$C:$C, C46)=0), "マスタ未登録", "") | C46: =D46&D151&E46&F46&G46&H46 -> 雑収入 | F46: 雑収入 | J46: 1379833 | K46: 12678 | L46: 0 | M46: 0 | N46: 0 | O46: 0 | P46: 0 | Q46: 0 | R46: 0 | S46: 0 | T46: 0 | U46: 0 | V46: 1392511
A47: {=XLOOKUP(C47, 'マスタ'!$C$2:$C$312, 'マスタ'!$D$2:$D$312, "マスタ未登録")} -> マスタ未登録 | B47: =IF(AND(C47<>"", COUNTIF('マスタ'!$C:$C, C47)=0), "マスタ未登録", "") -> マスタ未登録 | C47: =D47&D152&E47&F47&G47&H47 -> 営業外費用 | E47: 営業外費用 | J47: 43584257 | K47: 16225465 | L47: 16873731 | M47: 1709589 | N47: 1709589 | O47: 1656164 | P47: 1709589 | Q47: 1656164 | R47: 1709589 | S47: 1709589 | T47: 1549315 | U47: 1709589 | V47: 91802630
A48: {=XLOOKUP(C48, 'マスタ'!$C$2:$C$312, 'マスタ'!$D$2:$D$312, "マスタ未登録")} -> 支払利息 | B48: =IF(AND(C48<>"", COUNTIF('マスタ'!$C:$C, C48)=0), "マスタ未登録", "") | C48: =D48&D153&E48&F48&G48&H48 -> 支払利息 | F48: 支払利息 | J48: 42868816 | K48: 12025465 | L48: 16873731 | M48: 1709589 | N48: 1709589 | O48: 1656164 | P48: 1709589 | Q48: 1656164 | R48: 1709589 | S48: 1709589 | T48: 1549315 | U48: 1709589 | V48: 86887189
A49: {=XLOOKUP(C49, 'マスタ'!$C$2:$C$312, 'マスタ'!$D$2:$D$312, "マスタ未登録")} -> 雑損失 | B49: =IF(AND(C49<>"", COUNTIF('マスタ'!$C:$C, C49)=0), "マスタ未登録", "") | C49: =D49&D154&E49&F49&G49&H49 -> 雑損失 | F49: 雑損失 | J49: 715441 | K49: 0 | L49: 0 | M49: 0 | N49: 0 | O49: 0 | P49: 0 | Q49: 0 | R49: 0 | S49: 0 | T49: 0 | U49: 0 | V49: 715441
A50: {=XLOOKUP(C50, 'マスタ'!$C$2:$C$312, 'マスタ'!$D$2:$D$312, "マスタ未登録")} -> マスタ未登録 | B50: =IF(AND(C50<>"", COUNTIF('マスタ'!$C:$C, C50)=0), "マスタ未登録", "") -> マスタ未登録 | C50: =D50&D155&E50&F50&G50&H50 -> 支払手数料(営業外) | F50: 支払手数料(営業外) | J50: 0 | K50: 4200000 | L50: 0 | M50: 0 | N50: 0 | O50: 0 | P50: 0 | Q50: 0 | R50: 0 | S50: 0 | T50: 0 | U50: 0 | V50: 4200000
A51: {=XLOOKUP(C51, 'マスタ'!$C$2:$C$312, 'マスタ'!$D$2:$D$312, "マスタ未登録")} -> マスタ未登録 | B51: =IF(AND(C51<>"", COUNTIF('マスタ'!$C:$C, C51)=0), "マスタ未登録", "") -> マスタ未登録 | C51: =D51&D156&E51&F51&G51&H51 -> 経常損益金額 | D51: 経常損益金額 | J51: -40482396 | K51: 5162746 | L51: 3732500 | M51: 24175722 | N51: 24285722 | O51: 24339147 | P51: -18927611 | Q51: -18874186 | R51: -18800111 | S51: -18800111 | T51: -18639840 | U51: -18565131 | V51: -71393549
A52: {=XLOOKUP(C52, 'マスタ'!$C$2:$C$312, 'マスタ'!$D$2:$D$312, "マスタ未登録")} -> マスタ未登録 | B52: =IF(AND(C52<>"", COUNTIF('マスタ'!$C:$C, C52)=0), "マスタ未登録", "") -> マスタ未登録 | C52: =D52&D157&E52&F52&G52&H52 -> 特別利益 | E52: 特別利益 | J52: 0 | K52: 0 | L52: 0 | M52: 0 | N52: 0 | O52: 0 | P52: 0 | Q52: 0 | R52: 0 | S52: 0 | T52: 0 | U52: 0 | V52: 0
A53: {=XLOOKUP(C53, 'マスタ'!$C$2:$C$312, 'マスタ'!$D$2:$D$312, "マスタ未登録")} -> マスタ未登録 | B53: =IF(AND(C53<>"", COUNTIF('マスタ'!$C:$C, C53)=0), "マスタ未登録", "") -> マスタ未登録 | C53: =D53&D158&E53&F53&G53&H53 -> 特別損失 | E53: 特別損失 | J53: 0 | K53: 0 | L53: 0 | M53: 0 | N53: 0 | O53: 0 | P53: 0 | Q53: 0 | R53: 0 | S53: 0 | T53: 0 | U53: 0 | V53: 0
A54: {=XLOOKUP(C54, 'マスタ'!$C$2:$C$312, 'マスタ'!$D$2:$D$312, "マスタ未登録")} -> マスタ未登録 | B54: =IF(AND(C54<>"", COUNTIF('マスタ'!$C:$C, C54)=0), "マスタ未登録", "") -> マスタ未登録 | C54: =D54&D159&E54&F54&G54&H54 -> 固定資産売却損益 | F54: 固定資産売却損益 | J54: 0 | K54: 0 | L54: 0 | M54: 0 | N54: 0 | O54: 0 | P54: 0 | Q54: 0 | R54: 0 | S54: 0 | T54: 0 | U54: 0 | V54: 0
A55: {=XLOOKUP(C55, 'マスタ'!$C$2:$C$312, 'マスタ'!$D$2:$D$312, "マスタ未登録")} -> マスタ未登録 | B55: =IF(AND(C55<>"", COUNTIF('マスタ'!$C:$C, C55)=0), "マスタ未登録", "") -> マスタ未登録 | C55: =D55&D160&E55&F55&G55&H55 -> 税引前当期純損益金額 | D55: 税引前当期純損益金額 | J55: -40482396 | K55: 5162746 | L55: 3732500 | M55: 24175722 | N55: 24285722 | O55: 24339147 | P55: -18927611 | Q55: -18874186 | R55: -18800111 | S55: -18800111 | T55: -18639840 | U55: -18565131 | V55: -71393549
A56: {=XLOOKUP(C56, 'マスタ'!$C$2:$C$312, 'マスタ'!$D$2:$D$312, "マスタ未登録")} -> 法人税等 | B56: =IF(AND(C56<>"", COUNTIF('マスタ'!$C:$C, C56)=0), "マスタ未登録", "") | C56: =D56&D161&E56&F56&G56&H56 -> 法人税等 | E56: 法人税等 | J56: 0 | K56: 0 | L56: 0 | M56: 0 | N56: 0 | O56: 0 | P56: 0 | Q56: 0 | R56: 0 | S56: 0 | T56: 0 | U56: 0 | V56: 0
E57: 法人税等調整額 | J57: 0 | K57: 0 | L57: 0 | M57: 0 | N57: 0 | O57: 0 | P57: 0 | Q57: 0 | R57: 0 | S57: 0 | T57: 0 | U57: 0 | V57: 0
D58: 当期純損益金額 | J58: -40482396 | K58: 5162746 | L58: 3732500 | M58: 24175722 | N58: 24285722 | O58: 24339147 | P58: -18927611 | Q58: -18874186 | R58: -18800111 | S58: -18800111 | T58: -18639840 | U58: -18565131 | V58: -71393549

Sheet YG_PL(M)
A1: PL(M) のコピー | AP1: 28444299
E2: 留意事項 | AP2: -36774467
E3: ・下記FMTでウタイテ連結の事業計画を作成しております
E4: ・47行目以降のハイライト箇所に、別途算定した計画を転記ください | AD4: 26年3月期 | AE4: 26年3月期 | AF4: 26年3月期 | AG4: 26年3月期 | AH4: 26年3月期 | AI4: 26年3月期 | AJ4: 26年3月期 | AK4: 26年3月期 | AL4: 26年3月期 | AM4: 26年3月期 | AN4: 26年3月期 | AO4: 26年3月期 | AP4: 27年3月期 | AQ4: 27年3月期 | AR4: 27年3月期 | AS4: 27年3月期 | AT4: 27年3月期 | AU4: 27年3月期 | AV4: 27年3月期 | AW4: 27年3月期 | AX4: 27年3月期 | AY4: 27年3月期 | AZ4: 27年3月期 | BA4: 27年3月期 | BB4: 28年3月期 | BC4: 28年3月期 | BD4: 28年3月期 | BE4: 28年3月期 | BF4: 28年3月期 | BG4: 28年3月期 | BH4: 28年3月期 | BI4: 28年3月期 | BJ4: 28年3月期 | BK4: 28年3月期 | BL4: 28年3月期 | BM4: 28年3月期 | BN4: 29年3月期 | BO4: 29年3月期 | BP4: 29年3月期 | BQ4: 29年3月期 | BR4: 29年3月期 | BS4: 29年3月期 | BT4: 29年3月期 | BU4: 29年3月期 | BV4: 29年3月期 | BW4: 29年3月期 | BX4: 29年3月期 | BY4: 29年3月期 | BZ4: 30年3月期 | CA4: 30年3月期 | CB4: 30年3月期 | CC4: 30年3月期 | CD4: 30年3月期 | CE4: 30年3月期 | CF4: 30年3月期 | CG4: 30年3月期 | CH4: 30年3月期 | CI4: 30年3月期 | CJ4: 30年3月期 | CK4: 30年3月期
E5: ・28/3月期以降は年次となる場合は、年度の最終月に年間の数値を入力ください | AD5: 1H | AE5: 1H | AF5: 1H | AG5: 1H | AH5: 1H | AI5: 1H | AJ5: 2H | AK5: 2H | AL5: 2H | AM5: 2H | AN5: 2H | AO5: 2H | AP5: 1H | AQ5: 1H | AR5: 1H | AS5: 1H | AT5: 1H | AU5: 1H | AV5: 2H | AW5: 2H | AX5: 2H | AY5: 2H | AZ5: 2H | BA5: 2H | BB5: 1H | BC5: 1H | BD5: 1H | BE5: 1H | BF5: 1H | BG5: 1H | BH5: 2H | BI5: 2H | BJ5: 2H | BK5: 2H | BL5: 2H | BM5: 2H | BN5: 1H | BO5: 1H | BP5: 1H | BQ5: 1H | BR5: 1H | BS5: 1H | BT5: 2H | BU5: 2H | BV5: 2H | BW5: 2H | BX5: 2H | BY5: 2H | BZ5: 1H | CA5: 1H | CB5: 1H | CC5: 1H | CD5: 1H | CE5: 1H | CF5: 2H | CG5: 2H | CH5: 2H | CI5: 2H | CJ5: 2H | CK5: 2H
E6: ・”ウタイテ配賦額”は経営指導料を入力する箇所となりますのでご対応不要です | AD6: 1Q | AE6: 1Q | AF6: 1Q | AG6: 2Q | AH6: 2Q | AI6: 2Q | AJ6: 3Q | AK6: 3Q | AL6: 3Q | AM6: 4Q | AN6: 4Q | AO6: 4Q | AP6: 1Q | AQ6: 1Q | AR6: 1Q | AS6: 2Q | AT6: 2Q | AU6: 2Q | AV6: 3Q | AW6: 3Q | AX6: 3Q | AY6: 4Q | AZ6: 4Q | BA6: 4Q | BB6: 1Q | BC6: 1Q | BD6: 1Q | BE6: 2Q | BF6: 2Q | BG6: 2Q | BH6: 3Q | BI6: 3Q | BJ6: 3Q | BK6: 4Q | BL6: 4Q | BM6: 4Q | BN6: 1Q | BO6: 1Q | BP6: 1Q | BQ6: 2Q | BR6: 2Q | BS6: 2Q | BT6: 3Q | BU6: 3Q | BV6: 3Q | BW6: 4Q | BX6: 4Q | BY6: 4Q | BZ6: 1Q | CA6: 1Q | CB6: 1Q | CC6: 2Q | CD6: 2Q | CE6: 2Q | CF6: 3Q | CG6: 3Q | CH6: 3Q | CI6: 4Q | CJ6: 4Q | CK6: 4Q
AD7: 実績 | AE7: 実績 | AF7: 実績 | AG7: 実績 | AH7: 実績 | AI7: 実績 | AJ7: 実績 | AK7: 実績 | AL7: 実績 | AM7: 実績 | AN7: 実績 | AO7: 予算 | AP7: 実績 | AQ7: 予算 | AR7: 予算 | AS7: 予算 | AT7: 予算 | AU7: 予算 | AV7: 予算 | AW7: 予算 | AX7: 予算 | AY7: 予算 | AZ7: 予算 | BA7: 予算 | BB7: 予算 | BC7: 予算 | BD7: 予算 | BE7: 予算 | BF7: 予算 | BG7: 予算 | BH7: 予算 | BI7: 予算 | BJ7: 予算 | BK7: 予算 | BL7: 予算 | BM7: 予算 | BN7: 予算 | BO7: 予算 | BP7: 予算 | BQ7: 予算 | BR7: 予算 | BS7: 予算 | BT7: 予算 | BU7: 予算 | BV7: 予算 | BW7: 予算 | BX7: 予算 | BY7: 予算 | BZ7: 予算 | CA7: 予算 | CB7: 予算 | CC7: 予算 | CD7: 予算 | CE7: 予算 | CF7: 予算 | CG7: 予算 | CH7: 予算 | CI7: 予算 | CJ7: 予算 | CK7: 予算
H8: Sort | AD8: 25/4月 | AE8: 25/5月 | AF8: 25/6月 | AG8: 25/7月 | AH8: 25/8月 | AI8: 25/9月 | AJ8: 25/10月 | AK8: 25/11月 | AL8: 25/12月 | AM8: 26/1月 | AN8: 26/2月 | AO8: 26/3月 | AP8: 26/4月 | AQ8: 26/5月 | AR8: 26/6月 | AS8: 26/7月 | AT8: 26/8月 | AU8: 26/9月 | AV8: 26/10月 | AW8: 26/11月 | AX8: 26/12月 | AY8: 27/1月 | AZ8: 27/2月 | BA8: 27/3月 | BB8: 27/4月 | BC8: 27/5月 | BD8: 27/6月 | BE8: 27/7月 | BF8: 27/8月 | BG8: 27/9月 | BH8: 27/10月 | BI8: 27/11月 | BJ8: 27/12月 | BK8: 28/1月 | BL8: 28/2月 | BM8: 28/3月 | BN8: 28/4月 | BO8: 28/5月 | BP8: 28/6月 | BQ8: 28/7月 | BR8: 28/8月 | BS8: 28/9月 | BT8: 28/10月 | BU8: 28/11月 | BV8: 28/12月 | BW8: 29/1月 | BX8: 29/2月 | BY8: 29/3月 | BZ8: 29/4月 | CA8: 29/5月 | CB8: 29/6月 | CC8: 29/7月 | CD8: 29/8月 | CE8: 29/9月 | CF8: 29/10月 | CG8: 29/11月 | CH8: 29/12月 | CI8: 30/1月 | CJ8: 30/2月 | CK8: 30/3月 | CM8: 集計
A9: X | E9: 売上高 | F9: - | H9: 1 | I9: YOANI | J9: ALL | AP9: 0 | AQ9: 0 | AR9: 0 | AS9: 0 | AT9: 0 | AU9: 0 | AV9: 0 | AW9: 0 | AX9: 0 | AY9: 0 | AZ9: 0 | BA9: 0 | BB9: 0 | BC9: 0 | BD9: 0 | BE9: 0 | BF9: 0 | BG9: 0 | BH9: 0 | BI9: 0 | BJ9: 0 | BK9: 0 | BL9: 0 | BM9: 0 | BN9: 0 | BO9: 0 | BP9: 0 | BQ9: 0 | BR9: 0 | BS9: 0 | BT9: 0 | BU9: 0 | BV9: 0 | BW9: 0 | BX9: 0 | BY9: 0 | BZ9: 0 | CA9: 0 | CB9: 0 | CC9: 0 | CD9: 0 | CE9: 0 | CF9: 0 | CG9: 0 | CH9: 0 | CI9: 0 | CJ9: 0 | CK9: 0 | CM9: 売上高
E10: 変動費 | F10: 仕入高 | I10: YOANI | J10: ALL | AP10: 0 | AQ10: 0 | AR10: 0 | AS10: 0 | AT10: 0 | AU10: 0 | AV10: 0 | AW10: 0 | AX10: 0 | AY10: 0 | AZ10: 0 | BA10: 0 | BB10: 0 | BC10: 0 | BD10: 0 | BE10: 0 | BF10: 0 | BG10: 0 | BH10: 0 | BI10: 0 | BJ10: 0 | BK10: 0 | BL10: 0 | BM10: 0 | BN10: 0 | BO10: 0 | BP10: 0 | BQ10: 0 | BR10: 0 | BS10: 0 | BT10: 0 | BU10: 0 | BV10: 0 | BW10: 0 | BX10: 0 | BY10: 0 | BZ10: 0 | CA10: 0 | CB10: 0 | CC10: 0 | CD10: 0 | CE10: 0 | CF10: 0 | CG10: 0 | CH10: 0 | CI10: 0 | CJ10: 0 | CK10: 0 | CM10: 仕入高
E11: 変動費 | F11: 外注費 | I11: YOANI | J11: ALL | AP11: 0 | AQ11: 0 | AR11: 0 | AS11: 0 | AT11: 0 | AU11: 0 | AV11: 0 | AW11: 0 | AX11: 0 | AY11: 0 | AZ11: 0 | BA11: 0 | BB11: 0 | BC11: 0 | BD11: 0 | BE11: 0 | BF11: 0 | BG11: 0 | BH11: 0 | BI11: 0 | BJ11: 0 | BK11: 0 | BL11: 0 | BM11: 0 | BN11: 0 | BO11: 0 | BP11: 0 | BQ11: 0 | BR11: 0 | BS11: 0 | BT11: 0 | BU11: 0 | BV11: 0 | BW11: 0 | BX11: 0 | BY11: 0 | BZ11: 0 | CA11: 0 | CB11: 0 | CC11: 0 | CD11: 0 | CE11: 0 | CF11: 0 | CG11: 0 | CH11: 0 | CI11: 0 | CJ11: 0 | CK11: 0 | CM11: 外注費
E12: 変動費 | F12: 荷造運賃 | I12: YOANI | J12: ALL | AP12: 0 | AQ12: 0 | AR12: 0 | AS12: 0 | AT12: 0 | AU12: 0 | AV12: 0 | AW12: 0 | AX12: 0 | AY12: 0 | AZ12: 0 | BA12: 0 | BB12: 0 | BC12: 0 | BD12: 0 | BE12: 0 | BF12: 0 | BG12: 0 | BH12: 0 | BI12: 0 | BJ12: 0 | BK12: 0 | BL12: 0 | BM12: 0 | BN12: 0 | BO12: 0 | BP12: 0 | BQ12: 0 | BR12: 0 | BS12: 0 | BT12: 0 | BU12: 0 | BV12: 0 | BW12: 0 | BX12: 0 | BY12: 0 | BZ12: 0 | CA12: 0 | CB12: 0 | CC12: 0 | CD12: 0 | CE12: 0 | CF12: 0 | CG12: 0 | CH12: 0 | CI12: 0 | CJ12: 0 | CK12: 0 | CM12: 荷造運賃
E13: 変動費 | F13: 支払手数料 | I13: YOANI | J13: ALL | AP13: 0 | AQ13: 0 | AR13: 0 | AS13: 0 | AT13: 0 | AU13: 0 | AV13: 0 | AW13: 0 | AX13: 0 | AY13: 0 | AZ13: 0 | BA13: 0 | BB13: 0 | BC13: 0 | BD13: 0 | BE13: 0 | BF13: 0 | BG13: 0 | BH13: 0 | BI13: 0 | BJ13: 0 | BK13: 0 | BL13: 0 | BM13: 0 | BN13: 0 | BO13: 0 | BP13: 0 | BQ13: 0 | BR13: 0 | BS13: 0 | BT13: 0 | BU13: 0 | BV13: 0 | BW13: 0 | BX13: 0 | BY13: 0 | BZ13: 0 | CA13: 0 | CB13: 0 | CC13: 0 | CD13: 0 | CE13: 0 | CF13: 0 | CG13: 0 | CH13: 0 | CI13: 0 | CJ13: 0 | CK13: 0 | CM13: 支払手数料
E14: 変動費 | F14: 保険料 | I14: YOANI | J14: ALL | AP14: 0 | AQ14: 0 | AR14: 0 | AS14: 0 | AT14: 0 | AU14: 0 | AV14: 0 | AW14: 0 | AX14: 0 | AY14: 0 | AZ14: 0 | BA14: 0 | BB14: 0 | BC14: 0 | BD14: 0 | BE14: 0 | BF14: 0 | BG14: 0 | BH14: 0 | BI14: 0 | BJ14: 0 | BK14: 0 | BL14: 0 | BM14: 0 | BN14: 0 | BO14: 0 | BP14: 0 | BQ14: 0 | BR14: 0 | BS14: 0 | BT14: 0 | BU14: 0 | BV14: 0 | BW14: 0 | BX14: 0 | BY14: 0 | BZ14: 0 | CA14: 0 | CB14: 0 | CC14: 0 | CD14: 0 | CE14: 0 | CF14: 0 | CG14: 0 | CH14: 0 | CI14: 0 | CJ14: 0 | CK14: 0 | CM14: 保険料
E15: 準変動費 | F15: 広告宣伝費 | I15: YOANI | J15: ALL | AP15: 0 | AQ15: 0 | AR15: 0 | AS15: 0 | AT15: 0 | AU15: 0 | AV15: 0 | AW15: 0 | AX15: 0 | AY15: 0 | AZ15: 0 | BA15: 0 | BB15: 0 | BC15: 0 | BD15: 0 | BE15: 0 | BF15: 0 | BG15: 0 | BH15: 0 | BI15: 0 | BJ15: 0 | BK15: 0 | BL15: 0 | BM15: 0 | BN15: 0 | BO15: 0 | BP15: 0 | BQ15: 0 | BR15: 0 | BS15: 0 | BT15: 0 | BU15: 0 | BV15: 0 | BW15: 0 | BX15: 0 | BY15: 0 | BZ15: 0 | CA15: 0 | CB15: 0 | CC15: 0 | CD15: 0 | CE15: 0 | CF15: 0 | CG15: 0 | CH15: 0 | CI15: 0 | CJ15: 0 | CK15: 0 | CM15: 広告宣伝費
E16: 準変動費 | F16: その他 | I16: YOANI | J16: ALL | AP16: 0 | AQ16: 0 | AR16: 0 | AS16: 0 | AT16: 0 | AU16: 0 | AV16: 0 | AW16: 0 | AX16: 0 | AY16: 0 | AZ16: 0 | BA16: 0 | BB16: 0 | BC16: 0 | BD16: 0 | BE16: 0 | BF16: 0 | BG16: 0 | BH16: 0 | BI16: 0 | BJ16: 0 | BK16: 0 | BL16: 0 | BM16: 0 | BN16: 0 | BO16: 0 | BP16: 0 | BQ16: 0 | BR16: 0 | BS16: 0 | BT16: 0 | BU16: 0 | BV16: 0 | BW16: 0 | BX16: 0 | BY16: 0 | BZ16: 0 | CA16: 0 | CB16: 0 | CC16: 0 | CD16: 0 | CE16: 0 | CF16: 0 | CG16: 0 | CH16: 0 | CI16: 0 | CJ16: 0 | CK16: 0 | CM16: その他
E17: 準変動費 | F17: タレント報酬 | I17: YOANI | J17: ALL | AP17: 0 | AQ17: 0 | AR17: 0 | AS17: 0 | AT17: 0 | AU17: 0 | AV17: 0 | AW17: 0 | AX17: 0 | AY17: 0 | AZ17: 0 | BA17: 0 | BB17: 0 | BC17: 0 | BD17: 0 | BE17: 0 | BF17: 0 | BG17: 0 | BH17: 0 | BI17: 0 | BJ17: 0 | BK17: 0 | BL17: 0 | BM17: 0 | BN17: 0 | BO17: 0 | BP17: 0 | BQ17: 0 | BR17: 0 | BS17: 0 | BT17: 0 | BU17: 0 | BV17: 0 | BW17: 0 | BX17: 0 | BY17: 0 | BZ17: 0 | CA17: 0 | CB17: 0 | CC17: 0 | CD17: 0 | CE17: 0 | CF17: 0 | CG17: 0 | CH17: 0 | CI17: 0 | CJ17: 0 | CK17: 0 | CM17: タレント報酬
E18: 準変動費 | F18: 人件費 | I18: YOANI | J18: ALL | AP18: 0 | AQ18: 0 | AR18: 0 | AS18: 0 | AT18: 0 | AU18: 0 | AV18: 0 | AW18: 0 | AX18: 0 | AY18: 0 | AZ18: 0 | BA18: 0 | BB18: 0 | BC18: 0 | BD18: 0 | BE18: 0 | BF18: 0 | BG18: 0 | BH18: 0 | BI18: 0 | BJ18: 0 | BK18: 0 | BL18: 0 | BM18: 0 | BN18: 0 | BO18: 0 | BP18: 0 | BQ18: 0 | BR18: 0 | BS18: 0 | BT18: 0 | BU18: 0 | BV18: 0 | BW18: 0 | BX18: 0 | BY18: 0 | BZ18: 0 | CA18: 0 | CB18: 0 | CC18: 0 | CD18: 0 | CE18: 0 | CF18: 0 | CG18: 0 | CH18: 0 | CI18: 0 | CJ18: 0 | CK18: 0 | CM18: 人件費
E19: 準変動費 | F19: 採用教育費 | I19: YOANI | J19: ALL | AP19: 0 | AQ19: 0 | AR19: 0 | AS19: 0 | AT19: 0 | AU19: 0 | AV19: 0 | AW19: 0 | AX19: 0 | AY19: 0 | AZ19: 0 | BA19: 0 | BB19: 0 | BC19: 0 | BD19: 0 | BE19: 0 | BF19: 0 | BG19: 0 | BH19: 0 | BI19: 0 | BJ19: 0 | BK19: 0 | BL19: 0 | BM19: 0 | BN19: 0 | BO19: 0 | BP19: 0 | BQ19: 0 | BR19: 0 | BS19: 0 | BT19: 0 | BU19: 0 | BV19: 0 | BW19: 0 | BX19: 0 | BY19: 0 | BZ19: 0 | CA19: 0 | CB19: 0 | CC19: 0 | CD19: 0 | CE19: 0 | CF19: 0 | CG19: 0 | CH19: 0 | CI19: 0 | CJ19: 0 | CK19: 0 | CM19: 採用教育費
E20: 固定費 | F20: 共通費配賦 | I20: YOANI | J20: ALL | AP20: 0 | AQ20: 0 | AR20: 0 | AS20: 0 | AT20: 0 | AU20: 0 | AV20: 0 | AW20: 0 | AX20: 0 | AY20: 0 | AZ20: 0 | BA20: 0 | BB20: 0 | BC20: 0 | BD20: 0 | BE20: 0 | BF20: 0 | BG20: 0 | BH20: 0 | BI20: 0 | BJ20: 0 | BK20: 0 | BL20: 0 | BM20: 0 | BN20: 0 | BO20: 0 | BP20: 0 | BQ20: 0 | BR20: 0 | BS20: 0 | BT20: 0 | BU20: 0 | BV20: 0 | BW20: 0 | BX20: 0 | BY20: 0 | BZ20: 0 | CA20: 0 | CB20: 0 | CC20: 0 | CD20: 0 | CE20: 0 | CF20: 0 | CG20: 0 | CH20: 0 | CI20: 0 | CJ20: 0 | CK20: 0 | CM20: 共通費配賦
E21: 固定費 | F21: 地代家賃 | I21: YOANI | J21: ALL | AP21: 0 | AQ21: 0 | AR21: 0 | AS21: 0 | AT21: 0 | AU21: 0 | AV21: 0 | AW21: 0 | AX21: 0 | AY21: 0 | AZ21: 0 | BA21: 0 | BB21: 0 | BC21: 0 | BD21: 0 | BE21: 0 | BF21: 0 | BG21: 0 | BH21: 0 | BI21: 0 | BJ21: 0 | BK21: 0 | BL21: 0 | BM21: 0 | BN21: 0 | BO21: 0 | BP21: 0 | BQ21: 0 | BR21: 0 | BS21: 0 | BT21: 0 | BU21: 0 | BV21: 0 | BW21: 0 | BX21: 0 | BY21: 0 | BZ21: 0 | CA21: 0 | CB21: 0 | CC21: 0 | CD21: 0 | CE21: 0 | CF21: 0 | CG21: 0 | CH21: 0 | CI21: 0 | CJ21: 0 | CK21: 0 | CM21: 地代家賃
... E34: 固定費 | F34: ウタイテ配賦額 | I34: YOANI | J34: ALL | AP34: 0 | AQ34: 0 | AR34: 0 | AS34: 0 | AT34: 0 | AU34: 0 | AV34: 0 | AW34: 0 | AX34: 0 | AY34: 0 | AZ34: 0 | BA34: 0 | BB34: 0 | BC34: 0 | BD34: 0 | BE34: 0 | BF34: 0 | BG34: 0 | BH34: 0 | BI34: 0 | BJ34: 0 | BK34: 0 | BL34: 0 | BM34: 0 | BN34: 0 | BO34: 0 | BP34: 0 | BQ34: 0 | BR34: 0 | BS34: 0 | BT34: 0 | BU34: 0 | BV34: 0 | BW34: 0 | BX34: 0 | BY34: 0 | BZ34: 0 | CA34: 0 | CB34: 0 | CC34: 0 | CD34: 0 | CE34: 0 | CF34: 0 | CG34: 0 | CH34: 0 | CI34: 0 | CJ34: 0 | CK34: 0 | CM34: ウタイテ配賦額
E36: 営業利益 | H36: 1 | I36: YOANI | J36: ALL | AD36: 0 | AE36: 0 | AF36: 0 | AG36: 0 | AH36: 0 | AI36: 0 | AJ36: 0 | AK36: 0 | AL36: 0 | AM36: 0 | AN36: 0 | AO36: 0 | AP36: 0 | AQ36: 0 | AR36: 0 | AS36: 0 | AT36: 0 | AU36: 0 | AV36: 0 | AW36: 0 | AX36: 0 | AY36: 0 | AZ36: 0 | BA36: 0 | BB36: 0 | BC36: 0 | BD36: 0 | BE36: 0 | BF36: 0 | BG36: 0 | BH36: 0 | BI36: 0 | BJ36: 0 | BK36: 0 | BL36: 0 | BM36: 0 | BN36: 0 | BO36: 0 | BP36: 0 | BQ36: 0 | BR36: 0 | BS36: 0 | BT36: 0 | BU36: 0 | BV36: 0 | BW36: 0 | BX36: 0 | BY36: 0 | BZ36: 0 | CA36: 0 | CB36: 0 | CC36: 0 | CD36: 0 | CE36: 0 | CF36: 0 | CG36: 0 | CH36: 0 | CI36: 0 | CJ36: 0 | CK36: 0
E37: 営業外収益 | F37: - | I37: YOANI | J37: ALL
E38: 営業外収益 | F38: - | I38: YOANI | J38: ALL
E39: 特別利益 | F39: - | I39: YOANI | J39: ALL
E40: 特別損失 | F40: - | I40: YOANI | J40: ALL
E41: 法人税等 | F41: - | I41: YOANI | J41: ALL
E42: 法人税等調整額 | F42: - | I42: YOANI | J42: ALL
E43: 当期純利益 | I43: YOANI | J43: ALL | AP43: 0 | AQ43: 0 | AR43: 0 | AS43: 0 | AT43: 0 | AU43: 0 | AV43: 0 | AW43: 0 | AX43: 0 | AY43: 0 | AZ43: 0 | BA43: 0 | BB43: 0 | BC43: 0 | BD43: 0 | BE43: 0 | BF43: 0 | BG43: 0 | BH43: 0 | BI43: 0 | BJ43: 0 | BK43: 0 | BL43: 0 | BM43: 0 | BN43: 0 | BO43: 0 | BP43: 0 | BQ43: 0 | BR43: 0 | BS43: 0 | BT43: 0 | BU43: 0 | BV43: 0 | BW43: 0 | BX43: 0 | BY43: 0 | BZ43: 0 | CA43: 0 | CB43: 0 | CC43: 0 | CD43: 0 | CE43: 0 | CF43: 0 | CG43: 0 | CH43: 0 | CI43: 0 | CJ43: 0 | CK43: 0
B44: 補助列 | C44: ②マスタ結びつけ | D44: ①
H46: 1
B47: {=XLOOKUP(D47, 'マスタ'!$C$2:$C$1000, 'マスタ'!$D$2:$D$1000, "マスタ未登録")} -> 売上高 | C47: =IF(AND(D47<>"", COUNTIF('マスタ'!$C:$C, D47)=0), "マスタ未登録", "") | D47: =F47 -> 売上高 | E47: 売上高 | F47: 売上高 | H47: 1 | I47: YOANI | J47: 教育 | AD47: 296871389 | AE47: 272456691 | AF47: 267326019 | AG47: 265471022 | AH47: 266436263 | AI47: 271947067 | AJ47: 264563154 | AK47: 264405743 | AL47: 271514056 | AM47: 264967685 | AN47: 265297276 | AO47: 288600861 | AP47: 274897527 | AQ47: 274492845 | AR47: 264523861 | AS47: 255898325 | AT47: 256871049 | AU47: 264602714 | AV47: 253501668 | AW47: 254037604 | AX47: 255058656 | AY47: 254518036 | AZ47: 254893626 | BA47: 272121852 | CM47: 売上高
B48: {=XLOOKUP(D48, 'マスタ'!$C$2:$C$1000, 'マスタ'!$D$2:$D$1000, "マスタ未登録")} -> 当期商品仕入高 | C48: =IF(AND(D48<>"", COUNTIF('マスタ'!$C:$C, D48)=0), "マスタ未登録", "") | D48: =F48 -> 仕入高 | E48: 変動費 | F48: 仕入高 | I48: YOANI | J48: 教育 | AD48: -18163675 | AE48: -512673 | AF48: -570122 | AG48: -521683 | AH48: -1096110 | AI48: -427596 | AJ48: -466100 | AK48: 0 | AL48: 0 | AM48: -2816523 | AN48: -12699 | AO48: -4241810 | AP48: -20886815 | AQ48: -110000 | AR48: -280000 | AS48: -922200 | AT48: -843000 | AU48: -1626346 | AV48: -4000000 | AW48: 0 | AX48: -2000000 | AY48: 0 | AZ48: 0 | BA48: 0 | CM48: 仕入高
B49: {=XLOOKUP(D49, 'マスタ'!$C$2:$C$1000, 'マスタ'!$D$2:$D$1000, "マスタ未登録")} -> 外注費 | C49: =IF(AND(D49<>"", COUNTIF('マスタ'!$C:$C, D49)=0), "マスタ未登録", "") | D49: =F49 -> 外注費 | E49: 変動費 | F49: 外注費 | I49: YOANI | J49: 教育 | AD49: -25458188 | AE49: -32906723 | AF49: -32397971 | AG49: -28112283 | AH49: -17214188 | AI49: -25815330 | AJ49: -34137291 | AK49: -33442240 | AL49: -30494279 | AM49: -24470263 | AN49: -25435271 | AO49: -16211713 | AP49: -26185502 | AQ49: -25778170 | AR49: -28177410 | AS49: -25677255 | AT49: -19180474 | AU49: -21240287 | AV49: -28291389 | AW49: -28026400 | AX49: -28658094 | AY49: -21446984 | AZ49: -23243028 | BA49: -10798206 | CM49: 外注費
B50: {=XLOOKUP(D50, 'マスタ'!$C$2:$C$1000, 'マスタ'!$D$2:$D$1000, "マスタ未登録")} -> 荷造運賃 | C50: =IF(AND(D50<>"", COUNTIF('マスタ'!$C:$C, D50)=0), "マスタ未登録", "") | D50: =F50 -> 荷造運賃 | E50: 変動費 | F50: 荷造運賃 | I50: YOANI | J50: 教育 | AD50: -280865 | AE50: -266998 | AF50: -188754 | AG50: -343183 | AH50: -153943 | AI50: -146868 | AJ50: -150097 | AK50: -99671 | AL50: -211161 | AM50: -323779 | AN50: -272691 | AO50: -409224 | AP50: -247405 | AQ50: -285180 | AR50: -218969 | AS50: -237399 | AT50: -152512 | AU50: -204805 | AV50: -146347 | AW50: -130869 | AX50: -215970 | AY50: -284828 | AZ50: -203170 | BA50: -197634 | CM50: 荷造運賃
B51: {=XLOOKUP(D51, 'マスタ'!$C$2:$C$1000, 'マスタ'!$D$2:$D$1000, "マスタ未登録")} -> 支払手数料 | C51: =IF(AND(D51<>"", COUNTIF('マスタ'!$C:$C, D51)=0), "マスタ未登録", "") | D51: =F51 -> 支払手数料 | E51: 変動費 | F51: 支払手数料 | I51: YOANI | J51: 教育 | AD51: -262935 | AE51: -286121 | AF51: -254147 | AG51: -230125 | AH51: -315764 | AI51: -320245 | AJ51: -229760 | AK51: -1728704 | AL51: -2913841 | AM51: 1031916 | AN51: -445982 | AO51: 941363 | AP51: -255162 | AQ51: -224550 | AR51: -224550 | AS51: -224550 | AT51: -224550 | AU51: -224550 | AV51: -224550 | AW51: -224550 | AX51: -224550 | AY51: -224550 | AZ51: -224550 | BA51: -224550 | CM51: 支払手数料
B52: {=XLOOKUP(D52, 'マスタ'!$C$2:$C$1000, 'マスタ'!$D$2:$D$1000, "マスタ未登録")} -> 保険料 | C52: =IF(AND(D52<>"", COUNTIF('マスタ'!$C:$C, D52)=0), "マスタ未登録", "") | D52: =F52 -> 保険料 | E52: 変動費 | F52: 保険料 | I52: YOANI | J52: 教育 | AD52: -1039587 | AE52: -1038723 | AF52: -1039583 | AG52: -1065604 | AH52: -1045113 | AI52: -1045603 | AJ52: -1287943 | AK52: -1057233 | AL52: -1169973 | AM52: -1057583 | AN52: -1039583 | AO52: -1039583 | AP52: -1039587 | AQ52: -1039583 | AR52: -1039583 | AS52: -1039583 | AT52: -1039583 | AU52: -1039583 | AV52: -1039583 | AW52: -1039583 | AX52: -1039583 | AY52: -1039583 | AZ52: -1039583 | BA52: -1039583 | CM52: 保険料
B53: {=XLOOKUP(D53, 'マスタ'!$C$2:$C$1000, 'マスタ'!$D$2:$D$1000, "マスタ未登録")} -> 広告宣伝費 | C53: =IF(AND(D53<>"", COUNTIF('マスタ'!$C:$C, D53)=0), "マスタ未登録", "") | D53: =F53 -> 広告宣伝費 | E53: 準変動費 | F53: 広告宣伝費 | I53: YOANI | J53: 教育 | AD53: -63471142 | AE53: -62040319 | AF53: -75533817 | AG53: -88887280 | AH53: -80417496 | AI53: -48528184 | AJ53: -52450852 | AK53: -44125455 | AL53: -44020295 | AM53: -52143004 | AN53: -122333431 | AO53: -79537168 | AP53: -48303471 | AQ53: -41723670 | AR53: -41910955 | AS53: -45367005 | AT53: -37452174 | AU53: -37123992 | AV53: -35568128 | AW53: -36633492 | AX53: -38640879 | AY53: -40595115 | AZ53: -59367818 | BA53: -24117200 | CM53: 広告宣伝費
B54: {=XLOOKUP(D54, 'マスタ'!$C$2:$C$1000, 'マスタ'!$D$2:$D$1000, "マスタ未登録")} -> その他 | C54: =IF(AND(D54<>"", COUNTIF('マスタ'!$C:$C, D54)=0), "マスタ未登録", "") | D54: =F54 -> その他（変） | E54: 準変動費 | F54: その他（変） | I54: YOANI | J54: 教育 | AD54: 0 | AE54: 0 | AF54: 0 | AG54: 0 | AH54: 0 | AI54: 0 | AJ54: 0 | AK54: 0 | AL54: 0 | AM54: 0 | AN54: 0 | AO54: 0 | AP54: 0 | AQ54: 0 | AR54: 0 | AS54: 0 | AT54: 0 | AU54: 0 | AV54: 0 | AW54: 0 | AX54: 0 | AY54: 0 | AZ54: 0 | BA54: 0 | CM54: その他_準変動
B55: {=XLOOKUP(D55, 'マスタ'!$C$2:$C$1000, 'マスタ'!$D$2:$D$1000, "マスタ未登録")} -> 当期商品仕入高 | C55: =IF(AND(D55<>"", COUNTIF('マスタ'!$C:$C, D55)=0), "マスタ未登録", "") | D55: =F55 -> タレント報酬 | E55: 準変動費 | F55: タレント報酬 | I55: YOANI | J55: 教育 | AD55: 0 | AE55: 0 | AF55: 0 | AG55: 0 | AH55: 0 | AI55: 0 | AJ55: 0 | AK55: 0 | AL55: 0 | AM55: 0 | AN55: 0 | AO55: 0 | AP55: 0 | AQ55: -349500 | AR55: -349500 | AS55: -349500 | AT55: -349500 | AU55: -349500 | AV55: -349500 | AW55: -349500 | AX55: -349500 | AY55: -349500 | AZ55: -349500 | BA55: -298500 | CM55: タレント報酬
B56: {=XLOOKUP(D56, 'マスタ'!$C$2:$C$1000, 'マスタ'!$D$2:$D$1000, "マスタ未登録")} -> 当期商品仕入高 | C56: =IF(AND(D56<>"", COUNTIF('マスタ'!$C:$C, D56)=0), "マスタ未登録", "") | D56: =F56 -> 人件費 | E56: 準変動費 | F56: 人件費 | I56: YOANI | J56: 教育 | AD56: -71256696 | AE56: -68027168 | AF56: -68357731 | AG56: -67999945 | AH56: -67966506 | AI56: -68488371 | AJ56: -71422464 | AK56: -72082532 | AL56: -70316640 | AM56: -71010384 | AN56: -72803550 | AO56: -75233138 | AP56: -74288318 | AQ56: -74231739 | AR56: -74806091 | AS56: -72733517 | AT56: -73144209 | AU56: -74491113 | AV56: -77206130 | AW56: -76884076 | AX56: -76985380 | AY56: -76499131 | AZ56: -77199611 | BA56: -77159837 | CM56: 人件費
B57: {=XLOOKUP(D57, 'マスタ'!$C$2:$C$1000, 'マスタ'!$D$2:$D$1000, "マスタ未登録")} -> 採用教育費 | C57: =IF(AND(D57<>"", COUNTIF('マスタ'!$C:$C, D57)=0), "マスタ未登録", "") | D57: =F57 -> 採用教育費 | E57: 準変動費 | F57: 採用教育費 | I57: YOANI | J57: 教育 | AD57: 0 | AE57: 0 | AF57: 0 | AG57: 0 | AH57: 0 | AI57: 0 | AJ57: 0 | AK57: 0 | AL57: 0 | AM57: 0 | AN57: 0 | AO57: 0 | AP57: 0 | AQ57: 0 | AR57: 0 | AS57: 0 | AT57: 0 | AU57: 0 | AV57: 0 | AW57: 0 | AX57: 0 | AY57: 0 | AZ57: 0 | BA57: 0 | CM57: 採用教育費
B58: {=XLOOKUP(D58, 'マスタ'!$C$2:$C$1000, 'マスタ'!$D$2:$D$1000, "マスタ未登録")} -> 共通費配賦 | C58: =IF(AND(D58<>"", COUNTIF('マスタ'!$C:$C, D58)=0), "マスタ未登録", "") | D58: =F58 -> 共通費配賦 | E58: 固定費 | F58: 共通費配賦 | I58: YOANI | J58: 教育 | AD58: 0 | AE58: 0 | AF58: 0 | AG58: 0 | AH58: 0 | AI58: 0 | AJ58: 0 | AK58: 0 | AL58: 0 | AM58: 0 | AN58: 0 | AO58: 0 | AP58: 0 | AQ58: 0 | AR58: 0 | AS58: 0 | AT58: 0 | AU58: 0 | AV58: 0 | AW58: 0 | AX58: 0 | AY58: 0 | AZ58: 0 | BA58: 0 | CM58: 共通費配賦
B59: {=XLOOKUP(D59, 'マスタ'!$C$2:$C$1000, 'マスタ'!$D$2:$D$1000, "マスタ未登録")} -> 地代家賃 | C59: =IF(AND(D59<>"", COUNTIF('マスタ'!$C:$C, D59)=0), "マスタ未登録", "") | D59: =F59 -> 地代家賃 | E59: 固定費 | F59: 地代家賃 | I59: YOANI | J59: 教育 | AD59: -44452731 | AE59: -44525631 | AF59: -44604431 | AG59: -44624721 | AH59: -44674401 | AI59: -46030166 | AJ59: -46038024 | AK59: -46145175 | AL59: -46147675 | AM59: -50290485 | AN59: -50936724 | AO59: -50886024 | AP59: -47108546 | AQ59: -47132846 | AR59: -47132846 | AS59: -47132846 | AT59: -47132846 | AU59: -47132846 | AV59: -47132846 | AW59: -47132846 | AX59: -47132846 | AY59: -47132846 | AZ59: -47132846 | BA59: -47132846 | CM59: 地代家賃
... B71: {=XLOOKUP(D71, 'マスタ'!$C$2:$C$1000, 'マスタ'!$D$2:$D$1000, "マスタ未登録")} -> 雑費 | C71: =IF(AND(D71<>"", COUNTIF('マスタ'!$C:$C, D71)=0), "マスタ未登録", "") | D71: =F71 -> その他（固） | E71: 固定費 | F71: その他（固） | I71: YOANI | J71: 教育 | AD71: -31950257 | AE71: -17209488 | AF71: -29279080 | AG71: -30654710 | AH71: -26207078 | AI71: -28065302 | AJ71: -17566244 | AK71: -14410310 | AL71: -31657880 | AM71: -24365737 | AN71: -24381524 | AO71: -51042431 | AP71: -25909169 | AQ71: -23083579 | AR71: -24452911 | AS71: -31177428 | AT71: -27023047 | AU71: -16921771 | AV71: -17575938 | AW71: -17036489 | AX71: -22907282 | AY71: -14842092 | AZ71: -39538471 | BA71: -42074883 | CM71: その他_固定
B72: {=XLOOKUP(D72, 'マスタ'!$C$2:$C$1000, 'マスタ'!$D$2:$D$1000, "マスタ未登録")} -> マスタ未登録 | C72: =IF(AND(D72<>"", COUNTIF('マスタ'!$C:$C, D72)=0), "マスタ未登録", "") -> マスタ未登録 | D72: =F72 -> ウタイテ配賦額 | E72: 固定費 | F72: ウタイテ配賦額 | I72: YOANI | J72: 教育 | CM72: ウタイテ配賦額
B73: {=XLOOKUP(D73, 'マスタ'!$C$2:$C$1000, 'マスタ'!$D$2:$D$1000, "マスタ未登録")} -> マスタ未登録 | C73: =IF(AND(D73<>"", COUNTIF('マスタ'!$C:$C, D73)=0), "マスタ未登録", "") | D73: =F73 | J73: 教育
B74: {=XLOOKUP(D74, 'マスタ'!$C$2:$C$1000, 'マスタ'!$D$2:$D$1000, "マスタ未登録")} -> マスタ未登録 | C74: =IF(AND(D74<>"", COUNTIF('マスタ'!$C:$C, D74)=0), "マスタ未登録", "") | D74: =F74 | E74: 営業利益 | H74: 1 | I74: YOANI | J74: 教育 | AD74: -1354682 | AE74: 4899008 | AF74: -24352787 | AG74: -39885550 | AH74: -16892795 | AI74: 10630065 | AJ74: -2020077 | AK74: 6714374 | AL74: -2210616 | AM74: -3504431 | AN74: -79110764 | AO74: -76664425 | AP74: -8330168 | AQ74: 27189965 | AR74: 11112057 | AS74: -4270299 | AT74: 14694260 | AU74: 25451076 | AV74: 5943281 | AW74: 8990234 | AX74: -1750362 | AY74: 15416430 | AZ74: -31564452 | BA74: 28684677 | BB74: 0 | BC74: 0 | BD74: 0 | BE74: 0 | BF74: 0 | BG74: 0 | BH74: 0 | BI74: 0 | BJ74: 0 | BK74: 0 | BL74: 0 | BM74: 0 | BN74: 0 | BO74: 0 | BP74: 0 | BQ74: 0 | BR74: 0 | BS74: 0 | BT74: 0 | BU74: 0 | BV74: 0 | BW74: 0 | BX74: 0 | BY74: 0 | BZ74: 0 | CA74: 0 | CB74: 0 | CC74: 0 | CD74: 0 | CE74: 0 | CF74: 0 | CG74: 0 | CH74: 0 | CI74: 0 | CJ74: 0 | CK74: 0 | CM74: 91566699 | CN74: -223752680
B75: {=XLOOKUP(D75, 'マスタ'!$C$2:$C$1000, 'マスタ'!$D$2:$D$1000, "マスタ未登録")} -> マスタ未登録 | C75: =IF(AND(D75<>"", COUNTIF('マスタ'!$C:$C, D75)=0), "マスタ未登録", "") | D75: =F75 | H75: 1
B76: {=XLOOKUP(D76, 'マスタ'!$C$2:$C$1000, 'マスタ'!$D$2:$D$1000, "マスタ未登録")} -> 売上高 | C76: =IF(AND(D76<>"", COUNTIF('マスタ'!$C:$C, D76)=0), "マスタ未登録", "") | D76: =E76 -> 売上高 | E76: 売上高 | F76: - | H76: 1 | I76: YOANI | J76: エンタメ | AD76: 269610004 | AE76: 434900477 | AF76: 453827169 | AG76: 760452518 | AH76: 264534670 | AI76: 866106639 | AJ76: 507137645 | AK76: 1363748508 | AL76: 574462007 | AM76: 231931925 | AN76: 712994918 | AO76: 597162861 | AP76: 1442655107 | AQ76: 683240007 | AR76: 2221837739 | AS76: 484825841 | AT76: 397433565 | AU76: 627896579 | AV76: 222313896 | AW76: 395228124 | AX76: 481144275 | AY76: 1404818023 | AZ76: 629900175 | BA76: 524553859 | CM76: 売上高
B77: {=XLOOKUP(D77, 'マスタ'!$C$2:$C$1000, 'マスタ'!$D$2:$D$1000, "マスタ未登録")} -> 当期商品仕入高 | C77: =IF(AND(D77<>"", COUNTIF('マスタ'!$C:$C, D77)=0), "マスタ未登録", "") | D77: =F77 -> 仕入高 | E77: 変動費 | F77: 仕入高 | I77: YOANI | J77: エンタメ | AD77: -13254252 | AE77: -9030196 | AF77: -10505118 | AG77: -10798181 | AH77: -19305675 | AI77: -9081731 | AJ77: -17159741 | AK77: -12085474 | AL77: -10648534 | AM77: -10650820 | AN77: -18431999 | AO77: -21910372 | AP77: -42107977 | AQ77: -16070242 | AR77: -63161028 | AS77: -10318560 | AT77: -11306087 | AU77: -17172518 | AV77: -7581919 | AW77: -9110417 | AX77: -10888091 | AY77: -35697304 | AZ77: -12060655 | BA77: -11773259 | CM77: 仕入高
B78: {=XLOOKUP(D78, 'マスタ'!$C$2:$C$1000, 'マスタ'!$D$2:$D$1000, "マスタ未登録")} -> 外注費 | C78: =IF(AND(D78<>"", COUNTIF('マスタ'!$C:$C, D78)=0), "マスタ未登録", "") | D78: =F78 -> 外注費 | E78: 変動費 | F78: 外注費 | I78: YOANI | J78: エンタメ | AD78: -130512976 | AE78: -204428088 | AF78: -238097734 | AG78: -426781601 | AH78: -61111254 | AI78: -526868900 | AJ78: -347267317 | AK78: -989725564 | AL78: -333794397 | AM78: -29727803 | AN78: -332880983 | AO78: -260817349 | AP78: -657994859 | AQ78: -377243782 | AR78: -1271190873 | AS78: -239637419 | AT78: -192486146 | AU78: -339809419 | AV78: -78169782 | AW78: -227911328 | AX78: -252670509 | AY78: -857709600 | AZ78: -327956873 | BA78: -281624585 | CM78: 外注費
B79: {=XLOOKUP(D79, 'マスタ'!$C$2:$C$1000, 'マスタ'!$D$2:$D$1000, "マスタ未登録")} -> 荷造運賃 | C79: =IF(AND(D79<>"", COUNTIF('マスタ'!$C:$C, D79)=0), "マスタ未登録", "") | D79: =F79 -> 荷造運賃 | E79: 変動費 | F79: 荷造運賃 | I79: YOANI | J79: エンタメ | AD79: -3637 | AE79: -15029 | AF79: -3910 | AG79: -13510 | AH79: -10391 | AI79: 2972 | AJ79: -10437 | AK79: -8583 | AL79: -8964 | AM79: 0 | AN79: -16720 | AO79: -7077 | AP79: -36580 | AQ79: -7920 | AR79: -7920 | AS79: -7920 | AT79: -7920 | AU79: -7920 | AV79: -7920 | AW79: -7920 | AX79: -7920 | AY79: -7920 | AZ79: -7920 | BA79: -7922 | CM79: 荷造運賃
B80: {=XLOOKUP(D80, 'マスタ'!$C$2:$C$1000, 'マスタ'!$D$2:$D$1000, "マスタ未登録")} -> 支払手数料 | C80: =IF(AND(D80<>"", COUNTIF('マスタ'!$C:$C, D80)=0), "マスタ未登録", "") | D80: =F80 -> 支払手数料 | E80: 変動費 | F80: 支払手数料 | I80: YOANI | J80: エンタメ | AD80: -10246536 | AE80: -9692484 | AF80: -13379950 | AG80: -10739035 | AH80: -8497375 | AI80: -20454399 | AJ80: -10528046 | AK80: -20774446 | AL80: -20826067 | AM80: -13218438 | AN80: -14589917 | AO80: -26745588 | AP80: -20259856 | AQ80: -23387106 | AR80: -23387106 | AS80: -23387106 | AT80: -23387106 | AU80: -23387106 | AV80: -23387106 | AW80: -23387106 | AX80: -23387106 | AY80: -23387106 | AZ80: -23387106 | BA80: -23387131 | CM80: 支払手数料
B81: {=XLOOKUP(D81, 'マスタ'!$C$2:$C$1000, 'マスタ'!$D$2:$D$1000, "マスタ未登録")} -> 保険料 | C81: =IF(AND(D81<>"", COUNTIF('マスタ'!$C:$C, D81)=0), "マスタ未登録", "") | D81: =F81 -> 保険料 | E81: 変動費 | F81: 保険料 | I81: YOANI | J81: エンタメ | AD81: -73520 | AE81: -62500 | AF81: -44770 | AG81: -45771 | AH81: -45839 | AI81: -45839 | AJ81: -166599 | AK81: -87169 | AL81: -45839 | AM81: -35839 | AN81: -65839 | AO81: -45839 | AP81: -119316 | AQ81: -87676 | AR81: -87676 | AS81: -87676 | AT81: -87676 | AU81: -87676 | AV81: -87676 | AW81: -87676 | AX81: -87676 | AY81: -87676 | AZ81: -87676 | BA81: -87716 | CM81: 保険料
B82: {=XLOOKUP(D82, 'マスタ'!$C$2:$C$1000, 'マスタ'!$D$2:$D$1000, "マスタ未登録")} -> 広告宣伝費 | C82: =IF(AND(D82<>"", COUNTIF('マスタ'!$C:$C, D82)=0), "マスタ未登録", "") | D82: =F82 -> 広告宣伝費 | E82: 準変動費 | F82: 広告宣伝費 | I82: YOANI | J82: エンタメ | AD82: -7675000 | AE82: -13419584 | AF82: -9469647 | AG82: -2293273 | AH82: -24410000 | AI82: -3016828 | AJ82: -26531520 | AK82: -19100000 | AL82: -55459500 | AM82: -42525000 | AN82: -96775000 | AO82: -68942373 | AP82: -15775000 | AQ82: -25472945 | AR82: -33472945 | AS82: -27472945 | AT82: -25472945 | AU82: -25472945 | AV82: -28472945 | AW82: -27472945 | AX82: -30472945 | AY82: -25472945 | AZ82: -28472945 | BA82: -27472957 | CM82: 広告宣伝費
B83: {=XLOOKUP(D83, 'マスタ'!$C$2:$C$1000, 'マスタ'!$D$2:$D$1000, "マスタ未登録")} -> その他 | C83: =IF(AND(D83<>"", COUNTIF('マスタ'!$C:$C, D83)=0), "マスタ未登録", "") | D83: =F83 -> その他(変) | E83: 準変動費 | F83: その他(変) | I83: YOANI | J83: エンタメ | AD83: -28833333 | AE83: -4688087 | AF83: -14408711 | AG83: -3100000 | AH83: -3902500 | AI83: -16875549 | AJ83: -8062500 | AK83: -23675000 | AL83: -17004330 | AM83: -10960416 | AN83: -16447917 | AO83: -22270901 | AP83: -5112500 | AQ83: 0 | AR83: -27000000 | AS83: -23000000 | AT83: -40000000 | AU83: -5000000 | AV83: -23000000 | AW83: -23000000 | AX83: -40000000 | AY83: -5000000 | AZ83: -26000000 | BA83: -23000000 | CM83: その他_準変動
B84: {=XLOOKUP(D84, 'マスタ'!$C$2:$C$1000, 'マスタ'!$D$2:$D$1000, "マスタ未登録")} -> 当期商品仕入高 | C84: =IF(AND(D84<>"", COUNTIF('マスタ'!$C:$C, D84)=0), "マスタ未登録", "") | D84: =F84 -> タレント報酬 | E84: 準変動費 | F84: タレント報酬 | I84: YOANI | J84: エンタメ | AD84: -23928502 | AE84: -25156865 | AF84: -24166256 | AG84: -35166976 | AH84: -35327856 | AI84: -37463515 | AJ84: -38995970 | AK84: -24424528 | AL84: 0 | AM84: -48974028 | AN84: -50643174 | AO84: -51834298 | AP84: -50963888 | AQ84: -47457837 | AR84: -47457837 | AS84: -57339634 | AT84: -57339634 | AU84: -57339634 | AV84: -57339634 | AW84: -57339634 | AX84: -57339634 | AY84: -60732432 | AZ84: -60732432 | BA84: -60621250 | CM84: タレント報酬
B85: {=XLOOKUP(D85, 'マスタ'!$C$2:$C$1000, 'マスタ'!$D$2:$D$1000, "マスタ未登録")} -> 当期商品仕入高 | C85: =IF(AND(D85<>"", COUNTIF('マスタ'!$C:$C, D85)=0), "マスタ未登録", "") | D85: =F85 -> 人件費 | E85: 準変動費 | F85: 人件費 | I85: YOANI | J85: エンタメ | AD85: -13162838 | AE85: -12724998 | AF85: -13020754 | AG85: -12924478 | AH85: -12371933 | AI85: -14498135 | AJ85: -13705046 | AK85: -12397943 | AL85: -11693787 | AM85: -11467035 | AN85: -12619942 | AO85: -20083993 | AP85: -14684459 | AQ85: -15763767 | AR85: -16797960 | AS85: -15619443 | AT85: -15850443 | AU85: -16399943 | AV85: -16399943 | AW85: -16399943 | AX85: -16509943 | AY85: -16399943 | AZ85: -16289943 | BA85: -16289944 | CM85: 人件費
B86: {=XLOOKUP(D86, 'マスタ'!$C$2:$C$1000, 'マスタ'!$D$2:$D$1000, "マスタ未登録")} -> 採用教育費 | C86: =IF(AND(D86<>"", COUNTIF('マスタ'!$C:$C, D86)=0), "マスタ未登録", "") | D86: =F86 -> 採用教育費 | E86: 準変動費 | F86: 採用教育費 | I86: YOANI | J86: エンタメ | AD86: 0 | AE86: 0 | AF86: 0 | AG86: 0 | AH86: 0 | AI86: 0 | AJ86: 0 | AK86: 0 | AL86: 0 | AM86: 0 | AN86: 0 | AO86: 0 | AP86: 0 | AQ86: 0 | AR86: 0 | AS86: 0 | AT86: 0 | AU86: 0 | AV86: 0 | AW86: 0 | AX86: 0 | AY86: 0 | AZ86: 0 | BA86: 0 | CM86: 採用教育費
B87: {=XLOOKUP(D87, 'マスタ'!$C$2:$C$1000, 'マスタ'!$D$2:$D$1000, "マスタ未登録")} -> 共通費配賦 | C87: =IF(AND(D87<>"", COUNTIF('マスタ'!$C:$C, D87)=0), "マスタ未登録", "") | D87: =F87 -> 共通費配賦 | E87: 固定費 | F87: 共通費配賦 | I87: YOANI | J87: エンタメ | AD87: 0 | AE87: 0 | AF87: 0 | AG87: 0 | AH87: 0 | AI87: 0 | AJ87: 0 | AK87: 0 | AL87: 0 | AM87: 0 | AN87: 0 | AO87: 0 | AP87: 0 | AQ87: 0 | AR87: 0 | AS87: 0 | AT87: 0 | AU87: 0 | AV87: 0 | AW87: 0 | AX87: 0 | AY87: 0 | AZ87: 0 | BA87: 0 | CM87: 共通費配賦
B88: {=XLOOKUP(D88, 'マスタ'!$C$2:$C$1000, 'マスタ'!$D$2:$D$1000, "マスタ未登録")} -> 地代家賃 | C88: =IF(AND(D88<>"", COUNTIF('マスタ'!$C:$C, D88)=0), "マスタ未登録", "") | D88: =F88 -> 地代家賃 | E88: 固定費 | F88: 地代家賃 | I88: YOANI | J88: エンタメ | AD88: -3530273 | AE88: -3682532 | AF88: -3715953 | AG88: -3701940 | AH88: -3731273 | AI88: -3731273 | AJ88: -3656469 | AK88: -3819486 | AL88: -3949953 | AM88: -3840323 | AN88: -3856394 | AO88: -4089073 | AP88: -4358026 | AQ88: -3710934 | AR88: -3710934 | AS88: -3710934 | AT88: -3710934 | AU88: -3710934 | AV88: -3710934 | AW88: -3710934 | AX88: -3710934 | AY88: -3710934 | AZ88: -3710934 | BA88: -3710950 | CM88: 地代家賃
... B100: {=XLOOKUP(D100, 'マスタ'!$C$2:$C$1000, 'マスタ'!$D$2:$D$1000, "マスタ未登録")} -> 雑費 | C100: =IF(AND(D100<>"", COUNTIF('マスタ'!$C:$C, D100)=0), "マスタ未登録", "") | D100: =F100 -> その他(固) | E100: 固定費 | F100: その他(固) | I100: YOANI | J100: エンタメ | AD100: -3066057 | AE100: -2973598 | AF100: -3054638 | AG100: -3071388 | AH100: -3235617 | AI100: -3133277 | AJ100: -3355714 | AK100: -2809168 | AL100: -3101588 | AM100: -3653144 | AN100: -3315414 | AO100: -3189618 | AP100: -3588699 | AQ100: -7289766 | AR100: -7289766 | AS100: -7289766 | AT100: -7289766 | AU100: -7289766 | AV100: -7289766 | AW100: -7289766 | AX100: -7289766 | AY100: -7289766 | AZ100: -7289766 | BA100: -7289810 | CM100: その他_固定
B101: {=XLOOKUP(D101, 'マスタ'!$C$2:$C$1000, 'マスタ'!$D$2:$D$1000, "マスタ未登録")} -> マスタ未登録 | C101: =IF(AND(D101<>"", COUNTIF('マスタ'!$C:$C, D101)=0), "マスタ未登録", "") -> マスタ未登録 | D101: =F101 -> ウタイテ配賦額 | E101: 固定費 | F101: ウタイテ配賦額 | I101: YOANI | J101: エンタメ | CM101: ウタイテ配賦額
B102: {=XLOOKUP(D102, 'マスタ'!$C$2:$C$1000, 'マスタ'!$D$2:$D$1000, "マスタ未登録")} -> マスタ未登録 | C102: =IF(AND(D102<>"", COUNTIF('マスタ'!$C:$C, D102)=0), "マスタ未登録", "") | D102: =F102
B103: {=XLOOKUP(D103, 'マスタ'!$C$2:$C$1000, 'マスタ'!$D$2:$D$1000, "マスタ未登録")} -> マスタ未登録 | C103: =IF(AND(D103<>"", COUNTIF('マスタ'!$C:$C, D103)=0), "マスタ未登録", "") | D103: =F103 | E103: 営業利益 | H103: 1 | I103: YOANI | J103: エンタメ | AD103: 32205853 | AE103: 145447892 | AF103: 120590929 | AG103: 248066827 | AH103: 89634744 | AI103: 227013127 | AJ103: 32888174 | AK103: 251270853 | AL103: 113298706 | AM103: 53986736 | AN103: 160170453 | AO103: 109128847 | AP103: 623715438 | AQ103: 163263328 | AR103: 724788990 | AS103: 73469734 | AT103: 17010204 | AU103: 128734014 | AV103: -26618433 | AW103: -3974249 | AX103: 35295046 | AY103: 365837692 | AZ103: 120419220 | BA103: 65803422 | BB103: 0 | BC103: 0 | BD103: 0 | BE103: 0 | BF103: 0 | BG103: 0 | BH103: 0 | BI103: 0 | BJ103: 0 | BK103: 0 | BL103: 0 | BM103: 0 | BN103: 0 | BO103: 0 | BP103: 0 | BQ103: 0 | BR103: 0 | BS103: 0 | BT103: 0 | BU103: 0 | BV103: 0 | BW103: 0 | BX103: 0 | BY103: 0 | BZ103: 0 | CA103: 0 | CB103: 0 | CC103: 0 | CD103: 0 | CE103: 0 | CF103: 0 | CG103: 0 | CH103: 0 | CI103: 0 | CJ103: 0 | CK103: 0 | CM103: 2287744406 | CN103: 1583703141
B104: {=XLOOKUP(D104, 'マスタ'!$C$2:$C$1000, 'マスタ'!$D$2:$D$1000, "マスタ未登録")} -> マスタ未登録 | C104: =IF(AND(D104<>"", COUNTIF('マスタ'!$C:$C, D104)=0), "マスタ未登録", "") | D104: =F104 | H104: 1
B105: {=XLOOKUP(D105, 'マスタ'!$C$2:$C$1000, 'マスタ'!$D$2:$D$1000, "マスタ未登録")} -> 売上高 | C105: =IF(AND(D105<>"", COUNTIF('マスタ'!$C:$C, D105)=0), "マスタ未登録", "") | D105: =E105 -> 売上高 | E105: 売上高 | F105: - | H105: 1 | I105: YOANI | J105: 施設運営 | AD105: 39546912 | AE105: 35889928 | AF105: 30025299 | AG105: 18770312 | AH105: 31766061 | AI105: 39068827 | AJ105: 37347252 | AK105: 34176254 | AL105: 10222254 | AM105: 7148463 | AN105: 4966007 | AO105: 6759102 | AP105: 7842190 | AQ105: 6057091 | AR105: 4991909 | AS105: 7381364 | AT105: 7840545 | AU105: 7374636 | AV105: 7595000 | AW105: 8496636 | AX105: 9519636 | AY105: 7640273 | AZ105: 4956000 | BA105: 6002591 | CM105: 売上高
B106: {=XLOOKUP(D106, 'マスタ'!$C$2:$C$1000, 'マスタ'!$D$2:$D$1000, "マスタ未登録")} -> 当期商品仕入高 | C106: =IF(AND(D106<>"", COUNTIF('マスタ'!$C:$C, D106)=0), "マスタ未登録", "") | D106: =F106 -> 仕入高 | E106: 変動費 | F106: 仕入高 | I106: YOANI | J106: 施設運営 | AD106: -216553 | AE106: -203035 | AF106: -179634 | AG106: -291330 | AH106: -289673 | AI106: -282488 | AJ106: -232868 | AK106: -247896 | AL106: -346901 | AM106: -219687 | AN106: -142911 | AO106: -301888 | AP106: -229287 | AQ106: -222902 | AR106: -165139 | AS106: -287568 | AT106: -277923 | AU106: -269018 | AV106: -245125 | AW106: -246027 | AX106: -319290 | AY106: -246127 | AZ106: -194521 | BA106: -173497 | CM106: 仕入高
B107: {=XLOOKUP(D107, 'マスタ'!$C$2:$C$1000, 'マスタ'!$D$2:$D$1000, "マスタ未登録")} -> 外注費 | C107: =IF(AND(D107<>"", COUNTIF('マスタ'!$C:$C, D107)=0), "マスタ未登録", "") | D107: =F107 -> 外注費 | E107: 変動費 | F107: 外注費 | I107: YOANI | J107: 施設運営 | AD107: -5674835 | AE107: -5609695 | AF107: -7864003 | AG107: -4022520 | AH107: -5272728 | AI107: -6086180 | AJ107: -5559630 | AK107: -7136802 | AL107: -554254 | AM107: -612878 | AN107: -332467 | AO107: -737688 | AP107: -254708 | AQ107: -370000 | AR107: -370000 | AS107: -370000 | AT107: -370000 | AU107: -370000 | AV107: -370000 | AW107: -370000 | AX107: -370000 | AY107: -370000 | AZ107: -370000 | BA107: -370000 | CM107: 外注費
B108: {=XLOOKUP(D108, 'マスタ'!$C$2:$C$1000, 'マスタ'!$D$2:$D$1000, "マスタ未登録")} -> 荷造運賃 | C108: =IF(AND(D108<>"", COUNTIF('マスタ'!$C:$C, D108)=0), "マスタ未登録", "") | D108: =F108 -> 荷造運賃 | E108: 変動費 | F108: 荷造運賃 | I108: YOANI | J108: 施設運営 | AD108: 0 | AE108: -1682 | AF108: -6400 | AG108: -13350 | AH108: -43155 | AI108: -8433 | AJ108: -39220 | AK108: -2010 | AL108: 0 | AM108: -391 | AN108: 0 | AO108: -1173 | AP108: -4000 | AQ108: 0 | AR108: 0 | AS108: 0 | AT108: 0 | AU108: 0 | AV108: 0 | AW108: 0 | AX108: 0 | AY108: 0 | AZ108: 0 | BA108: 0 | CM108: 荷造運賃
B109: {=XLOOKUP(D109, 'マスタ'!$C$2:$C$1000, 'マスタ'!$D$2:$D$1000, "マスタ未登録")} -> 支払手数料 | C109: =IF(AND(D109<>"", COUNTIF('マスタ'!$C:$C, D109)=0), "マスタ未登録", "") | D109: =F109 -> 支払手数料 | E109: 変動費 | F109: 支払手数料 | I109: YOANI | J109: 施設運営 | AD109: -410877 | AE109: -307554 | AF109: -1094616 | AG109: -305838 | AH109: -433670 | AI109: -1208553 | AJ109: -387140 | AK109: -3152331 | AL109: -142500 | AM109: -142999 | AN109: -141000 | AO109: -142000 | AP109: -142000 | AQ109: -146636 | AR109: -146636 | AS109: -146636 | AT109: -146636 | AU109: -146636 | AV109: -146636 | AW109: -146636 | AX109: -146636 | AY109: -146636 | AZ109: -146636 | BA109: -146636 | CM109: 支払手数料
B110: {=XLOOKUP(D110, 'マスタ'!$C$2:$C$1000, 'マスタ'!$D$2:$D$1000, "マスタ未登録")} -> 保険料 | C110: =IF(AND(D110<>"", COUNTIF('マスタ'!$C:$C, D110)=0), "マスタ未登録", "") | D110: =F110 -> 保険料 | E110: 変動費 | F110: 保険料 | I110: YOANI | J110: 施設運営 | AD110: 0 | AE110: 0 | AF110: 0 | AG110: 0 | AH110: 0 | AI110: 0 | AJ110: 0 | AK110: 0 | AL110: 0 | AM110: 0 | AN110: 0 | AO110: 0 | AP110: 0 | AQ110: 0 | AR110: 0 | AS110: 0 | AT110: 0 | AU110: 0 | AV110: 0 | AW110: 0 | AX110: 0 | AY110: 0 | AZ110: 0 | BA110: 0 | CM110: 保険料
B111: {=XLOOKUP(D111, 'マスタ'!$C$2:$C$1000, 'マスタ'!$D$2:$D$1000, "マスタ未登録")} -> 広告宣伝費 | C111: =IF(AND(D111<>"", COUNTIF('マスタ'!$C:$C, D111)=0), "マスタ未登録", "") | D111: =F111 -> 広告宣伝費 | E111: 準変動費 | F111: 広告宣伝費 | I111: YOANI | J111: 施設運営 | AD111: 0 | AE111: 0 | AF111: 0 | AG111: 0 | AH111: 0 | AI111: 0 | AJ111: 0 | AK111: 0 | AL111: 0 | AM111: 0 | AN111: 0 | AO111: 0 | AP111: 0 | AQ111: 0 | AR111: 0 | AS111: 0 | AT111: 0 | AU111: 0 | AV111: 0 | AW111: 0 | AX111: 0 | AY111: 0 | AZ111: 0 | BA111: 0 | CM111: 広告宣伝費
B112: {=XLOOKUP(D112, 'マスタ'!$C$2:$C$1000, 'マスタ'!$D$2:$D$1000, "マスタ未登録")} -> その他 | C112: =IF(AND(D112<>"", COUNTIF('マスタ'!$C:$C, D112)=0), "マスタ未登録", "") | D112: =F112 -> その他(変) | E112: 準変動費 | F112: その他(変) | I112: YOANI | J112: 施設運営 | AD112: 0 | AE112: 0 | AF112: 0 | AG112: 0 | AH112: 0 | AI112: 0 | AJ112: 0 | AK112: 0 | AL112: 0 | AM112: 0 | AN112: 0 | AO112: 0 | AP112: 0 | AQ112: 0 | AR112: 0 | AS112: 0 | AT112: 0 | AU112: 0 | AV112: 0 | AW112: 0 | AX112: 0 | AY112: 0 | AZ112: 0 | BA112: 0 | CM112: その他_準変動
B113: {=XLOOKUP(D113, 'マスタ'!$C$2:$C$1000, 'マスタ'!$D$2:$D$1000, "マスタ未登録")} -> 当期商品仕入高 | C113: =IF(AND(D113<>"", COUNTIF('マスタ'!$C:$C, D113)=0), "マスタ未登録", "") | D113: =F113 -> タレント報酬 | E113: 準変動費 | F113: タレント報酬 | I113: YOANI | J113: 施設運営 | AD113: 0 | AE113: 0 | AF113: 0 | AG113: 0 | AH113: 0 | AI113: 0 | AJ113: 0 | AK113: 0 | AL113: 0 | AM113: 0 | AN113: 0 | AO113: 0 | AP113: 0 | AQ113: 0 | AR113: 0 | AS113: 0 | AT113: 0 | AU113: 0 | AV113: 0 | AW113: 0 | AX113: 0 | AY113: 0 | AZ113: 0 | BA113: 0 | CM113: タレント報酬
B114: {=XLOOKUP(D114, 'マスタ'!$C$2:$C$1000, 'マスタ'!$D$2:$D$1000, "マスタ未登録")} -> 当期商品仕入高 | C114: =IF(AND(D114<>"", COUNTIF('マスタ'!$C:$C, D114)=0), "マスタ未登録", "") | D114: =F114 -> 人件費 | E114: 準変動費 | F114: 人件費 | I114: YOANI | J114: 施設運営 | AD114: -4168983 | AE114: -4018227 | AF114: -4231665 | AG114: -4143825 | AH114: -4508798 | AI114: -4675962 | AJ114: -4180932 | AK114: -4208032 | AL114: -1691183 | AM114: -1704011 | AN114: -1624830 | AO114: -1761584 | AP114: -1751164 | AQ114: -1124421 | AR114: -1086481 | AS114: -1090497 | AT114: -1086298 | AU114: -1201226 | AV114: -1133900 | AW114: -1072437 | AX114: -1105866 | AY114: -1093428 | AZ114: -1065655 | BA114: -1165111 | CM114: 人件費
B115: {=XLOOKUP(D115, 'マスタ'!$C$2:$C$1000, 'マスタ'!$D$2:$D$1000, "マスタ未登録")} -> 採用教育費 | C115: =IF(AND(D115<>"", COUNTIF('マスタ'!$C:$C, D115)=0), "マスタ未登録", "") | D115: =F115 -> 採用教育費 | E115: 準変動費 | F115: 採用教育費 | I115: YOANI | J115: 施設運営 | AD115: 0 | AE115: 0 | AF115: 0 | AG115: 0 | AH115: 0 | AI115: 0 | AJ115: 0 | AK115: 0 | AL115: 0 | AM115: 0 | AN115: 0 | AO115: 0 | AP115: 0 | AQ115: 0 | AR115: 0 | AS115: 0 | AT115: 0 | AU115: 0 | AV115: 0 | AW115: 0 | AX115: 0 | AY115: 0 | AZ115: 0 | BA115: 0 | CM115: 採用教育費
B116: {=XLOOKUP(D116, 'マスタ'!$C$2:$C$1000, 'マスタ'!$D$2:$D$1000, "マスタ未登録")} -> 共通費配賦 | C116: =IF(AND(D116<>"", COUNTIF('マスタ'!$C:$C, D116)=0), "マスタ未登録", "") | D116: =F116 -> 共通費配賦 | E116: 固定費 | F116: 共通費配賦 | I116: YOANI | J116: 施設運営 | AD116: 0 | AE116: 0 | AF116: 0 | AG116: 0 | AH116: 0 | AI116: 0 | AJ116: 0 | AK116: 0 | AL116: 0 | AM116: 0 | AN116: 0 | AO116: 0 | AP116: 0 | AQ116: 0 | AR116: 0 | AS116: 0 | AT116: 0 | AU116: 0 | AV116: 0 | AW116: 0 | AX116: 0 | AY116: 0 | AZ116: 0 | BA116: 0 | CM116: 共通費配賦
B117: {=XLOOKUP(D117, 'マスタ'!$C$2:$C$1000, 'マスタ'!$D$2:$D$1000, "マスタ未登録")} -> 地代家賃 | C117: =IF(AND(D117<>"", COUNTIF('マスタ'!$C:$C, D117)=0), "マスタ未登録", "") | D117: =F117 -> 地代家賃 | E117: 固定費 | F117: 地代家賃 | I117: YOANI | J117: 施設運営 | AD117: -2273458 | AE117: -2273458 | AF117: -2273458 | AG117: -2273458 | AH117: -2273458 | AI117: -2273458 | AJ117: -2273458 | AK117: -2273458 | AL117: -1918728 | AM117: -1918728 | AN117: -1918728 | AO117: -1918728 | AP117: -1918728 | AQ117: -1918728 | AR117: -1918728 | AS117: -1918728 | AT117: -1918728 | AU117: -1918728 | AV117: -1918728 | AW117: -1918728 | AX117: -1918728 | AY117: -1918728 | AZ117: -1918728 | BA117: -1918728 | CM117: 地代家賃
... B129: {=XLOOKUP(D129, 'マスタ'!$C$2:$C$1000, 'マスタ'!$D$2:$D$1000, "マスタ未登録")} -> 雑費 | C129: =IF(AND(D129<>"", COUNTIF('マスタ'!$C:$C, D129)=0), "マスタ未登録", "") | D129: =F129 -> その他(固) | E129: 固定費 | F129: その他(固) | I129: YOANI | J129: 施設運営 | AD129: -5262678 | AE129: -5002945 | AF129: -6795802 | AG129: -6295254 | AH129: -6445569 | AI129: -4791307 | AJ129: -5138507 | AK129: -14688180 | AL129: -37000 | AM129: -37000 | AN129: -45500 | AO129: -37000 | AP129: -37000 | AQ129: -137000 | AR129: -132800 | AS129: -132800 | AT129: -132800 | AU129: -132800 | AV129: -132800 | AW129: -132800 | AX129: -132800 | AY129: -132800 | AZ129: -132800 | BA129: -135000 | CM129: その他_固定
B130: {=XLOOKUP(D130, 'マスタ'!$C$2:$C$1000, 'マスタ'!$D$2:$D$1000, "マスタ未登録")} -> マスタ未登録 | C130: =IF(AND(D130<>"", COUNTIF('マスタ'!$C:$C, D130)=0), "マスタ未登録", "") -> マスタ未登録 | D130: =F130 -> ウタイテ配賦額 | E130: 固定費 | F130: ウタイテ配賦額 | I130: YOANI | J130: 施設運営 | CM130: ウタイテ配賦額
B131: {=XLOOKUP(D131, 'マスタ'!$C$2:$C$1000, 'マスタ'!$D$2:$D$1000, "マスタ未登録")} -> マスタ未登録 | C131: =IF(AND(D131<>"", COUNTIF('マスタ'!$C:$C, D131)=0), "マスタ未登録", "") | D131: =F131
B132: {=XLOOKUP(D132, 'マスタ'!$C$2:$C$1000, 'マスタ'!$D$2:$D$1000, "マスタ未登録")} -> マスタ未登録 | C132: =IF(AND(D132<>"", COUNTIF('マスタ'!$C:$C, D132)=0), "マスタ未登録", "") | D132: =F132 | E132: 営業利益 | H132: 1 | I132: YOANI | J132: 施設運営 | AD132: 12295041 | AE132: 10322425 | AF132: -1084901 | AG132: -7178457 | AH132: 2920301 | AI132: 10487743 | AJ132: 10993021 | AK132: -6324679 | AL132: 4803991 | AM132: 1896520 | AN132: 150190 | AO132: 1282882 | AP132: 2930225 | AQ132: 1595125 | AR132: 644491 | AS132: 2871195 | AT132: 3340297 | AU132: 2782279 | AV132: 3113181 | AW132: 4054876 | AX132: 5005275 | AY132: 3180124 | AZ132: 600322 | BA132: 1541071 | BB132: 0 | BC132: 0 | BD132: 0 | BE132: 0 | BF132: 0 | BG132: 0 | BH132: 0 | BI132: 0 | BJ132: 0 | BK132: 0 | BL132: 0 | BM132: 0 | BN132: 0 | BO132: 0 | BP132: 0 | BQ132: 0 | BR132: 0 | BS132: 0 | BT132: 0 | BU132: 0 | BV132: 0 | BW132: 0 | BX132: 0 | BY132: 0 | BZ132: 0 | CA132: 0 | CB132: 0 | CC132: 0 | CD132: 0 | CE132: 0 | CF132: 0 | CG132: 0 | CH132: 0 | CI132: 0 | CJ132: 0 | CK132: 0 | CM132: 31658462 | CN132: 40564077 | CO132: 1400
B133: {=XLOOKUP(D133, 'マスタ'!$C$2:$C$1000, 'マスタ'!$D$2:$D$1000, "マスタ未登録")} -> マスタ未登録 | C133: =IF(AND(D133<>"", COUNTIF('マスタ'!$C:$C, D133)=0), "マスタ未登録", "") | D133: =F133 | H133: 1
B134: {=XLOOKUP(D134, 'マスタ'!$C$2:$C$1000, 'マスタ'!$D$2:$D$1000, "マスタ未登録")} -> 売上高 | C134: =IF(AND(D134<>"", COUNTIF('マスタ'!$C:$C, D134)=0), "マスタ未登録", "") | D134: =E134 -> 売上高 | E134: 売上高 | F134: - | H134: 1 | I134: YOANI | J134: 共通 | AD134: 9212252 | AE134: 9212252 | AF134: 9212252 | AG134: 9212252 | AH134: 9212252 | AI134: 7885708 | AJ134: 7885708 | AK134: 7885708 | AL134: 7885708 | AM134: 7885708 | AN134: 12285708 | AO134: 8285708 | AP134: 8285708 | AQ134: 8285708 | AR134: 8285708 | AS134: 8285708 | AT134: 8285708 | AU134: 8285708 | AV134: 8285708 | AW134: 8285708 | AX134: 8285708 | AY134: 8285708 | AZ134: 8285708 | BA134: 8285708 | CM134: 売上高
B135: {=XLOOKUP(D135, 'マスタ'!$C$2:$C$1000, 'マスタ'!$D$2:$D$1000, "マスタ未登録")} -> 当期商品仕入高 | C135: =IF(AND(D135<>"", COUNTIF('マスタ'!$C:$C, D135)=0), "マスタ未登録", "") | D135: =F135 -> 仕入高 | E135: 変動費 | F135: 仕入高 | I135: YOANI | J135: 共通 | AD135: 0 | AE135: 0 | AF135: 0 | AG135: 0 | AH135: 0 | AI135: 0 | AJ135: 0 | AK135: 0 | AL135: 0 | AM135: 0 | AN135: 0 | AO135: 0 | AP135: 0 | AQ135: 0 | AR135: 0 | AS135: 0 | AT135: 0 | AU135: 0 | AV135: 0 | AW135: 0 | AX135: 0 | AY135: 0 | AZ135: 0 | BA135: 0 | CM135: 仕入高
B136: {=XLOOKUP(D136, 'マスタ'!$C$2:$C$1000, 'マスタ'!$D$2:$D$1000, "マスタ未登録")} -> 外注費 | C136: =IF(AND(D136<>"", COUNTIF('マスタ'!$C:$C, D136)=0), "マスタ未登録", "") | D136: =F136 -> 外注費 | E136: 変動費 | F136: 外注費 | I136: YOANI | J136: 共通 | AD136: -1335000 | AE136: -1429000 | AF136: -2794359 | AG136: -2709000 | AH136: -5732000 | AI136: -2445000 | AJ136: -2560000 | AK136: -2729000 | AL136: -2861000 | AM136: -2459000 | AN136: -2482000 | AO136: -2435000 | AP136: -34503546 | AQ136: -34715000 | AR136: -34715000 | AS136: -34665000 | AT136: -34665000 | AU136: -34665000 | AV136: -34665000 | AW136: -35165000 | AX136: -34665000 | AY136: -34665000 | AZ136: -34665000 | BA136: -34665000 | CM136: 外注費
B137: {=XLOOKUP(D137, 'マスタ'!$C$2:$C$1000, 'マスタ'!$D$2:$D$1000, "マスタ未登録")} -> 荷造運賃 | C137: =IF(AND(D137<>"", COUNTIF('マスタ'!$C:$C, D137)=0), "マスタ未登録", "") | D137: =F137 -> 荷造運賃 | E137: 変動費 | F137: 荷造運賃 | I137: YOANI | J137: 共通 | AD137: -156490 | AE137: -75834 | AF137: -105484 | AG137: -78596 | AH137: -69843 | AI137: -66214 | AJ137: -51594 | AK137: -56865 | AL137: -48068 | AM137: -113203 | AN137: -99394 | AO137: -258998 | AP137: -180727 | AQ137: -156490 | AR137: -156490 | AS137: -156490 | AT137: -156490 | AU137: -156490 | AV137: -156490 | AW137: -156490 | AX137: -156490 | AY137: -156490 | AZ137: -156490 | BA137: -156490 | CM137: 荷造運賃
B138: {=XLOOKUP(D138, 'マスタ'!$C$2:$C$1000, 'マスタ'!$D$2:$D$1000, "マスタ未登録")} -> 支払手数料 | C138: =IF(AND(D138<>"", COUNTIF('マスタ'!$C:$C, D138)=0), "マスタ未登録", "") | D138: =F138 -> 支払手数料 | E138: 変動費 | F138: 支払手数料 | I138: YOANI | J138: 共通 | AD138: -1110145 | AE138: -675237 | AF138: -574586 | AG138: -527570 | AH138: -649549 | AI138: -797718 | AJ138: -929428 | AK138: -449111 | AL138: -885059 | AM138: -1950780 | AN138: -773423 | AO138: -1954042 | AP138: -475583 | AQ138: -365024 | AR138: -365024 | AS138: -365024 | AT138: -365024 | AU138: -365024 | AV138: -365024 | AW138: -365024 | AX138: -365024 | AY138: -365024 | AZ138: -365024 | BA138: -365024 | CM138: 支払手数料
B139: {=XLOOKUP(D139, 'マスタ'!$C$2:$C$1000, 'マスタ'!$D$2:$D$1000, "マスタ未登録")} -> 保険料 | C139: =IF(AND(D139<>"", COUNTIF('マスタ'!$C:$C, D139)=0), "マスタ未登録", "") | D139: =F139 -> 保険料 | E139: 変動費 | F139: 保険料 | I139: YOANI | J139: 共通 | AD139: 980417 | AE139: -483575 | AF139: -483575 | AG139: -457554 | AH139: -483575 | AI139: -483575 | AJ139: -350435 | AK139: -313075 | AL139: -186895 | AM139: -337075 | AN139: -313075 | AO139: -313075 | AP139: -216335 | AQ139: -292284 | AR139: -292284 | AS139: -292284 | AT139: -292284 | AU139: -292284 | AV139: -292284 | AW139: -292284 | AX139: -292284 | AY139: -292284 | AZ139: -292284 | BA139: -292284 | CM139: 保険料
B140: {=XLOOKUP(D140, 'マスタ'!$C$2:$C$1000, 'マスタ'!$D$2:$D$1000, "マスタ未登録")} -> 広告宣伝費 | C140: =IF(AND(D140<>"", COUNTIF('マスタ'!$C:$C, D140)=0), "マスタ未登録", "") | D140: =F140 -> 広告宣伝費 | E140: 準変動費 | F140: 広告宣伝費 | I140: YOANI | J140: 共通 | AD140: 0 | AE140: 0 | AF140: 0 | AG140: 0 | AH140: 0 | AI140: 0 | AJ140: 0 | AK140: 0 | AL140: 0 | AM140: -3310 | AN140: 0 | AO140: 0 | AP140: 0 | AQ140: 0 | AR140: 0 | AS140: 0 | AT140: 0 | AU140: 0 | AV140: 0 | AW140: 0 | AX140: 0 | AY140: 0 | AZ140: 0 | BA140: 0 | CM140: 広告宣伝費
B141: {=XLOOKUP(D141, 'マスタ'!$C$2:$C$1000, 'マスタ'!$D$2:$D$1000, "マスタ未登録")} -> その他 | C141: =IF(AND(D141<>"", COUNTIF('マスタ'!$C:$C, D141)=0), "マスタ未登録", "") | D141: =F141 -> その他(変) | E141: 準変動費 | F141: その他(変) | I141: YOANI | J141: 共通 | AD141: 0 | AE141: 0 | AF141: 0 | AG141: 0 | AH141: 0 | AI141: 0 | AJ141: 0 | AK141: 0 | AL141: 0 | AM141: 0 | AN141: 0 | AO141: 0 | AP141: 0 | AQ141: 0 | AR141: 0 | AS141: 0 | AT141: 0 | AU141: 0 | AV141: 0 | AW141: 0 | AX141: 0 | AY141: 0 | AZ141: 0 | BA141: 0 | CM141: その他_準変動
B142: {=XLOOKUP(D142, 'マスタ'!$C$2:$C$1000, 'マスタ'!$D$2:$D$1000, "マスタ未登録")} -> 当期商品仕入高 | C142: =IF(AND(D142<>"", COUNTIF('マスタ'!$C:$C, D142)=0), "マスタ未登録", "") | D142: =F142 -> タレント報酬 | E142: 準変動費 | F142: タレント報酬 | I142: YOANI | J142: 共通 | AD142: -324619 | AE142: -324619 | AF142: 0 | AG142: -324619 | AH142: -324619 | AI142: -321819 | AJ142: -324619 | AK142: -324619 | AL142: -324619 | AM142: -324619 | AN142: -324619 | AO142: -324619 | AP142: -355219 | AQ142: -341819 | AR142: -341819 | AS142: -341819 | AT142: -341819 | AU142: -341819 | AV142: -341819 | AW142: -341819 | AX142: -341819 | AY142: -341819 | AZ142: -341819 | BA142: -341819 | CM142: タレント報酬
B143: {=XLOOKUP(D143, 'マスタ'!$C$2:$C$1000, 'マスタ'!$D$2:$D$1000, "マスタ未登録")} -> 当期商品仕入高 | C143: =IF(AND(D143<>"", COUNTIF('マスタ'!$C:$C, D143)=0), "マスタ未登録", "") | D143: =F143 -> 人件費 | E143: 準変動費 | F143: 人件費 | I143: YOANI | J143: 共通 | AD143: -15422855 | AE143: -16197393 | AF143: -15327225 | AG143: -17099422 | AH143: -16558327 | AI143: -17372251 | AJ143: -16651172 | AK143: -16918625 | AL143: -18064194 | AM143: -17549606 | AN143: -16577134 | AO143: -20113032 | AP143: -11578090 | AQ143: -13538083 | AR143: -14498771 | AS143: -14548582 | AT143: -14579608 | AU143: -15428190 | AV143: -14847872 | AW143: -14728942 | AX143: -14683263 | AY143: -14750473 | AZ143: -14684181 | BA143: -14562005 | CM143: 人件費
B144: {=XLOOKUP(D144, 'マスタ'!$C$2:$C$1000, 'マスタ'!$D$2:$D$1000, "マスタ未登録")} -> 採用教育費 | C144: =IF(AND(D144<>"", COUNTIF('マスタ'!$C:$C, D144)=0), "マスタ未登録", "") | D144: =F144 -> 採用教育費 | E144: 準変動費 | F144: 採用教育費 | I144: YOANI | J144: 共通 | AD144: 0 | AE144: 0 | AF144: 0 | AG144: 0 | AH144: 0 | AI144: 0 | AJ144: 0 | AK144: 0 | AL144: 0 | AM144: 0 | AN144: 0 | AO144: 0 | AP144: 0 | AQ144: 0 | AR144: 0 | AS144: 0 | AT144: 0 | AU144: 0 | AV144: 0 | AW144: 0 | AX144: 0 | AY144: 0 | AZ144: 0 | BA144: 0 | CM144: 採用教育費
B145: {=XLOOKUP(D145, 'マスタ'!$C$2:$C$1000, 'マスタ'!$D$2:$D$1000, "マスタ未登録")} -> 共通費配賦 | C145: =IF(AND(D145<>"", COUNTIF('マスタ'!$C:$C, D145)=0), "マスタ未登録", "") | D145: =F145 -> 共通費配賦 | E145: 固定費 | F145: 共通費配賦 | I145: YOANI | J145: 共通 | AD145: 0 | AE145: 0 | AF145: 0 | AG145: 0 | AH145: 0 | AI145: 0 | AJ145: 0 | AK145: 0 | AL145: 0 | AM145: 0 | AN145: 0 | AO145: 0 | AP145: 0 | AQ145: 0 | AR145: 0 | AS145: 0 | AT145: 0 | AU145: 0 | AV145: 0 | AW145: 0 | AX145: 0 | AY145: 0 | AZ145: 0 | BA145: 0 | CM145: 共通費配賦
B146: {=XLOOKUP(D146, 'マスタ'!$C$2:$C$1000, 'マスタ'!$D$2:$D$1000, "マスタ未登録")} -> 地代家賃 | C146: =IF(AND(D146<>"", COUNTIF('マスタ'!$C:$C, D146)=0), "マスタ未登録", "") | D146: =F146 -> 地代家賃 | E146: 固定費 | F146: 地代家賃 | I146: YOANI | J146: 共通 | AD146: -7010879 | AE146: -7010879 | AF146: -7010879 | AG146: -7010879 | AH146: -7010879 | AI146: -5684335 | AJ146: -5687835 | AK146: -5684335 | AL146: -5687062 | AM146: -5684323 | AN146: -5700522 | AO146: -5700522 | AP146: -6996880 | AQ146: -6996877 | AR146: -6996877 | AS146: -6996877 | AT146: -6996877 | AU146: -6996877 | AV146: -6996877 | AW146: -6996877 | AX146: -6996877 | AY146: -6996877 | AZ146: -6996877 | BA146: -6996877 | CM146: 地代家賃
... B158: {=XLOOKUP(D158, 'マスタ'!$C$2:$C$1000, 'マスタ'!$D$2:$D$1000, "マスタ未登録")} -> 雑費 | C158: =IF(AND(D158<>"", COUNTIF('マスタ'!$C:$C, D158)=0), "マスタ未登録", "") | D158: =F158 -> その他(固) | E158: 固定費 | F158: その他(固) | I158: YOANI | J158: 共通 | AD158: -154700 | AE158: -92700 | AF158: -665442 | AG158: -31300 | AH158: 5500 | AI158: -665517 | AJ158: -26682 | AK158: -14500 | AL158: -5022691 | AM158: -120835 | AN158: -54167 | AO158: 705561 | AP158: -454970 | AQ158: -138000 | AR158: -738000 | AS158: -138000 | AT158: -138000 | AU158: -738000 | AV158: -138000 | AW158: -138000 | AX158: -738000 | AY158: -138000 | AZ158: -138000 | BA158: -738000 | CM158: その他_固定
...

Sheet FoC_PL
D1: 月次推移：損益計算書_ForCreators株式会社（期間：2026年04月〜2027年03月、表示単位：円）
J2: 46113 | K2: 46143 | L2: 46174 | M2: 46204 | N2: 46235 | O2: 46266 | P2: 46296 | Q2: 46327 | R2: 46357 | S2: 46388 | T2: 46419 | U2: 46447 | V2: 期間累計
D3: 売上高
A4: {=XLOOKUP(C4, 'マスタ'!$C$2:$C$312, 'マスタ'!$D$2:$D$312, "マスタ未登録")} -> 売上高 | B4: =IF(AND(C4<>"", COUNTIF('マスタ'!$C:$C, C4)=0), "マスタ未登録", "") | C4: =D4&D109&E4&F4&G4&H4 -> 売上高 | E4: 売上高 | J4: 21265200 | K4: 32272288 | L4: 0 | M4: 0 | N4: 0 | O4: 0 | P4: 0 | Q4: 0 | R4: 0 | S4: 0 | T4: 0 | U4: 0 | V4: 53537488
A5: {=XLOOKUP(C5, 'マスタ'!$C$2:$C$312, 'マスタ'!$D$2:$D$312, "マスタ未登録")} -> マスタ未登録 | B5: =IF(AND(C5<>"", COUNTIF('マスタ'!$C:$C, C5)=0), "マスタ未登録", "") -> マスタ未登録 | C5: =D5&D110&E5&F5&G5&H5 -> 売上高 計 | D5: 売上高 計 | J5: 21265200 | K5: 32272288 | L5: 0 | M5: 0 | N5: 0 | O5: 0 | P5: 0 | Q5: 0 | R5: 0 | S5: 0 | T5: 0 | U5: 0 | V5: 53537488
A6: {=XLOOKUP(C6, 'マスタ'!$C$2:$C$312, 'マスタ'!$D$2:$D$312, "マスタ未登録")} -> マスタ未登録 | B6: =IF(AND(C6<>"", COUNTIF('マスタ'!$C:$C, C6)=0), "マスタ未登録", "") -> マスタ未登録 | C6: =D6&D111&E6&F6&G6&H6 -> 売上原価 | E6: 売上原価
A7: {=XLOOKUP(C7, 'マスタ'!$C$2:$C$312, 'マスタ'!$D$2:$D$312, "マスタ未登録")} -> マスタ未登録 | B7: =IF(AND(C7<>"", COUNTIF('マスタ'!$C:$C, C7)=0), "マスタ未登録", "") -> マスタ未登録 | C7: =D7&D112&E7&F7&G7&H7 -> 売上原価 | E7: 売上原価 | J7: 13187465 | K7: 15954741 | L7: 684688 | M7: 461927 | N7: 461927 | O7: 461927 | P7: 461927 | Q7: 461927 | R7: 461927 | S7: 461927 | T7: 461927 | U7: 461957 | V7: 33984267
A8: {=XLOOKUP(C8, 'マスタ'!$C$2:$C$312, 'マスタ'!$D$2:$D$312, "マスタ未登録")} -> 期首商品棚卸高 | B8: =IF(AND(C8<>"", COUNTIF('マスタ'!$C:$C, C8)=0), "マスタ未登録", "") | C8: =D8&D113&E8&F8&G8&H8 -> 期首商品棚卸 | G8: 期首商品棚卸 | J8: 0 | K8: 0 | L8: 0 | M8: 0 | N8: 0 | O8: 0 | P8: 0 | Q8: 0 | R8: 0 | S8: 0 | T8: 0 | U8: 0 | V8: 0
A9: {=XLOOKUP(C9, 'マスタ'!$C$2:$C$312, 'マスタ'!$D$2:$D$312, "マスタ未登録")} -> 当期商品仕入高 | B9: =IF(AND(C9<>"", COUNTIF('マスタ'!$C:$C, C9)=0), "マスタ未登録", "") | C9: =D9&D114&E9&F9&G9&H9 -> 当期商品仕入 | G9: 当期商品仕入 | J9: 13187465 | K9: 15954741 | L9: 684688 | M9: 461927 | N9: 461927 | O9: 461927 | P9: 461927 | Q9: 461927 | R9: 461927 | S9: 461927 | T9: 461927 | U9: 461957 | V9: 33984267
A10: {=XLOOKUP(C10, 'マスタ'!$C$2:$C$312, 'マスタ'!$D$2:$D$312, "マスタ未登録")} -> 当期商品仕入高 | B10: =IF(AND(C10<>"", COUNTIF('マスタ'!$C:$C, C10)=0), "マスタ未登録", "") | C10: =D10&D115&E10&F10&G10&H10 -> 給料手当(原) | H10: 給料手当(原) | J10: 2258594 | K10: 2555829 | L10: 0 | M10: 0 | N10: 0 | O10: 0 | P10: 0 | Q10: 0 | R10: 0 | S10: 0 | T10: 0 | U10: 0 | V10: 4814423
A11: {=XLOOKUP(C11, 'マスタ'!$C$2:$C$312, 'マスタ'!$D$2:$D$312, "マスタ未登録")} -> 当期商品仕入高 | B11: =IF(AND(C11<>"", COUNTIF('マスタ'!$C:$C, C11)=0), "マスタ未登録", "") | C11: =D11&D116&E11&F11&G11&H11 -> 法定福利費(原) | H11: 法定福利費(原) | J11: 441611 | K11: 484872 | L11: 0 | M11: 0 | N11: 0 | O11: 0 | P11: 0 | Q11: 0 | R11: 0 | S11: 0 | T11: 0 | U11: 0 | V11: 926483
A12: {=XLOOKUP(C12, 'マスタ'!$C$2:$C$312, 'マスタ'!$D$2:$D$312, "マスタ未登録")} -> 当期商品仕入高 | B12: =IF(AND(C12<>"", COUNTIF('マスタ'!$C:$C, C12)=0), "マスタ未登録", "") | C12: =D12&D117&E12&F12&G12&H12 -> 外注費(原) | H12: 外注費(原) | J12: 9032770 | K12: 11131450 | L12: 0 | M12: 0 | N12: 0 | O12: 0 | P12: 0 | Q12: 0 | R12: 0 | S12: 0 | T12: 0 | U12: 0 | V12: 20164220
A13: {=XLOOKUP(C13, 'マスタ'!$C$2:$C$312, 'マスタ'!$D$2:$D$312, "マスタ未登録")} -> 当期商品仕入高 | B13: =IF(AND(C13<>"", COUNTIF('マスタ'!$C:$C, C13)=0), "マスタ未登録", "") | C13: =D13&D118&E13&F13&G13&H13 -> 業務委託費(原) | H13: 業務委託費(原) | J13: 595037 | K13: 904952 | L13: 0 | M13: 0 | N13: 0 | O13: 0 | P13: 0 | Q13: 0 | R13: 0 | S13: 0 | T13: 0 | U13: 0 | V13: 1499989
A14: {=XLOOKUP(C14, 'マスタ'!$C$2:$C$312, 'マスタ'!$D$2:$D$312, "マスタ未登録")} -> 当期商品仕入高 | B14: =IF(AND(C14<>"", COUNTIF('マスタ'!$C:$C, C14)=0), "マスタ未登録", "") | C14: =D14&D119&E14&F14&G14&H14 -> 旅費交通費(原) | H14: 旅費交通費(原) | J14: 100628 | K14: 141651 | L14: 0 | M14: 0 | N14: 0 | O14: 0 | P14: 0 | Q14: 0 | R14: 0 | S14: 0 | T14: 0 | U14: 0 | V14: 242279
A15: {=XLOOKUP(C15, 'マスタ'!$C$2:$C$312, 'マスタ'!$D$2:$D$312, "マスタ未登録")} -> 当期商品仕入高 | B15: =IF(AND(C15<>"", COUNTIF('マスタ'!$C:$C, C15)=0), "マスタ未登録", "") | C15: =D15&D120&E15&F15&G15&H15 -> 消耗品費(原) | H15: 消耗品費(原) | J15: 537 | K15: 0 | L15: 0 | M15: 0 | N15: 0 | O15: 0 | P15: 0 | Q15: 0 | R15: 0 | S15: 0 | T15: 0 | U15: 0 | V15: 537
A16: {=XLOOKUP(C16, 'マスタ'!$C$2:$C$312, 'マスタ'!$D$2:$D$312, "マスタ未登録")} -> 当期商品仕入高 | B16: =IF(AND(C16<>"", COUNTIF('マスタ'!$C:$C, C16)=0), "マスタ未登録", "") | C16: =D16&D121&E16&F16&G16&H16 -> 通信費(原) | H16: 通信費(原) | J16: 296361 | K16: 274060 | L16: 222761 | M16: 0 | N16: 0 | O16: 0 | P16: 0 | Q16: 0 | R16: 0 | S16: 0 | T16: 0 | U16: 0 | V16: 793182
A17: {=XLOOKUP(C17, 'マスタ'!$C$2:$C$312, 'マスタ'!$D$2:$D$312, "マスタ未登録")} -> 当期商品仕入高 | B17: =IF(AND(C17<>"", COUNTIF('マスタ'!$C:$C, C17)=0), "マスタ未登録", "") | C17: =D17&D122&E17&F17&G17&H17 -> 減価償却費(原) | H17: 減価償却費(原) | J17: 461927 | K17: 461927 | L17: 461927 | M17: 461927 | N17: 461927 | O17: 461927 | P17: 461927 | Q17: 461927 | R17: 461927 | S17: 461927 | T17: 461927 | U17: 461957 | V17: 5543154
A18: {=XLOOKUP(C18, 'マスタ'!$C$2:$C$312, 'マスタ'!$D$2:$D$312, "マスタ未登録")} -> 他勘定振替高 | B18: =IF(AND(C18<>"", COUNTIF('マスタ'!$C:$C, C18)=0), "マスタ未登録", "") | C18: =D18&D123&E18&F18&G18&H18 -> 他勘定振替高(商) | G18: 他勘定振替高(商) | J18: 0 | K18: 0 | L18: 0 | M18: 0 | N18: 0 | O18: 0 | P18: 0 | Q18: 0 | R18: 0 | S18: 0 | T18: 0 | U18: 0 | V18: 0
A19: {=XLOOKUP(C19, 'マスタ'!$C$2:$C$312, 'マスタ'!$D$2:$D$312, "マスタ未登録")} -> 期末商品棚卸高 | B19: =IF(AND(C19<>"", COUNTIF('マスタ'!$C:$C, C19)=0), "マスタ未登録", "") | C19: =D19&D124&E19&F19&G19&H19 -> 期末商品棚卸 | G19: 期末商品棚卸 | J19: 0 | K19: 0 | L19: 0 | M19: 0 | N19: 0 | O19: 0 | P19: 0 | Q19: 0 | R19: 0 | S19: 0 | T19: 0 | U19: 0 | V19: 0
A20: {=XLOOKUP(C20, 'マスタ'!$C$2:$C$312, 'マスタ'!$D$2:$D$312, "マスタ未登録")} -> マスタ未登録 | B20: =IF(AND(C20<>"", COUNTIF('マスタ'!$C:$C, C20)=0), "マスタ未登録", "") -> マスタ未登録 | C20: =D20&D125&E20&F20&G20&H20 -> 商品売上原価 | F20: 商品売上原価 | J20: 13187465 | K20: 15954741 | L20: 684688 | M20: 461927 | N20: 461927 | O20: 461927 | P20: 461927 | Q20: 461927 | R20: 461927 | S20: 461927 | T20: 461927 | U20: 461957 | V20: 33984267
A21: {=XLOOKUP(C21, 'マスタ'!$C$2:$C$312, 'マスタ'!$D$2:$D$312, "マスタ未登録")} -> マスタ未登録 | B21: =IF(AND(C21<>"", COUNTIF('マスタ'!$C:$C, C21)=0), "マスタ未登録", "") -> マスタ未登録 | C21: =D21&D126&E21&F21&G21&H21 -> 売上総損益金額 | D21: 売上総損益金額 | J21: 8077735 | K21: 16317547 | L21: -684688 | M21: -461927 | N21: -461927 | O21: -461927 | P21: -461927 | Q21: -461927 | R21: -461927 | S21: -461927 | T21: -461927 | U21: -461957 | V21: 19553221
A22: {=XLOOKUP(C22, 'マスタ'!$C$2:$C$312, 'マスタ'!$D$2:$D$312, "マスタ未登録")} -> マスタ未登録 | B22: =IF(AND(C22<>"", COUNTIF('マスタ'!$C:$C, C22)=0), "マスタ未登録", "") -> マスタ未登録 | C22: =D22&D127&E22&F22&G22&H22 -> 販売管理費 | E22: 販売管理費
A23: {=XLOOKUP(C23, 'マスタ'!$C$2:$C$312, 'マスタ'!$D$2:$D$312, "マスタ未登録")} -> 役員報酬 | B23: =IF(AND(C23<>"", COUNTIF('マスタ'!$C:$C, C23)=0), "マスタ未登録", "") | C23: =D23&D128&E23&F23&G23&H23 -> 役員報酬 | F23: 役員報酬 | J23: 1200000 | K23: 1200000 | L23: 0 | M23: 0 | N23: 0 | O23: 0 | P23: 0 | Q23: 0 | R23: 0 | S23: 0 | T23: 0 | U23: 0 | V23: 2400000
A24: {=XLOOKUP(C24, 'マスタ'!$C$2:$C$312, 'マスタ'!$D$2:$D$312, "マスタ未登録")} -> 採用教育費 | B24: =IF(AND(C24<>"", COUNTIF('マスタ'!$C:$C, C24)=0), "マスタ未登録", "") | C24: =D24&D129&E24&F24&G24&H24 -> 採用教育費 | F24: 採用教育費 | J24: 138000 | K24: 55000 | L24: 55000 | M24: 55000 | N24: 55000 | O24: 55000 | P24: 55000 | Q24: 55000 | R24: 55000 | S24: 55000 | T24: 55000 | U24: 55000 | V24: 743000
A25: {=XLOOKUP(C25, 'マスタ'!$C$2:$C$312, 'マスタ'!$D$2:$D$312, "マスタ未登録")} -> 業務委託費 | B25: =IF(AND(C25<>"", COUNTIF('マスタ'!$C:$C, C25)=0), "マスタ未登録", "") | C25: =D25&D130&E25&F25&G25&H25 -> 業務委託費 | F25: 業務委託費 | J25: 250420 | K25: 454055 | L25: 0 | M25: 0 | N25: 0 | O25: 0 | P25: 0 | Q25: 0 | R25: 0 | S25: 0 | T25: 0 | U25: 0 | V25: 704475
A26: {=XLOOKUP(C26, 'マスタ'!$C$2:$C$312, 'マスタ'!$D$2:$D$312, "マスタ未登録")} -> 外注費 | B26: =IF(AND(C26<>"", COUNTIF('マスタ'!$C:$C, C26)=0), "マスタ未登録", "") | C26: =D26&D131&E26&F26&G26&H26 -> 外注費 | F26: 外注費 | J26: -47 | K26: 0 | L26: 0 | M26: 0 | N26: 0 | O26: 0 | P26: 0 | Q26: 0 | R26: 0 | S26: 0 | T26: 0 | U26: 0 | V26: -47
A27: {=XLOOKUP(C27, 'マスタ'!$C$2:$C$312, 'マスタ'!$D$2:$D$312, "マスタ未登録")} -> 広告宣伝費 | B27: =IF(AND(C27<>"", COUNTIF('マスタ'!$C:$C, C27)=0), "マスタ未登録", "") | C27: =D27&D132&E27&F27&G27&H27 -> 広告宣伝費 | F27: 広告宣伝費 | J27: 23260 | K27: 15260 | L27: 0 | M27: 0 | N27: 0 | O27: 0 | P27: 0 | Q27: 0 | R27: 0 | S27: 0 | T27: 0 | U27: 0 | V27: 38520
A28: {=XLOOKUP(C28, 'マスタ'!$C$2:$C$312, 'マスタ'!$D$2:$D$312, "マスタ未登録")} -> 接待交際費 | B28: =IF(AND(C28<>"", COUNTIF('マスタ'!$C:$C, C28)=0), "マスタ未登録", "") | C28: =D28&D133&E28&F28&G28&H28 -> 交際費 | F28: 交際費 | J28: 124321 | K28: 34454 | L28: 0 | M28: 0 | N28: 0 | O28: 0 | P28: 0 | Q28: 0 | R28: 0 | S28: 0 | T28: 0 | U28: 0 | V28: 158775
A29: {=XLOOKUP(C29, 'マスタ'!$C$2:$C$312, 'マスタ'!$D$2:$D$312, "マスタ未登録")} -> 旅費交通費 | B29: =IF(AND(C29<>"", COUNTIF('マスタ'!$C:$C, C29)=0), "マスタ未登録", "") | C29: =D29&D134&E29&F29&G29&H29 -> 旅費交通費 | F29: 旅費交通費 | J29: 143057 | K29: 105502 | L29: 0 | M29: 0 | N29: 0 | O29: 0 | P29: 0 | Q29: 0 | R29: 0 | S29: 0 | T29: 0 | U29: 0 | V29: 248559
A30: {=XLOOKUP(C30, 'マスタ'!$C$2:$C$312, 'マスタ'!$D$2:$D$312, "マスタ未登録")} -> 通信費 | B30: =IF(AND(C30<>"", COUNTIF('マスタ'!$C:$C, C30)=0), "マスタ未登録", "") | C30: =D30&D135&E30&F30&G30&H30 -> 通信費 | F30: 通信費 | J30: 157510 | K30: 328433 | L30: 33326 | M30: 0 | N30: 0 | O30: 0 | P30: 0 | Q30: 0 | R30: 0 | S30: 0 | T30: 0 | U30: 0 | V30: 519269
A31: {=XLOOKUP(C31, 'マスタ'!$C$2:$C$312, 'マスタ'!$D$2:$D$312, "マスタ未登録")} -> 消耗品費 | B31: =IF(AND(C31<>"", COUNTIF('マスタ'!$C:$C, C31)=0), "マスタ未登録", "") | C31: =D31&D136&E31&F31&G31&H31 -> 消耗品費 | F31: 消耗品費 | J31: 54825 | K31: 21018 | L31: 1174 | M31: 0 | N31: 0 | O31: 0 | P31: 0 | Q31: 0 | R31: 0 | S31: 0 | T31: 0 | U31: 0 | V31: 77017
A32: {=XLOOKUP(C32, 'マスタ'!$C$2:$C$312, 'マスタ'!$D$2:$D$312, "マスタ未登録")} -> 諸会費 | B32: =IF(AND(C32<>"", COUNTIF('マスタ'!$C:$C, C32)=0), "マスタ未登録", "") | C32: =D32&D137&E32&F32&G32&H32 -> 諸会費 | F32: 諸会費 | J32: 600 | K32: 600 | L32: 0 | M32: 0 | N32: 0 | O32: 0 | P32: 0 | Q32: 0 | R32: 0 | S32: 0 | T32: 0 | U32: 0 | V32: 1200
A33: {=XLOOKUP(C33, 'マスタ'!$C$2:$C$312, 'マスタ'!$D$2:$D$312, "マスタ未登録")} -> 支払手数料 | B33: =IF(AND(C33<>"", COUNTIF('マスタ'!$C:$C, C33)=0), "マスタ未登録", "") | C33: =D33&D138&E33&F33&G33&H33 -> 支払手数料 | F33: 支払手数料 | J33: 25482 | K33: 19700 | L33: 0 | M33: 0 | N33: 0 | O33: 0 | P33: 0 | Q33: 0 | R33: 0 | S33: 0 | T33: 0 | U33: 0 | V33: 45182
A34: {=XLOOKUP(C34, 'マスタ'!$C$2:$C$312, 'マスタ'!$D$2:$D$312, "マスタ未登録")} -> 地代家賃 | B34: =IF(AND(C34<>"", COUNTIF('マスタ'!$C:$C, C34)=0), "マスタ未登録", "") | C34: =D34&D139&E34&F34&G34&H34 -> 地代家賃 | F34: 地代家賃 | J34: 150000 | K34: 170000 | L34: 0 | M34: 0 | N34: 0 | O34: 0 | P34: 0 | Q34: 0 | R34: 0 | S34: 0 | T34: 0 | U34: 0 | V34: 320000
... A38: {=XLOOKUP(C38, 'マスタ'!$C$2:$C$312, 'マスタ'!$D$2:$D$312, "マスタ未登録")} -> 減価償却費 | B38: =IF(AND(C38<>"", COUNTIF('マスタ'!$C:$C, C38)=0), "マスタ未登録", "") | C38: =D38&D143&E38&F38&G38&H38 -> 減価償却費 | F38: 減価償却費 | J38: 12191 | K38: 12191 | L38: 12191 | M38: 12191 | N38: 12191 | O38: 12191 | P38: 12191 | Q38: 12191 | R38: 12191 | S38: 12191 | T38: 12191 | U38: 12197 | V38: 146298
A39: {=XLOOKUP(C39, 'マスタ'!$C$2:$C$312, 'マスタ'!$D$2:$D$312, "マスタ未登録")} -> マスタ未登録 | B39: =IF(AND(C39<>"", COUNTIF('マスタ'!$C:$C, C39)=0), "マスタ未登録", "") -> マスタ未登録 | C39: =D39&D144&E39&F39&G39&H39 -> 販売管理費 計 | E39: 販売管理費 計 | J39: 2532557 | K39: 2836114 | L39: 101691 | M39: 67191 | N39: 67191 | O39: 67191 | P39: 67191 | Q39: 67191 | R39: 67191 | S39: 67191 | T39: 67191 | U39: 67197 | V39: 6075087
A40: {=XLOOKUP(C40, 'マスタ'!$C$2:$C$312, 'マスタ'!$D$2:$D$312, "マスタ未登録")} -> マスタ未登録 | B40: =IF(AND(C40<>"", COUNTIF('マスタ'!$C:$C, C40)=0), "マスタ未登録", "") -> マスタ未登録 | C40: =D40&D145&E40&F40&G40&H40 -> 営業損益金額 | D40: 営業損益金額 | J40: 5545178 | K40: 13481433 | L40: -786379 | M40: -529118 | N40: -529118 | O40: -529118 | P40: -529118 | Q40: -529118 | R40: -529118 | S40: -529118 | T40: -529118 | U40: -529154 | V40: 13478134
A41: {=XLOOKUP(C41, 'マスタ'!$C$2:$C$312, 'マスタ'!$D$2:$D$312, "マスタ未登録")} -> マスタ未登録 | B41: =IF(AND(C41<>"", COUNTIF('マスタ'!$C:$C, C41)=0), "マスタ未登録", "") -> マスタ未登録 | C41: =D41&D146&E41&F41&G41&H41 -> 営業外収益 | E41: 営業外収益 | J41: 1088 | K41: 1248 | L41: 0 | M41: 0 | N41: 0 | O41: 0 | P41: 0 | Q41: 0 | R41: 0 | S41: 0 | T41: 0 | U41: 0 | V41: 2336
A42: {=XLOOKUP(C42, 'マスタ'!$C$2:$C$312, 'マスタ'!$D$2:$D$312, "マスタ未登録")} -> 受取利息 | B42: =IF(AND(C42<>"", COUNTIF('マスタ'!$C:$C, C42)=0), "マスタ未登録", "") | C42: =D42&D147&E42&F42&G42&H42 -> 受取利息 | F42: 受取利息 | J42: 1088 | K42: 1248 | L42: 0 | M42: 0 | N42: 0 | O42: 0 | P42: 0 | Q42: 0 | R42: 0 | S42: 0 | T42: 0 | U42: 0 | V42: 2336
A43: {=XLOOKUP(C43, 'マスタ'!$C$2:$C$312, 'マスタ'!$D$2:$D$312, "マスタ未登録")} -> マスタ未登録 | B43: =IF(AND(C43<>"", COUNTIF('マスタ'!$C:$C, C43)=0), "マスタ未登録", "") -> マスタ未登録 | C43: =D43&D148&E43&F43&G43&H43 -> 営業外費用 | E43: 営業外費用 | J43: 8326 | K43: 0 | L43: 0 | M43: 0 | N43: 0 | O43: 0 | P43: 0 | Q43: 0 | R43: 0 | S43: 0 | T43: 0 | U43: 0 | V43: 8326
A44: {=XLOOKUP(C44, 'マスタ'!$C$2:$C$312, 'マスタ'!$D$2:$D$312, "マスタ未登録")} -> 支払利息 | B44: =IF(AND(C44<>"", COUNTIF('マスタ'!$C:$C, C44)=0), "マスタ未登録", "") | C44: =D44&D149&E44&F44&G44&H44 -> 支払利息 | F44: 支払利息 | J44: 8326 | K44: 0 | L44: 0 | M44: 0 | N44: 0 | O44: 0 | P44: 0 | Q44: 0 | R44: 0 | S44: 0 | T44: 0 | U44: 0 | V44: 8326
A45: {=XLOOKUP(C45, 'マスタ'!$C$2:$C$312, 'マスタ'!$D$2:$D$312, "マスタ未登録")} -> マスタ未登録 | B45: =IF(AND(C45<>"", COUNTIF('マスタ'!$C:$C, C45)=0), "マスタ未登録", "") -> マスタ未登録 | C45: =D45&D150&E45&F45&G45&H45 -> 経常損益金額 | D45: 経常損益金額 | J45: 5537940 | K45: 13482681 | L45: -786379 | M45: -529118 | N45: -529118 | O45: -529118 | P45: -529118 | Q45: -529118 | R45: -529118 | S45: -529118 | T45: -529118 | U45: -529154 | V45: 13472144
A46: {=XLOOKUP(C46, 'マスタ'!$C$2:$C$312, 'マスタ'!$D$2:$D$312, "マスタ未登録")} -> マスタ未登録 | B46: =IF(AND(C46<>"", COUNTIF('マスタ'!$C:$C, C46)=0), "マスタ未登録", "") -> マスタ未登録 | C46: =D46&D151&E46&F46&G46&H46 -> 特別利益 | E46: 特別利益 | J46: 0 | K46: 0 | L46: 0 | M46: 0 | N46: 0 | O46: 0 | P46: 0 | Q46: 0 | R46: 0 | S46: 0 | T46: 0 | U46: 0 | V46: 0
A47: {=XLOOKUP(C47, 'マスタ'!$C$2:$C$312, 'マスタ'!$D$2:$D$312, "マスタ未登録")} -> マスタ未登録 | B47: =IF(AND(C47<>"", COUNTIF('マスタ'!$C:$C, C47)=0), "マスタ未登録", "") -> マスタ未登録 | C47: =D47&D152&E47&F47&G47&H47 -> 特別損失 | E47: 特別損失 | J47: 0 | K47: 0 | L47: 0 | M47: 0 | N47: 0 | O47: 0 | P47: 0 | Q47: 0 | R47: 0 | S47: 0 | T47: 0 | U47: 0 | V47: 0
A48: {=XLOOKUP(C48, 'マスタ'!$C$2:$C$312, 'マスタ'!$D$2:$D$312, "マスタ未登録")} -> マスタ未登録 | B48: =IF(AND(C48<>"", COUNTIF('マスタ'!$C:$C, C48)=0), "マスタ未登録", "") -> マスタ未登録 | C48: =D48&D153&E48&F48&G48&H48 -> 税引前当期純損益金額 | D48: 税引前当期純損益金額 | J48: 5537940 | K48: 13482681 | L48: -786379 | M48: -529118 | N48: -529118 | O48: -529118 | P48: -529118 | Q48: -529118 | R48: -529118 | S48: -529118 | T48: -529118 | U48: -529154 | V48: 13472144
A49: {=XLOOKUP(C49, 'マスタ'!$C$2:$C$312, 'マスタ'!$D$2:$D$312, "マスタ未登録")} -> 法人税等 | B49: =IF(AND(C49<>"", COUNTIF('マスタ'!$C:$C, C49)=0), "マスタ未登録", "") | C49: =D49&D154&E49&F49&G49&H49 -> 法人税等 | E49: 法人税等 | J49: 0 | K49: 191 | L49: 0 | M49: 0 | N49: 0 | O49: 0 | P49: 0 | Q49: 0 | R49: 0 | S49: 0 | T49: 0 | U49: 0 | V49: 191
A50: {=XLOOKUP(C50, 'マスタ'!$C$2:$C$312, 'マスタ'!$D$2:$D$312, "マスタ未登録")} -> 法人税等 | B50: =IF(AND(C50<>"", COUNTIF('マスタ'!$C:$C, C50)=0), "マスタ未登録", "") | C50: =D50&D155&E50&F50&G50&H50 -> 法人税等 | F50: 法人税等 | J50: 0 | K50: 191 | L50: 0 | M50: 0 | N50: 0 | O50: 0 | P50: 0 | Q50: 0 | R50: 0 | S50: 0 | T50: 0 | U50: 0 | V50: 191
E51: 法人税等調整額 | J51: 0 | K51: 0 | L51: 0 | M51: 0 | N51: 0 | O51: 0 | P51: 0 | Q51: 0 | R51: 0 | S51: 0 | T51: 0 | U51: 0 | V51: 0
D52: 当期純損益金額 | J52: 5537940 | K52: 13482490 | L52: -786379 | M52: -529118 | N52: -529118 | O52: -529118 | P52: -529118 | Q52: -529118 | R52: -529118 | S52: -529118 | T52: -529118 | U52: -529154 | V52: 13471953

Sheet UTAITE_PL
D1: 月次推移：損益計算書_株式会社UTAITE（期間：2026年04月〜2027年03月、表示単位：円）
J2: 46113 | K2: 46143 | L2: 46174 | M2: 46204 | N2: 46235 | O2: 46266 | P2: 46296 | Q2: 46327 | R2: 46357 | S2: 46388 | T2: 46419 | U2: 46447 | V2: 期間累計
A3: {=XLOOKUP(C3, 'マスタ'!$C$2:$C$312, 'マスタ'!$D$2:$D$312, "マスタ未登録")} -> マスタ未登録 | D3: 売上高
A4: {=XLOOKUP(C4, 'マスタ'!$C$2:$C$312, 'マスタ'!$D$2:$D$312, "マスタ未登録")} -> マスタ未登録 | B4: =IF(AND(C4<>"", COUNTIF('マスタ'!$C:$C, C4)=0), "マスタ未登録", "") -> マスタ未登録 | C4: =D4&D109&E4&F4&G4&H4 -> 売上高 計 | D4: 売上高 計 | J4: 0 | K4: 0 | L4: 0 | M4: 0 | N4: 0 | O4: 0 | P4: 0 | Q4: 0 | R4: 0 | S4: 0 | T4: 0 | U4: 0 | V4: 0
A5: {=XLOOKUP(C5, 'マスタ'!$C$2:$C$312, 'マスタ'!$D$2:$D$312, "マスタ未登録")} -> マスタ未登録 | B5: =IF(AND(C5<>"", COUNTIF('マスタ'!$C:$C, C5)=0), "マスタ未登録", "") -> マスタ未登録 | C5: =D5&D110&E5&F5&G5&H5 -> 売上原価 | E5: 売上原価
A6: {=XLOOKUP(C6, 'マスタ'!$C$2:$C$312, 'マスタ'!$D$2:$D$312, "マスタ未登録")} -> マスタ未登録 | B6: =IF(AND(C6<>"", COUNTIF('マスタ'!$C:$C, C6)=0), "マスタ未登録", "") -> マスタ未登録 | C6: =D6&D111&E6&F6&G6&H6 -> 売上原価 | E6: 売上原価 | J6: 0 | K6: 0 | L6: 0 | M6: 0 | N6: 0 | O6: 0 | P6: 0 | Q6: 0 | R6: 0 | S6: 0 | T6: 0 | U6: 0 | V6: 0
A7: {=XLOOKUP(C7, 'マスタ'!$C$2:$C$312, 'マスタ'!$D$2:$D$312, "マスタ未登録")} -> 期首商品棚卸高 | B7: =IF(AND(C7<>"", COUNTIF('マスタ'!$C:$C, C7)=0), "マスタ未登録", "") | C7: =D7&D112&E7&F7&G7&H7 -> 期首商品棚卸 | G7: 期首商品棚卸 | J7: 0 | K7: 0 | L7: 0 | M7: 0 | N7: 0 | O7: 0 | P7: 0 | Q7: 0 | R7: 0 | S7: 0 | T7: 0 | U7: 0 | V7: 0
A8: {=XLOOKUP(C8, 'マスタ'!$C$2:$C$312, 'マスタ'!$D$2:$D$312, "マスタ未登録")} -> 当期商品仕入高 | B8: =IF(AND(C8<>"", COUNTIF('マスタ'!$C:$C, C8)=0), "マスタ未登録", "") | C8: =D8&D113&E8&F8&G8&H8 -> 当期商品仕入 | G8: 当期商品仕入 | J8: 0 | K8: 0 | L8: 0 | M8: 0 | N8: 0 | O8: 0 | P8: 0 | Q8: 0 | R8: 0 | S8: 0 | T8: 0 | U8: 0 | V8: 0
A9: {=XLOOKUP(C9, 'マスタ'!$C$2:$C$312, 'マスタ'!$D$2:$D$312, "マスタ未登録")} -> 他勘定振替高 | B9: =IF(AND(C9<>"", COUNTIF('マスタ'!$C:$C, C9)=0), "マスタ未登録", "") | C9: =D9&D114&E9&F9&G9&H9 -> 他勘定振替高(商) | G9: 他勘定振替高(商) | J9: 0 | K9: 0 | L9: 0 | M9: 0 | N9: 0 | O9: 0 | P9: 0 | Q9: 0 | R9: 0 | S9: 0 | T9: 0 | U9: 0 | V9: 0
A10: {=XLOOKUP(C10, 'マスタ'!$C$2:$C$312, 'マスタ'!$D$2:$D$312, "マスタ未登録")} -> 期末商品棚卸高 | B10: =IF(AND(C10<>"", COUNTIF('マスタ'!$C:$C, C10)=0), "マスタ未登録", "") | C10: =D10&D115&E10&F10&G10&H10 -> 期末商品棚卸 | G10: 期末商品棚卸 | J10: 0 | K10: 0 | L10: 0 | M10: 0 | N10: 0 | O10: 0 | P10: 0 | Q10: 0 | R10: 0 | S10: 0 | T10: 0 | U10: 0 | V10: 0
A11: {=XLOOKUP(C11, 'マスタ'!$C$2:$C$312, 'マスタ'!$D$2:$D$312, "マスタ未登録")} -> マスタ未登録 | B11: =IF(AND(C11<>"", COUNTIF('マスタ'!$C:$C, C11)=0), "マスタ未登録", "") -> マスタ未登録 | C11: =D11&D116&E11&F11&G11&H11 -> 商品売上原価 | F11: 商品売上原価 | J11: 0 | K11: 0 | L11: 0 | M11: 0 | N11: 0 | O11: 0 | P11: 0 | Q11: 0 | R11: 0 | S11: 0 | T11: 0 | U11: 0 | V11: 0
A12: {=XLOOKUP(C12, 'マスタ'!$C$2:$C$312, 'マスタ'!$D$2:$D$312, "マスタ未登録")} -> マスタ未登録 | B12: =IF(AND(C12<>"", COUNTIF('マスタ'!$C:$C, C12)=0), "マスタ未登録", "") -> マスタ未登録 | C12: =D12&D117&E12&F12&G12&H12 -> 売上総損益金額 | D12: 売上総損益金額 | J12: 0 | K12: 0 | L12: 0 | M12: 0 | N12: 0 | O12: 0 | P12: 0 | Q12: 0 | R12: 0 | S12: 0 | T12: 0 | U12: 0 | V12: 0
A13: {=XLOOKUP(C13, 'マスタ'!$C$2:$C$312, 'マスタ'!$D$2:$D$312, "マスタ未登録")} -> マスタ未登録 | B13: =IF(AND(C13<>"", COUNTIF('マスタ'!$C:$C, C13)=0), "マスタ未登録", "") -> マスタ未登録 | C13: =D13&D118&E13&F13&G13&H13 -> 販売管理費 | E13: 販売管理費
A14: {=XLOOKUP(C14, 'マスタ'!$C$2:$C$312, 'マスタ'!$D$2:$D$312, "マスタ未登録")} -> 通信費 | B14: =IF(AND(C14<>"", COUNTIF('マスタ'!$C:$C, C14)=0), "マスタ未登録", "") | C14: =D14&D119&E14&F14&G14&H14 -> 通信費 | F14: 通信費 | J14: 0 | K14: 1955 | L14: 0 | M14: 0 | N14: 0 | O14: 0 | P14: 0 | Q14: 0 | R14: 0 | S14: 0 | T14: 0 | U14: 0 | V14: 1955
A15: {=XLOOKUP(C15, 'マスタ'!$C$2:$C$312, 'マスタ'!$D$2:$D$312, "マスタ未登録")} -> 支払報酬 | B15: =IF(AND(C15<>"", COUNTIF('マスタ'!$C:$C, C15)=0), "マスタ未登録", "") | C15: =D15&D120&E15&F15&G15&H15 -> 支払報酬料 | F15: 支払報酬料 | J15: 0 | K15: 55000 | L15: 0 | M15: 0 | N15: 0 | O15: 0 | P15: 0 | Q15: 0 | R15: 0 | S15: 0 | T15: 0 | U15: 0 | V15: 55000
A16: {=XLOOKUP(C16, 'マスタ'!$C$2:$C$312, 'マスタ'!$D$2:$D$312, "マスタ未登録")} -> 支払手数料 | B16: =IF(AND(C16<>"", COUNTIF('マスタ'!$C:$C, C16)=0), "マスタ未登録", "") | C16: =D16&D121&E16&F16&G16&H16 -> 支払手数料 | F16: 支払手数料 | J16: 4200 | K16: 6000 | L16: 1046 | M16: 0 | N16: 0 | O16: 0 | P16: 0 | Q16: 0 | R16: 0 | S16: 0 | T16: 0 | U16: 0 | V16: 11246
A17: {=XLOOKUP(C17, 'マスタ'!$C$2:$C$312, 'マスタ'!$D$2:$D$312, "マスタ未登録")} -> 租税公課 | B17: =IF(AND(C17<>"", COUNTIF('マスタ'!$C:$C, C17)=0), "マスタ未登録", "") | C17: =D17&D122&E17&F17&G17&H17 -> 租税公課 | F17: 租税公課 | J17: 0 | K17: 60820 | L17: 0 | M17: 0 | N17: 0 | O17: 0 | P17: 0 | Q17: 0 | R17: 0 | S17: 0 | T17: 0 | U17: 0 | V17: 60820
A18: {=XLOOKUP(C18, 'マスタ'!$C$2:$C$312, 'マスタ'!$D$2:$D$312, "マスタ未登録")} -> マスタ未登録 | B18: =IF(AND(C18<>"", COUNTIF('マスタ'!$C:$C, C18)=0), "マスタ未登録", "") -> マスタ未登録 | C18: =D18&D123&E18&F18&G18&H18 -> 販売管理費 計 | E18: 販売管理費 計 | J18: 4200 | K18: 123775 | L18: 1046 | M18: 0 | N18: 0 | O18: 0 | P18: 0 | Q18: 0 | R18: 0 | S18: 0 | T18: 0 | U18: 0 | V18: 129021
A19: {=XLOOKUP(C19, 'マスタ'!$C$2:$C$312, 'マスタ'!$D$2:$D$312, "マスタ未登録")} -> マスタ未登録 | B19: =IF(AND(C19<>"", COUNTIF('マスタ'!$C:$C, C19)=0), "マスタ未登録", "") -> マスタ未登録 | C19: =D19&D124&E19&F19&G19&H19 -> 営業損益金額 | D19: 営業損益金額 | J19: -4200 | K19: -123775 | L19: -1046 | M19: 0 | N19: 0 | O19: 0 | P19: 0 | Q19: 0 | R19: 0 | S19: 0 | T19: 0 | U19: 0 | V19: -129021
A20: {=XLOOKUP(C20, 'マスタ'!$C$2:$C$312, 'マスタ'!$D$2:$D$312, "マスタ未登録")} -> マスタ未登録 | B20: =IF(AND(C20<>"", COUNTIF('マスタ'!$C:$C, C20)=0), "マスタ未登録", "") -> マスタ未登録 | C20: =D20&D125&E20&F20&G20&H20 -> 営業外収益 | E20: 営業外収益 | J20: 0 | K20: 0 | L20: 0 | M20: 0 | N20: 0 | O20: 0 | P20: 0 | Q20: 0 | R20: 0 | S20: 0 | T20: 0 | U20: 0 | V20: 0
A21: {=XLOOKUP(C21, 'マスタ'!$C$2:$C$312, 'マスタ'!$D$2:$D$312, "マスタ未登録")} -> マスタ未登録 | B21: =IF(AND(C21<>"", COUNTIF('マスタ'!$C:$C, C21)=0), "マスタ未登録", "") -> マスタ未登録 | C21: =D21&D126&E21&F21&G21&H21 -> 営業外費用 | E21: 営業外費用 | J21: 0 | K21: 0 | L21: 0 | M21: 0 | N21: 0 | O21: 0 | P21: 0 | Q21: 0 | R21: 0 | S21: 0 | T21: 0 | U21: 0 | V21: 0
A22: {=XLOOKUP(C22, 'マスタ'!$C$2:$C$312, 'マスタ'!$D$2:$D$312, "マスタ未登録")} -> マスタ未登録 | B22: =IF(AND(C22<>"", COUNTIF('マスタ'!$C:$C, C22)=0), "マスタ未登録", "") -> マスタ未登録 | C22: =D22&D127&E22&F22&G22&H22 -> 経常損益金額 | D22: 経常損益金額 | J22: -4200 | K22: -123775 | L22: -1046 | M22: 0 | N22: 0 | O22: 0 | P22: 0 | Q22: 0 | R22: 0 | S22: 0 | T22: 0 | U22: 0 | V22: -129021
A23: {=XLOOKUP(C23, 'マスタ'!$C$2:$C$312, 'マスタ'!$D$2:$D$312, "マスタ未登録")} -> マスタ未登録 | B23: =IF(AND(C23<>"", COUNTIF('マスタ'!$C:$C, C23)=0), "マスタ未登録", "") -> マスタ未登録 | C23: =D23&D128&E23&F23&G23&H23 -> 特別利益 | E23: 特別利益 | J23: 0 | K23: 0 | L23: 0 | M23: 0 | N23: 0 | O23: 0 | P23: 0 | Q23: 0 | R23: 0 | S23: 0 | T23: 0 | U23: 0 | V23: 0
A24: {=XLOOKUP(C24, 'マスタ'!$C$2:$C$312, 'マスタ'!$D$2:$D$312, "マスタ未登録")} -> マスタ未登録 | B24: =IF(AND(C24<>"", COUNTIF('マスタ'!$C:$C, C24)=0), "マスタ未登録", "") -> マスタ未登録 | C24: =D24&D129&E24&F24&G24&H24 -> 特別損失 | E24: 特別損失 | J24: 0 | K24: 0 | L24: 0 | M24: 0 | N24: 0 | O24: 0 | P24: 0 | Q24: 0 | R24: 0 | S24: 0 | T24: 0 | U24: 0 | V24: 0
A25: {=XLOOKUP(C25, 'マスタ'!$C$2:$C$312, 'マスタ'!$D$2:$D$312, "マスタ未登録")} -> マスタ未登録 | B25: =IF(AND(C25<>"", COUNTIF('マスタ'!$C:$C, C25)=0), "マスタ未登録", "") -> マスタ未登録 | C25: =D25&D130&E25&F25&G25&H25 -> 税引前当期純損益金額 | D25: 税引前当期純損益金額 | J25: -4200 | K25: -123775 | L25: -1046 | M25: 0 | N25: 0 | O25: 0 | P25: 0 | Q25: 0 | R25: 0 | S25: 0 | T25: 0 | U25: 0 | V25: -129021
A26: {=XLOOKUP(C26, 'マスタ'!$C$2:$C$312, 'マスタ'!$D$2:$D$312, "マスタ未登録")} -> 法人税等 | B26: =IF(AND(C26<>"", COUNTIF('マスタ'!$C:$C, C26)=0), "マスタ未登録", "") | C26: =D26&D131&E26&F26&G26&H26 -> 法人税等 | E26: 法人税等 | J26: 0 | K26: 0 | L26: 0 | M26: 0 | N26: 0 | O26: 0 | P26: 0 | Q26: 0 | R26: 0 | S26: 0 | T26: 0 | U26: 0 | V26: 0
A27: {=XLOOKUP(C27, 'マスタ'!$C$2:$C$312, 'マスタ'!$D$2:$D$312, "マスタ未登録")} -> 法人税等調整額 | B27: =IF(AND(C27<>"", COUNTIF('マスタ'!$C:$C, C27)=0), "マスタ未登録", "") | C27: =D27&D132&E27&F27&G27&H27 -> 法人税等調整額 | E27: 法人税等調整額 | J27: 0 | K27: 0 | L27: 0 | M27: 0 | N27: 0 | O27: 0 | P27: 0 | Q27: 0 | R27: 0 | S27: 0 | T27: 0 | U27: 0 | V27: 0
A28: {=XLOOKUP(C28, 'マスタ'!$C$2:$C$312, 'マスタ'!$D$2:$D$312, "マスタ未登録")} -> マスタ未登録 | B28: =IF(AND(C28<>"", COUNTIF('マスタ'!$C:$C, C28)=0), "マスタ未登録", "") -> マスタ未登録 | C28: =D28&D133&E28&F28&G28&H28 -> 当期純損益金額 | D28: 当期純損益金額 | J28: -4200 | K28: -123775 | L28: -1046 | M28: 0 | N28: 0 | O28: 0 | P28: 0 | Q28: 0 | R28: 0 | S28: 0 | T28: 0 | U28: 0 | V28: -129021

Sheet MD1_PL
D1: MD1
F2: 46113 | G2: 46143 | H2: 46174 | I2: 46204 | J2: 46235 | K2: 46266 | L2: 46296 | M2: 46327 | N2: 46357 | O2: 46388 | P2: 46419 | Q2: 46447 | R2: 決算整理 | S2: 合計
A3: {=XLOOKUP(C3, 'マスタ'!$C$2:$C$312, 'マスタ'!$D$2:$D$312, "マスタ未登録")} -> マスタ未登録 | D3: 売上高
A4: {=XLOOKUP(C4, 'マスタ'!$C$2:$C$312, 'マスタ'!$D$2:$D$312, "マスタ未登録")} -> マスタ未登録 | B4: =IF(AND(C4<>"", COUNTIF('マスタ'!$C:$C, C4)=0), "マスタ未登録", "") -> マスタ未登録 | C4: =D4&D109&E4&F4&G4&H4 -> 売上高00 | E4: 売上高 | F4: 0 | G4: 0 | S4: 0
A5: {=XLOOKUP(C5, 'マスタ'!$C$2:$C$312, 'マスタ'!$D$2:$D$312, "マスタ未登録")} -> マスタ未登録 | B5: =IF(AND(C5<>"", COUNTIF('マスタ'!$C:$C, C5)=0), "マスタ未登録", "") -> マスタ未登録 | C5: =D5&D110&E5&F5&G5&H5 -> 売上高合計00 | D5: 売上高合計 | F5: 0 | G5: 0 | S5: 0
A6: {=XLOOKUP(C6, 'マスタ'!$C$2:$C$312, 'マスタ'!$D$2:$D$312, "マスタ未登録")} -> マスタ未登録 | B6: =IF(AND(C6<>"", COUNTIF('マスタ'!$C:$C, C6)=0), "マスタ未登録", "") -> マスタ未登録 | C6: =D6&D111&E6&F6&G6&H6 -> 売上原価 | D6: 売上原価
A7: {=XLOOKUP(C7, 'マスタ'!$C$2:$C$312, 'マスタ'!$D$2:$D$312, "マスタ未登録")} -> マスタ未登録 | B7: =IF(AND(C7<>"", COUNTIF('マスタ'!$C:$C, C7)=0), "マスタ未登録", "") -> マスタ未登録 | C7: =D7&D112&E7&F7&G7&H7 -> 売上原価合計00 | D7: 売上原価合計 | F7: 0 | G7: 0 | S7: 0
A8: {=XLOOKUP(C8, 'マスタ'!$C$2:$C$312, 'マスタ'!$D$2:$D$312, "マスタ未登録")} -> マスタ未登録 | B8: =IF(AND(C8<>"", COUNTIF('マスタ'!$C:$C, C8)=0), "マスタ未登録", "") -> マスタ未登録 | C8: =D8&D113&E8&F8&G8&H8 -> 売上総利益00 | D8: 売上総利益 | F8: 0 | G8: 0 | S8: 0
A9: {=XLOOKUP(C9, 'マスタ'!$C$2:$C$312, 'マスタ'!$D$2:$D$312, "マスタ未登録")} -> マスタ未登録 | B9: =IF(AND(C9<>"", COUNTIF('マスタ'!$C:$C, C9)=0), "マスタ未登録", "") -> マスタ未登録 | C9: =D9&D114&E9&F9&G9&H9 -> 販売費及び一般管理費 | D9: 販売費及び一般管理費
A10: {=XLOOKUP(C10, 'マスタ'!$C$2:$C$312, 'マスタ'!$D$2:$D$312, "マスタ未登録")} -> マスタ未登録 | B10: =IF(AND(C10<>"", COUNTIF('マスタ'!$C:$C, C10)=0), "マスタ未登録", "") -> マスタ未登録 | C10: =D10&D115&E10&F10&G10&H10 -> 消耗品費00 | E10: 消耗品費 | F10: 0 | G10: 0 | S10: 0
A11: {=XLOOKUP(C11, 'マスタ'!$C$2:$C$312, 'マスタ'!$D$2:$D$312, "マスタ未登録")} -> マスタ未登録 | B11: =IF(AND(C11<>"", COUNTIF('マスタ'!$C:$C, C11)=0), "マスタ未登録", "") -> マスタ未登録 | C11: =D11&D116&E11&F11&G11&H11 -> 租税公課00 | E11: 租税公課 | F11: 0 | G11: 0 | S11: 0
A12: {=XLOOKUP(C12, 'マスタ'!$C$2:$C$312, 'マスタ'!$D$2:$D$312, "マスタ未登録")} -> マスタ未登録 | B12: =IF(AND(C12<>"", COUNTIF('マスタ'!$C:$C, C12)=0), "マスタ未登録", "") -> マスタ未登録 | C12: =D12&D117&E12&F12&G12&H12 -> 支払手数料00 | E12: 支払手数料 | F12: 0 | G12: 0 | S12: 0
A13: {=XLOOKUP(C13, 'マスタ'!$C$2:$C$312, 'マスタ'!$D$2:$D$312, "マスタ未登録")} -> マスタ未登録 | B13: =IF(AND(C13<>"", COUNTIF('マスタ'!$C:$C, C13)=0), "マスタ未登録", "") -> マスタ未登録 | C13: =D13&D118&E13&F13&G13&H13 -> 支払報酬00 | E13: 支払報酬 | F13: 0 | G13: 0 | S13: 0
A14: {=XLOOKUP(C14, 'マスタ'!$C$2:$C$312, 'マスタ'!$D$2:$D$312, "マスタ未登録")} -> マスタ未登録 | B14: =IF(AND(C14<>"", COUNTIF('マスタ'!$C:$C, C14)=0), "マスタ未登録", "") -> マスタ未登録 | C14: =D14&D119&E14&F14&G14&H14 -> 販売費及び一般管理費合計00 | D14: 販売費及び一般管理費合計 | F14: 0 | G14: 0 | S14: 0
A15: {=XLOOKUP(C15, 'マスタ'!$C$2:$C$312, 'マスタ'!$D$2:$D$312, "マスタ未登録")} -> マスタ未登録 | B15: =IF(AND(C15<>"", COUNTIF('マスタ'!$C:$C, C15)=0), "マスタ未登録", "") -> マスタ未登録 | C15: =D15&D120&E15&F15&G15&H15 -> 営業利益00 | D15: 営業利益 | F15: 0 | G15: 0 | S15: 0
A16: {=XLOOKUP(C16, 'マスタ'!$C$2:$C$312, 'マスタ'!$D$2:$D$312, "マスタ未登録")} -> マスタ未登録 | B16: =IF(AND(C16<>"", COUNTIF('マスタ'!$C:$C, C16)=0), "マスタ未登録", "") -> マスタ未登録 | C16: =D16&D121&E16&F16&G16&H16 -> 受取利息00 | E16: 受取利息 | F16: 0 | G16: 0 | S16: 0
A17: {=XLOOKUP(C17, 'マスタ'!$C$2:$C$312, 'マスタ'!$D$2:$D$312, "マスタ未登録")} -> マスタ未登録 | B17: =IF(AND(C17<>"", COUNTIF('マスタ'!$C:$C, C17)=0), "マスタ未登録", "") -> マスタ未登録 | C17: =D17&D122&E17&F17&G17&H17 -> 営業外収益00 | D17: 営業外収益 | F17: 0 | G17: 0 | S17: 0
A18: {=XLOOKUP(C18, 'マスタ'!$C$2:$C$312, 'マスタ'!$D$2:$D$312, "マスタ未登録")} -> マスタ未登録 | B18: =IF(AND(C18<>"", COUNTIF('マスタ'!$C:$C, C18)=0), "マスタ未登録", "") -> マスタ未登録 | C18: =D18&D123&E18&F18&G18&H18 -> 営業外収益合計00 | D18: 営業外収益合計 | F18: 0 | G18: 0 | S18: 0
A19: {=XLOOKUP(C19, 'マスタ'!$C$2:$C$312, 'マスタ'!$D$2:$D$312, "マスタ未登録")} -> マスタ未登録 | B19: =IF(AND(C19<>"", COUNTIF('マスタ'!$C:$C, C19)=0), "マスタ未登録", "") -> マスタ未登録 | C19: =D19&D124&E19&F19&G19&H19 -> 営業外費用00 | D19: 営業外費用 | F19: 0 | G19: 0 | S19: 0
A20: {=XLOOKUP(C20, 'マスタ'!$C$2:$C$312, 'マスタ'!$D$2:$D$312, "マスタ未登録")} -> マスタ未登録 | B20: =IF(AND(C20<>"", COUNTIF('マスタ'!$C:$C, C20)=0), "マスタ未登録", "") -> マスタ未登録 | C20: =D20&D125&E20&F20&G20&H20 -> 営業外費用合計00 | D20: 営業外費用合計 | F20: 0 | G20: 0 | S20: 0
A21: {=XLOOKUP(C21, 'マスタ'!$C$2:$C$312, 'マスタ'!$D$2:$D$312, "マスタ未登録")} -> マスタ未登録 | B21: =IF(AND(C21<>"", COUNTIF('マスタ'!$C:$C, C21)=0), "マスタ未登録", "") -> マスタ未登録 | C21: =D21&D126&E21&F21&G21&H21 -> 経常利益00 | D21: 経常利益 | F21: 0 | G21: 0 | S21: 0
A22: {=XLOOKUP(C22, 'マスタ'!$C$2:$C$312, 'マスタ'!$D$2:$D$312, "マスタ未登録")} -> マスタ未登録 | B22: =IF(AND(C22<>"", COUNTIF('マスタ'!$C:$C, C22)=0), "マスタ未登録", "") -> マスタ未登録 | C22: =D22&D127&E22&F22&G22&H22 -> 特別利益00 | D22: 特別利益 | F22: 0 | G22: 0 | S22: 0
A23: {=XLOOKUP(C23, 'マスタ'!$C$2:$C$312, 'マスタ'!$D$2:$D$312, "マスタ未登録")} -> マスタ未登録 | B23: =IF(AND(C23<>"", COUNTIF('マスタ'!$C:$C, C23)=0), "マスタ未登録", "") -> マスタ未登録 | C23: =D23&D128&E23&F23&G23&H23 -> 特別利益合計00 | D23: 特別利益合計 | F23: 0 | G23: 0 | S23: 0
A24: {=XLOOKUP(C24, 'マスタ'!$C$2:$C$312, 'マスタ'!$D$2:$D$312, "マスタ未登録")} -> マスタ未登録 | B24: =IF(AND(C24<>"", COUNTIF('マスタ'!$C:$C, C24)=0), "マスタ未登録", "") -> マスタ未登録 | C24: =D24&D129&E24&F24&G24&H24 -> 特別損失00 | D24: 特別損失 | F24: 0 | G24: 0 | S24: 0
A25: {=XLOOKUP(C25, 'マスタ'!$C$2:$C$312, 'マスタ'!$D$2:$D$312, "マスタ未登録")} -> マスタ未登録 | B25: =IF(AND(C25<>"", COUNTIF('マスタ'!$C:$C, C25)=0), "マスタ未登録", "") -> マスタ未登録 | C25: =D25&D130&E25&F25&G25&H25 -> 特別損失合計00 | D25: 特別損失合計 | F25: 0 | G25: 0 | S25: 0
A26: {=XLOOKUP(C26, 'マスタ'!$C$2:$C$312, 'マスタ'!$D$2:$D$312, "マスタ未登録")} -> マスタ未登録 | B26: =IF(AND(C26<>"", COUNTIF('マスタ'!$C:$C, C26)=0), "マスタ未登録", "") -> マスタ未登録 | C26: =D26&D131&E26&F26&G26&H26 -> 税引前当期純利益00 | D26: 税引前当期純利益 | F26: 0 | G26: 0 | S26: 0
A27: {=XLOOKUP(C27, 'マスタ'!$C$2:$C$312, 'マスタ'!$D$2:$D$312, "マスタ未登録")} -> マスタ未登録 | B27: =IF(AND(C27<>"", COUNTIF('マスタ'!$C:$C, C27)=0), "マスタ未登録", "") -> マスタ未登録 | C27: =D27&D132&E27&F27&G27&H27 -> 法人税00 | D27: 法人税 | F27: 0 | G27: 0 | S27: 0
A28: {=XLOOKUP(C28, 'マスタ'!$C$2:$C$312, 'マスタ'!$D$2:$D$312, "マスタ未登録")} -> マスタ未登録 | B28: =IF(AND(C28<>"", COUNTIF('マスタ'!$C:$C, C28)=0), "マスタ未登録", "") -> マスタ未登録 | C28: =D28&D133&E28&F28&G28&H28 -> 当期純利益00 | D28: 当期純利益 | F28: 0 | G28: 0 | S28: 0

Sheet VO_PL
B1: ②マスタ結びつけ | C1: ① | D1: 月次推移：損益計算書_株式会社VOISING（期間：2026年04月〜2027年03月、表示単位：円）
J2: 46113 | K2: 46143 | L2: 46174 | M2: 46204 | N2: 46235 | O2: 46266 | P2: 46296 | Q2: 46327 | R2: 46357 | S2: 46388 | T2: 46419 | U2: 46447 | V2: 期間累計
D3: 売上高
A4: {=XLOOKUP(C4, 'マスタ'!$C$2:$C$312, 'マスタ'!$D$2:$D$312, "マスタ未登録")} -> 売上高 | B4: =IF(AND(C4<>"", COUNTIF('マスタ'!$C:$C, C4)=0), "マスタ未登録", "") | C4: =D4&D109&E4&F4&G4&H4 -> 売上高 | E4: 売上高 | J4: 129158562 | K4: 0 | L4: 0 | M4: 0 | N4: 0 | O4: 0 | P4: 0 | Q4: 0 | R4: 0 | S4: 0 | T4: 0 | U4: 0 | V4: 129158562
A5: {=XLOOKUP(C5, 'マスタ'!$C$2:$C$312, 'マスタ'!$D$2:$D$312, "マスタ未登録")} -> 売上高 | B5: =IF(AND(C5<>"", COUNTIF('マスタ'!$C:$C, C5)=0), "マスタ未登録", "") | C5: =D5&D110&E5&F5&G5&H5 -> 委託販売売上高 | E5: 委託販売売上高 | J5: 6904597 | K5: 0 | L5: 0 | M5: 0 | N5: 0 | O5: 0 | P5: 0 | Q5: 0 | R5: 0 | S5: 0 | T5: 0 | U5: 0 | V5: 6904597
A6: {=XLOOKUP(C6, 'マスタ'!$C$2:$C$312, 'マスタ'!$D$2:$D$312, "マスタ未登録")} -> マスタ未登録 | B6: =IF(AND(C6<>"", COUNTIF('マスタ'!$C:$C, C6)=0), "マスタ未登録", "") -> マスタ未登録 | C6: =D6&D111&E6&F6&G6&H6 -> 売上高 計 | D6: 売上高 計 | J6: 136063159 | K6: 0 | L6: 0 | M6: 0 | N6: 0 | O6: 0 | P6: 0 | Q6: 0 | R6: 0 | S6: 0 | T6: 0 | U6: 0 | V6: 136063159
A7: {=XLOOKUP(C7, 'マスタ'!$C$2:$C$312, 'マスタ'!$D$2:$D$312, "マスタ未登録")} -> マスタ未登録 | B7: =IF(AND(C7<>"", COUNTIF('マスタ'!$C:$C, C7)=0), "マスタ未登録", "") -> マスタ未登録 | C7: =D7&D112&E7&F7&G7&H7 -> 売上原価 | E7: 売上原価
A8: {=XLOOKUP(C8, 'マスタ'!$C$2:$C$312, 'マスタ'!$D$2:$D$312, "マスタ未登録")} -> マスタ未登録 | B8: =IF(AND(C8<>"", COUNTIF('マスタ'!$C:$C, C8)=0), "マスタ未登録", "") -> マスタ未登録 | C8: =D8&D113&E8&F8&G8&H8 -> 売上原価 | E8: 売上原価 | J8: 159509316 | K8: 9834167 | L8: 0 | M8: 0 | N8: 0 | O8: 0 | P8: 0 | Q8: 0 | R8: 0 | S8: 0 | T8: 0 | U8: 0 | V8: 169343483
A9: {=XLOOKUP(C9, 'マスタ'!$C$2:$C$312, 'マスタ'!$D$2:$D$312, "マスタ未登録")} -> 期首商品棚卸高 | B9: =IF(AND(C9<>"", COUNTIF('マスタ'!$C:$C, C9)=0), "マスタ未登録", "") | C9: =D9&D114&E9&F9&G9&H9 -> 期首商品棚卸 | G9: 期首商品棚卸 | J9: 0 | K9: 0 | L9: 0 | M9: 0 | N9: 0 | O9: 0 | P9: 0 | Q9: 0 | R9: 0 | S9: 0 | T9: 0 | U9: 0 | V9: 0
A10: {=XLOOKUP(C10, 'マスタ'!$C$2:$C$312, 'マスタ'!$D$2:$D$312, "マスタ未登録")} -> 当期商品仕入高 | B10: =IF(AND(C10<>"", COUNTIF('マスタ'!$C:$C, C10)=0), "マスタ未登録", "") | C10: =D10&D115&E10&F10&G10&H10 -> 当期商品仕入 | G10: 当期商品仕入 | J10: 155220049 | K10: 2355194 | L10: 0 | M10: 0 | N10: 0 | O10: 0 | P10: 0 | Q10: 0 | R10: 0 | S10: 0 | T10: 0 | U10: 0 | V10: 157575243
A11: {=XLOOKUP(C11, 'マスタ'!$C$2:$C$312, 'マスタ'!$D$2:$D$312, "マスタ未登録")} -> 当期商品仕入高 | B11: =IF(AND(C11<>"", COUNTIF('マスタ'!$C:$C, C11)=0), "マスタ未登録", "") | C11: =D11&D116&E11&F11&G11&H11 -> 仕入高 | H11: 仕入高 | J11: 6881986 | K11: 0 | L11: 0 | M11: 0 | N11: 0 | O11: 0 | P11: 0 | Q11: 0 | R11: 0 | S11: 0 | T11: 0 | U11: 0 | V11: 6881986
A12: {=XLOOKUP(C12, 'マスタ'!$C$2:$C$312, 'マスタ'!$D$2:$D$312, "マスタ未登録")} -> 当期商品仕入高 | B12: =IF(AND(C12<>"", COUNTIF('マスタ'!$C:$C, C12)=0), "マスタ未登録", "") | C12: =D12&D117&E12&F12&G12&H12 -> 給料手当(原・ビ) | H12: 給料手当(原・ビ) | J12: 8052485 | K12: 0 | L12: 0 | M12: 0 | N12: 0 | O12: 0 | P12: 0 | Q12: 0 | R12: 0 | S12: 0 | T12: 0 | U12: 0 | V12: 8052485
A13: {=XLOOKUP(C13, 'マスタ'!$C$2:$C$312, 'マスタ'!$D$2:$D$312, "マスタ未登録")} -> 当期商品仕入高 | B13: =IF(AND(C13<>"", COUNTIF('マスタ'!$C:$C, C13)=0), "マスタ未登録", "") | C13: =D13&D118&E13&F13&G13&H13 -> 給料手当(原・製) | H13: 給料手当(原・製) | J13: 27763461 | K13: 0 | L13: 0 | M13: 0 | N13: 0 | O13: 0 | P13: 0 | Q13: 0 | R13: 0 | S13: 0 | T13: 0 | U13: 0 | V13: 27763461
A14: {=XLOOKUP(C14, 'マスタ'!$C$2:$C$312, 'マスタ'!$D$2:$D$312, "マスタ未登録")} -> 当期商品仕入高 | B14: =IF(AND(C14<>"", COUNTIF('マスタ'!$C:$C, C14)=0), "マスタ未登録", "") | C14: =D14&D119&E14&F14&G14&H14 -> 法定福利費(原・ビ) | H14: 法定福利費(原・ビ) | J14: 1179172 | K14: 0 | L14: 0 | M14: 0 | N14: 0 | O14: 0 | P14: 0 | Q14: 0 | R14: 0 | S14: 0 | T14: 0 | U14: 0 | V14: 1179172
A15: {=XLOOKUP(C15, 'マスタ'!$C$2:$C$312, 'マスタ'!$D$2:$D$312, "マスタ未登録")} -> 当期商品仕入高 | B15: =IF(AND(C15<>"", COUNTIF('マスタ'!$C:$C, C15)=0), "マスタ未登録", "") | C15: =D15&D120&E15&F15&G15&H15 -> 法定福利費(原・製) | H15: 法定福利費(原・製) | J15: 4588449 | K15: 0 | L15: 0 | M15: 0 | N15: 0 | O15: 0 | P15: 0 | Q15: 0 | R15: 0 | S15: 0 | T15: 0 | U15: 0 | V15: 4588449
A16: {=XLOOKUP(C16, 'マスタ'!$C$2:$C$312, 'マスタ'!$D$2:$D$312, "マスタ未登録")} -> 当期商品仕入高 | B16: =IF(AND(C16<>"", COUNTIF('マスタ'!$C:$C, C16)=0), "マスタ未登録", "") | C16: =D16&D121&E16&F16&G16&H16 -> 外注費(原) | H16: 外注費(原) | J16: 57149571 | K16: 1451755 | L16: 0 | M16: 0 | N16: 0 | O16: 0 | P16: 0 | Q16: 0 | R16: 0 | S16: 0 | T16: 0 | U16: 0 | V16: 58601326
A17: {=XLOOKUP(C17, 'マスタ'!$C$2:$C$312, 'マスタ'!$D$2:$D$312, "マスタ未登録")} -> 当期商品仕入高 | B17: =IF(AND(C17<>"", COUNTIF('マスタ'!$C:$C, C17)=0), "マスタ未登録", "") | C17: =D17&D122&E17&F17&G17&H17 -> 業務委託費(原・タレント) | H17: 業務委託費(原・タレント) | J17: 25778039 | K17: 0 | L17: 0 | M17: 0 | N17: 0 | O17: 0 | P17: 0 | Q17: 0 | R17: 0 | S17: 0 | T17: 0 | U17: 0 | V17: 25778039
A18: {=XLOOKUP(C18, 'マスタ'!$C$2:$C$312, 'マスタ'!$D$2:$D$312, "マスタ未登録")} -> 当期商品仕入高 | B18: =IF(AND(C18<>"", COUNTIF('マスタ'!$C:$C, C18)=0), "マスタ未登録", "") | C18: =D18&D123&E18&F18&G18&H18 -> 業務委託費(原・製) | H18: 業務委託費(原・製) | J18: 15445571 | K18: 0 | L18: 0 | M18: 0 | N18: 0 | O18: 0 | P18: 0 | Q18: 0 | R18: 0 | S18: 0 | T18: 0 | U18: 0 | V18: 15445571
A19: {=XLOOKUP(C19, 'マスタ'!$C$2:$C$312, 'マスタ'!$D$2:$D$312, "マスタ未登録")} -> 当期商品仕入高 | B19: =IF(AND(C19<>"", COUNTIF('マスタ'!$C:$C, C19)=0), "マスタ未登録", "") | C19: =D19&D124&E19&F19&G19&H19 -> 業務委託費(原・ビ) | H19: 業務委託費(原・ビ) | J19: 1138039 | K19: 0 | L19: 0 | M19: 0 | N19: 0 | O19: 0 | P19: 0 | Q19: 0 | R19: 0 | S19: 0 | T19: 0 | U19: 0 | V19: 1138039
A20: {=XLOOKUP(C20, 'マスタ'!$C$2:$C$312, 'マスタ'!$D$2:$D$312, "マスタ未登録")} -> 当期商品仕入高 | B20: =IF(AND(C20<>"", COUNTIF('マスタ'!$C:$C, C20)=0), "マスタ未登録", "") | C20: =D20&D125&E20&F20&G20&H20 -> 旅費交通費(原) | H20: 旅費交通費(原) | J20: 2743860 | K20: 0 | L20: 0 | M20: 0 | N20: 0 | O20: 0 | P20: 0 | Q20: 0 | R20: 0 | S20: 0 | T20: 0 | U20: 0 | V20: 2743860
A21: {=XLOOKUP(C21, 'マスタ'!$C$2:$C$312, 'マスタ'!$D$2:$D$312, "マスタ未登録")} -> 当期商品仕入高 | B21: =IF(AND(C21<>"", COUNTIF('マスタ'!$C:$C, C21)=0), "マスタ未登録", "") | C21: =D21&D126&E21&F21&G21&H21 -> 通信費(原) | H21: 通信費(原) | J21: 1646407 | K21: 903439 | L21: 0 | M21: 0 | N21: 0 | O21: 0 | P21: 0 | Q21: 0 | R21: 0 | S21: 0 | T21: 0 | U21: 0 | V21: 2549846
A22: {=XLOOKUP(C22, 'マスタ'!$C$2:$C$312, 'マスタ'!$D$2:$D$312, "マスタ未登録")} -> 当期商品仕入高 | B22: =IF(AND(C22<>"", COUNTIF('マスタ'!$C:$C, C22)=0), "マスタ未登録", "") | C22: =D22&D127&E22&F22&G22&H22 -> 消耗品費(原) | H22: 消耗品費(原) | J22: 1300808 | K22: 0 | L22: 0 | M22: 0 | N22: 0 | O22: 0 | P22: 0 | Q22: 0 | R22: 0 | S22: 0 | T22: 0 | U22: 0 | V22: 1300808
A23: {=XLOOKUP(C23, 'マスタ'!$C$2:$C$312, 'マスタ'!$D$2:$D$312, "マスタ未登録")} -> 当期商品仕入高 | B23: =IF(AND(C23<>"", COUNTIF('マスタ'!$C:$C, C23)=0), "マスタ未登録", "") | C23: =D23&D128&E23&F23&G23&H23 -> 賃借料(原) | H23: 賃借料(原) | J23: 1552201 | K23: 0 | L23: 0 | M23: 0 | N23: 0 | O23: 0 | P23: 0 | Q23: 0 | R23: 0 | S23: 0 | T23: 0 | U23: 0 | V23: 1552201
A24: {=XLOOKUP(C24, 'マスタ'!$C$2:$C$312, 'マスタ'!$D$2:$D$312, "マスタ未登録")} -> 他勘定振替高 | B24: =IF(AND(C24<>"", COUNTIF('マスタ'!$C:$C, C24)=0), "マスタ未登録", "") | C24: =D24&D129&E24&F24&G24&H24 -> 他勘定振替高(商) | G24: 他勘定振替高(商) | J24: 0 | K24: 0 | L24: 0 | M24: 0 | N24: 0 | O24: 0 | P24: 0 | Q24: 0 | R24: 0 | S24: 0 | T24: 0 | U24: 0 | V24: 0
A25: {=XLOOKUP(C25, 'マスタ'!$C$2:$C$312, 'マスタ'!$D$2:$D$312, "マスタ未登録")} -> 期末商品棚卸高 | B25: =IF(AND(C25<>"", COUNTIF('マスタ'!$C:$C, C25)=0), "マスタ未登録", "") | C25: =D25&D130&E25&F25&G25&H25 -> 期末商品棚卸 | G25: 期末商品棚卸 | J25: -4289267 | K25: -7478973 | L25: 0 | M25: 0 | N25: 0 | O25: 0 | P25: 0 | Q25: 0 | R25: 0 | S25: 0 | T25: 0 | U25: 0 | V25: -11768240
A26: {=XLOOKUP(C26, 'マスタ'!$C$2:$C$312, 'マスタ'!$D$2:$D$312, "マスタ未登録")} -> 期末商品棚卸高 | B26: =IF(AND(C26<>"", COUNTIF('マスタ'!$C:$C, C26)=0), "マスタ未登録", "") | C26: =D26&D131&E26&F26&G26&H26 -> 期末商品棚卸高 | H26: 期末商品棚卸高 | J26: -4289267 | K26: -7478973 | L26: 0 | M26: 0 | N26: 0 | O26: 0 | P26: 0 | Q26: 0 | R26: 0 | S26: 0 | T26: 0 | U26: 0 | V26: -11768240
A27: {=XLOOKUP(C27, 'マスタ'!$C$2:$C$312, 'マスタ'!$D$2:$D$312, "マスタ未登録")} -> マスタ未登録 | B27: =IF(AND(C27<>"", COUNTIF('マスタ'!$C:$C, C27)=0), "マスタ未登録", "") -> マスタ未登録 | C27: =D27&D132&E27&F27&G27&H27 -> 商品売上原価 | F27: 商品売上原価 | J27: 159509316 | K27: 9834167 | L27: 0 | M27: 0 | N27: 0 | O27: 0 | P27: 0 | Q27: 0 | R27: 0 | S27: 0 | T27: 0 | U27: 0 | V27: 169343483
A28: {=XLOOKUP(C28, 'マスタ'!$C$2:$C$312, 'マスタ'!$D$2:$D$312, "マスタ未登録")} -> マスタ未登録 | B28: =IF(AND(C28<>"", COUNTIF('マスタ'!$C:$C, C28)=0), "マスタ未登録", "") -> マスタ未登録 | C28: =D28&D133&E28&F28&G28&H28 -> 売上総損益金額 | D28: 売上総損益金額 | J28: -23446157 | K28: -9834167 | L28: 0 | M28: 0 | N28: 0 | O28: 0 | P28: 0 | Q28: 0 | R28: 0 | S28: 0 | T28: 0 | U28: 0 | V28: -33280324
A29: {=XLOOKUP(C29, 'マスタ'!$C$2:$C$312, 'マスタ'!$D$2:$D$312, "マスタ未登録")} -> マスタ未登録 | B29: =IF(AND(C29<>"", COUNTIF('マスタ'!$C:$C, C29)=0), "マスタ未登録", "") -> マスタ未登録 | C29: =D29&D134&E29&F29&G29&H29 -> 販売管理費 | E29: 販売管理費
A30: {=XLOOKUP(C30, 'マスタ'!$C$2:$C$312, 'マスタ'!$D$2:$D$312, "マスタ未登録")} -> 給料手当 | B30: =IF(AND(C30<>"", COUNTIF('マスタ'!$C:$C, C30)=0), "マスタ未登録", "") | C30: =D30&D135&E30&F30&G30&H30 -> 給料手当 | F30: 給料手当 | J30: 9286900 | K30: 0 | L30: 0 | M30: 0 | N30: 0 | O30: 0 | P30: 0 | Q30: 0 | R30: 0 | S30: 0 | T30: 0 | U30: 0 | V30: 9286900
A31: {=XLOOKUP(C31, 'マスタ'!$C$2:$C$312, 'マスタ'!$D$2:$D$312, "マスタ未登録")} -> 法定福利費 | B31: =IF(AND(C31<>"", COUNTIF('マスタ'!$C:$C, C31)=0), "マスタ未登録", "") | C31: =D31&D136&E31&F31&G31&H31 -> 法定福利費 | F31: 法定福利費 | J31: 966320 | K31: 0 | L31: 0 | M31: 0 | N31: 0 | O31: 0 | P31: 0 | Q31: 0 | R31: 0 | S31: 0 | T31: 0 | U31: 0 | V31: 966320
A32: {=XLOOKUP(C32, 'マスタ'!$C$2:$C$312, 'マスタ'!$D$2:$D$312, "マスタ未登録")} -> 福利厚生費 | B32: =IF(AND(C32<>"", COUNTIF('マスタ'!$C:$C, C32)=0), "マスタ未登録", "") | C32: =D32&D137&E32&F32&G32&H32 -> 福利厚生費 | F32: 福利厚生費 | J32: 432775 | K32: 35630 | L32: 0 | M32: 0 | N32: 0 | O32: 0 | P32: 0 | Q32: 0 | R32: 0 | S32: 0 | T32: 0 | U32: 0 | V32: 468405
A33: {=XLOOKUP(C33, 'マスタ'!$C$2:$C$312, 'マスタ'!$D$2:$D$312, "マスタ未登録")} -> 旅費交通費 | B33: =IF(AND(C33<>"", COUNTIF('マスタ'!$C:$C, C33)=0), "マスタ未登録", "") | C33: =D33&D138&E33&F33&G33&H33 -> 旅費交通費 | F33: 旅費交通費 | J33: 136176 | K33: 0 | L33: 0 | M33: 0 | N33: 0 | O33: 0 | P33: 0 | Q33: 0 | R33: 0 | S33: 0 | T33: 0 | U33: 0 | V33: 136176
A34: {=XLOOKUP(C34, 'マスタ'!$C$2:$C$312, 'マスタ'!$D$2:$D$312, "マスタ未登録")} -> 通信費 | B34: =IF(AND(C34<>"", COUNTIF('マスタ'!$C:$C, C34)=0), "マスタ未登録", "") | C34: =D34&D139&E34&F34&G34&H34 -> 通信費 | F34: 通信費 | J34: 2884315 | K34: 1908278 | L34: 0 | M34: 0 | N34: 0 | O34: 0 | P34: 0 | Q34: 0 | R34: 0 | S34: 0 | T34: 0 | U34: 0 | V34: 4792593
A35: {=XLOOKUP(C35, 'マスタ'!$C$2:$C$312, 'マスタ'!$D$2:$D$312, "マスタ未登録")} -> 採用教育費 | B35: =IF(AND(C35<>"", COUNTIF('マスタ'!$C:$C, C35)=0), "マスタ未登録", "") | C35: =D35&D140&E35&F35&G35&H35 -> 採用教育費 | F35: 採用教育費 | J35: 72000 | K35: 45000 | L35: 0 | M35: 0 | N35: 0 | O35: 0 | P35: 0 | Q35: 0 | R35: 0 | S35: 0 | T35: 0 | U35: 0 | V35: 117000
A36: {=XLOOKUP(C36, 'マスタ'!$C$2:$C$312, 'マスタ'!$D$2:$D$312, "マスタ未登録")} -> 業務委託費 | B36: =IF(AND(C36<>"", COUNTIF('マスタ'!$C:$C, C36)=0), "マスタ未登録", "") | C36: =D36&D141&E36&F36&G36&H36 -> 業務委託費 | F36: 業務委託費 | J36: 10327403 | K36: 0 | L36: 0 | M36: 0 | N36: 0 | O36: 0 | P36: 0 | Q36: 0 | R36: 0 | S36: 0 | T36: 0 | U36: 0 | V36: 10327403
A37: {=XLOOKUP(C37, 'マスタ'!$C$2:$C$312, 'マスタ'!$D$2:$D$312, "マスタ未登録")} -> 支払報酬 | B37: =IF(AND(C37<>"", COUNTIF('マスタ'!$C:$C, C37)=0), "マスタ未登録", "") | C37: =D37&D142&E37&F37&G37&H37 -> 支払報酬料 | F37: 支払報酬料 | J37: 580000 | K37: 360000 | L37: 0 | M37: 0 | N37: 0 | O37: 0 | P37: 0 | Q37: 0 | R37: 0 | S37: 0 | T37: 0 | U37: 0 | V37: 940000
A38: {=XLOOKUP(C38, 'マスタ'!$C$2:$C$312, 'マスタ'!$D$2:$D$312, "マスタ未登録")} -> 販売促進費 | B38: =IF(AND(C38<>"", COUNTIF('マスタ'!$C:$C, C38)=0), "マスタ未登録", "") | C38: =D38&D143&E38&F38&G38&H38 -> 販売促進費 | F38: 販売促進費 | J38: 4130080 | K38: 0 | L38: 0 | M38: 0 | N38: 0 | O38: 0 | P38: 0 | Q38: 0 | R38: 0 | S38: 0 | T38: 0 | U38: 0 | V38: 4130080
A39: {=XLOOKUP(C39, 'マスタ'!$C$2:$C$312, 'マスタ'!$D$2:$D$312, "マスタ未登録")} -> 広告宣伝費 | B39: =IF(AND(C39<>"", COUNTIF('マスタ'!$C:$C, C39)=0), "マスタ未登録", "") | C39: =D39&D144&E39&F39&G39&H39 -> 広告宣伝費 | F39: 広告宣伝費 | J39: 1853930 | K39: 0 | L39: 0 | M39: 0 | N39: 0 | O39: 0 | P39: 0 | Q39: 0 | R39: 0 | S39: 0 | T39: 0 | U39: 0 | V39: 1853930
A40: {=XLOOKUP(C40, 'マスタ'!$C$2:$C$312, 'マスタ'!$D$2:$D$312, "マスタ未登録")} -> 荷造運賃 | B40: =IF(AND(C40<>"", COUNTIF('マスタ'!$C:$C, C40)=0), "マスタ未登録", "") | C40: =D40&D145&E40&F40&G40&H40 -> 荷造運賃 | F40: 荷造運賃 | J40: 4585467 | K40: 0 | L40: 0 | M40: 0 | N40: 0 | O40: 0 | P40: 0 | Q40: 0 | R40: 0 | S40: 0 | T40: 0 | U40: 0 | V40: 4585467
A41: {=XLOOKUP(C41, 'マスタ'!$C$2:$C$312, 'マスタ'!$D$2:$D$312, "マスタ未登録")} -> 水道光熱費 | B41: =IF(AND(C41<>"", COUNTIF('マスタ'!$C:$C, C41)=0), "マスタ未登録", "") | C41: =D41&D146&E41&F41&G41&H41 -> 水道光熱費 | F41: 水道光熱費 | J41: 367893 | K41: 0 | L41: 0 | M41: 0 | N41: 0 | O41: 0 | P41: 0 | Q41: 0 | R41: 0 | S41: 0 | T41: 0 | U41: 0 | V41: 367893
... A51: {=XLOOKUP(C51, 'マスタ'!$C$2:$C$312, 'マスタ'!$D$2:$D$312, "マスタ未登録")} -> 減価償却費 | B51: =IF(AND(C51<>"", COUNTIF('マスタ'!$C:$C, C51)=0), "マスタ未登録", "") | C51: =D51&D156&E51&F51&G51&H51 -> 減価償却費 | F51: 減価償却費 | J51: 1737996 | K51: 0 | L51: 0 | M51: 0 | N51: 0 | O51: 0 | P51: 0 | Q51: 0 | R51: 0 | S51: 0 | T51: 0 | U51: 0 | V51: 1737996
A52: {=XLOOKUP(C52, 'マスタ'!$C$2:$C$312, 'マスタ'!$D$2:$D$312, "マスタ未登録")} -> マスタ未登録 | B52: =IF(AND(C52<>"", COUNTIF('マスタ'!$C:$C, C52)=0), "マスタ未登録", "") -> マスタ未登録 | C52: =D52&D157&E52&F52&G52&H52 -> 販売管理費 計 | E52: 販売管理費 計 | J52: 55872130 | K52: 11049427 | L52: 0 | M52: 0 | N52: 0 | O52: 0 | P52: 0 | Q52: 0 | R52: 0 | S52: 0 | T52: 0 | U52: 0 | V52: 66921557
A53: {=XLOOKUP(C53, 'マスタ'!$C$2:$C$312, 'マスタ'!$D$2:$D$312, "マスタ未登録")} -> マスタ未登録 | B53: =IF(AND(C53<>"", COUNTIF('マスタ'!$C:$C, C53)=0), "マスタ未登録", "") -> マスタ未登録 | C53: =D53&D158&E53&F53&G53&H53 -> 営業損益金額 | D53: 営業損益金額 | J53: -79318287 | K53: -20883594 | L53: 0 | M53: 0 | N53: 0 | O53: 0 | P53: 0 | Q53: 0 | R53: 0 | S53: 0 | T53: 0 | U53: 0 | V53: -100201881
A54: {=XLOOKUP(C54, 'マスタ'!$C$2:$C$312, 'マスタ'!$D$2:$D$312, "マスタ未登録")} -> マスタ未登録 | B54: =IF(AND(C54<>"", COUNTIF('マスタ'!$C:$C, C54)=0), "マスタ未登録", "") -> マスタ未登録 | C54: =D54&D159&E54&F54&G54&H54 -> 営業外収益 | E54: 営業外収益 | J54: 102214 | K54: 30147 | L54: 0 | M54: 0 | N54: 0 | O54: 0 | P54: 0 | Q54: 0 | R54: 0 | S54: 0 | T54: 0 | U54: 0 | V54: 132361
A55: {=XLOOKUP(C55, 'マスタ'!$C$2:$C$312, 'マスタ'!$D$2:$D$312, "マスタ未登録")} -> 受取利息 | B55: =IF(AND(C55<>"", COUNTIF('マスタ'!$C:$C, C55)=0), "マスタ未登録", "") | C55: =D55&D160&E55&F55&G55&H55 -> 受取利息 | F55: 受取利息 | J55: 32085 | K55: 0 | L55: 0 | M55: 0 | N55: 0 | O55: 0 | P55: 0 | Q55: 0 | R55: 0 | S55: 0 | T55: 0 | U55: 0 | V55: 32085
A56: {=XLOOKUP(C56, 'マスタ'!$C$2:$C$312, 'マスタ'!$D$2:$D$312, "マスタ未登録")} -> 雑収入 | B56: =IF(AND(C56<>"", COUNTIF('マスタ'!$C:$C, C56)=0), "マスタ未登録", "") | C56: =D56&D161&E56&F56&G56&H56 -> 雑収入 | F56: 雑収入 | J56: 70129 | K56: 30147 | L56: 0 | M56: 0 | N56: 0 | O56: 0 | P56: 0 | Q56: 0 | R56: 0 | S56: 0 | T56: 0 | U56: 0 | V56: 100276
E57: 営業外費用 | J57: 139716 | K57: 0 | L57: 0 | M57: 0 | N57: 0 | O57: 0 | P57: 0 | Q57: 0 | R57: 0 | S57: 0 | T57: 0 | U57: 0 | V57: 139716
F58: 支払利息 | J58: 139716 | K58: 0 | L58: 0 | M58: 0 | N58: 0 | O58: 0 | P58: 0 | Q58: 0 | R58: 0 | S58: 0 | T58: 0 | U58: 0 | V58: 139716
D59: 経常損益金額 | J59: -79355789 | K59: -20853447 | L59: 0 | M59: 0 | N59: 0 | O59: 0 | P59: 0 | Q59: 0 | R59: 0 | S59: 0 | T59: 0 | U59: 0 | V59: -100209236
E60: 特別利益 | J60: 0 | K60: 0 | L60: 0 | M60: 0 | N60: 0 | O60: 0 | P60: 0 | Q60: 0 | R60: 0 | S60: 0 | T60: 0 | U60: 0 | V60: 0
E61: 特別損失 | J61: 0 | K61: 0 | L61: 0 | M61: 0 | N61: 0 | O61: 0 | P61: 0 | Q61: 0 | R61: 0 | S61: 0 | T61: 0 | U61: 0 | V61: 0
D62: 税引前当期純損益金額 | J62: -79355789 | K62: -20853447 | L62: 0 | M62: 0 | N62: 0 | O62: 0 | P62: 0 | Q62: 0 | R62: 0 | S62: 0 | T62: 0 | U62: 0 | V62: -100209236
E63: 法人税等 | J63: 0 | K63: 0 | L63: 0 | M63: 0 | N63: 0 | O63: 0 | P63: 0 | Q63: 0 | R63: 0 | S63: 0 | T63: 0 | U63: 0 | V63: 0
E64: 法人税等調整額 | J64: 0 | K64: 0 | L64: 0 | M64: 0 | N64: 0 | O64: 0 | P64: 0 | Q64: 0 | R64: 0 | S64: 0 | T64: 0 | U64: 0 | V64: 0
D65: 当期純損益金額 | J65: -79355789 | K65: -20853447 | L65: 0 | M65: 0 | N65: 0 | O65: 0 | P65: 0 | Q65: 0 | R65: 0 | S65: 0 | T65: 0 | U65: 0 | V65: -100209236

Sheet VO_PL(ORIGIN)
A1: 補助列 | B1: ②マスタ結びつけ | C1: ① | D1: 月次推移：損益計算書_株式会社VOISING（期間：2026年04月〜2027年03月、表示単位：円）
J2: 46113 | K2: 46143 | L2: 46174 | M2: 46204 | N2: 46235 | O2: 46266 | P2: 46296 | Q2: 46327 | R2: 46357 | S2: 46388 | T2: 46419 | U2: 46447 | V2: 期間累計
D3: 売上高
A4: {=XLOOKUP(C4, 'マスタ'!$C$2:$C$312, 'マスタ'!$D$2:$D$312, "マスタ未登録")} -> 売上高 | B4: =IF(AND(C4<>"", COUNTIF('マスタ'!$C:$C, C4)=0), "マスタ未登録", "") | C4: =D4&D109&E4&F4&G4&H4 -> 売上高 | E4: 売上高 | J4: 72501616 | K4: 0 | L4: 0 | M4: 0 | N4: 0 | O4: 0 | P4: 0 | Q4: 0 | R4: 0 | S4: 0 | T4: 0 | U4: 0 | V4: 72501616
A5: {=XLOOKUP(C5, 'マスタ'!$C$2:$C$312, 'マスタ'!$D$2:$D$312, "マスタ未登録")} -> 売上高 | B5: =IF(AND(C5<>"", COUNTIF('マスタ'!$C:$C, C5)=0), "マスタ未登録", "") | C5: =D5&D110&E5&F5&G5&H5 -> 委託販売売上高 | E5: 委託販売売上高 | J5: 3698888 | K5: 0 | L5: 0 | M5: 0 | N5: 0 | O5: 0 | P5: 0 | Q5: 0 | R5: 0 | S5: 0 | T5: 0 | U5: 0 | V5: 3698888
A6: {=XLOOKUP(C6, 'マスタ'!$C$2:$C$312, 'マスタ'!$D$2:$D$312, "マスタ未登録")} -> マスタ未登録 | B6: =IF(AND(C6<>"", COUNTIF('マスタ'!$C:$C, C6)=0), "マスタ未登録", "") -> マスタ未登録 | C6: =D6&D111&E6&F6&G6&H6 -> 売上高 計 | D6: 売上高 計 | J6: 76200504 | K6: 0 | L6: 0 | M6: 0 | N6: 0 | O6: 0 | P6: 0 | Q6: 0 | R6: 0 | S6: 0 | T6: 0 | U6: 0 | V6: 76200504
A7: {=XLOOKUP(C7, 'マスタ'!$C$2:$C$312, 'マスタ'!$D$2:$D$312, "マスタ未登録")} -> マスタ未登録 | B7: =IF(AND(C7<>"", COUNTIF('マスタ'!$C:$C, C7)=0), "マスタ未登録", "") -> マスタ未登録 | C7: =D7&D112&E7&F7&G7&H7 -> 売上原価 | E7: 売上原価
A8: {=XLOOKUP(C8, 'マスタ'!$C$2:$C$312, 'マスタ'!$D$2:$D$312, "マスタ未登録")} -> マスタ未登録 | B8: =IF(AND(C8<>"", COUNTIF('マスタ'!$C:$C, C8)=0), "マスタ未登録", "") -> マスタ未登録 | C8: =D8&D113&E8&F8&G8&H8 -> 売上原価 | E8: 売上原価 | J8: 48118946 | K8: 3753998 | L8: 0 | M8: 0 | N8: 0 | O8: 0 | P8: 0 | Q8: 0 | R8: 0 | S8: 0 | T8: 0 | U8: 0 | V8: 51872944
A9: {=XLOOKUP(C9, 'マスタ'!$C$2:$C$312, 'マスタ'!$D$2:$D$312, "マスタ未登録")} -> 期首商品棚卸高 | B9: =IF(AND(C9<>"", COUNTIF('マスタ'!$C:$C, C9)=0), "マスタ未登録", "") | C9: =D9&D114&E9&F9&G9&H9 -> 期首商品棚卸 | G9: 期首商品棚卸 | J9: 0 | K9: 0 | L9: 0 | M9: 0 | N9: 0 | O9: 0 | P9: 0 | Q9: 0 | R9: 0 | S9: 0 | T9: 0 | U9: 0 | V9: 0
A10: {=XLOOKUP(C10, 'マスタ'!$C$2:$C$312, 'マスタ'!$D$2:$D$312, "マスタ未登録")} -> マスタ未登録 | B10: =IF(AND(C10<>"", COUNTIF('マスタ'!$C:$C, C10)=0), "マスタ未登録", "") -> マスタ未登録 | C10: =D10&D115&E10&F10&G10&H10 -> 当期商品仕入(見出し） | G10: 当期商品仕入(見出し） | J10: 47062337 | K10: 1116300 | L10: 0 | M10: 0 | N10: 0 | O10: 0 | P10: 0 | Q10: 0 | R10: 0 | S10: 0 | T10: 0 | U10: 0 | V10: 48178637
A11: {=XLOOKUP(C11, 'マスタ'!$C$2:$C$312, 'マスタ'!$D$2:$D$312, "マスタ未登録")} -> 当期商品仕入高 | B11: =IF(AND(C11<>"", COUNTIF('マスタ'!$C:$C, C11)=0), "マスタ未登録", "") | C11: =D11&D116&E11&F11&G11&H11 -> 仕入高 | H11: 仕入高 | J11: 2294400 | K11: 0 | L11: 0 | M11: 0 | N11: 0 | O11: 0 | P11: 0 | Q11: 0 | R11: 0 | S11: 0 | T11: 0 | U11: 0 | V11: 2294400
A12: {=XLOOKUP(C12, 'マスタ'!$C$2:$C$312, 'マスタ'!$D$2:$D$312, "マスタ未登録")} -> 当期商品仕入高 | B12: =IF(AND(C12<>"", COUNTIF('マスタ'!$C:$C, C12)=0), "マスタ未登録", "") | C12: =D12&D117&E12&F12&G12&H12 -> 外注費(原) | H12: 外注費(原) | J12: 24825482 | K12: 1116300 | L12: 0 | M12: 0 | N12: 0 | O12: 0 | P12: 0 | Q12: 0 | R12: 0 | S12: 0 | T12: 0 | U12: 0 | V12: 25941782
A13: {=XLOOKUP(C13, 'マスタ'!$C$2:$C$312, 'マスタ'!$D$2:$D$312, "マスタ未登録")} -> 当期商品仕入高 | B13: =IF(AND(C13<>"", COUNTIF('マスタ'!$C:$C, C13)=0), "マスタ未登録", "") | C13: =D13&D118&E13&F13&G13&H13 -> 業務委託費(原・タレント) | H13: 業務委託費(原・タレント) | J13: 16433661 | K13: 0 | L13: 0 | M13: 0 | N13: 0 | O13: 0 | P13: 0 | Q13: 0 | R13: 0 | S13: 0 | T13: 0 | U13: 0 | V13: 16433661
A14: {=XLOOKUP(C14, 'マスタ'!$C$2:$C$312, 'マスタ'!$D$2:$D$312, "マスタ未登録")} -> 当期商品仕入高 | B14: =IF(AND(C14<>"", COUNTIF('マスタ'!$C:$C, C14)=0), "マスタ未登録", "") | C14: =D14&D119&E14&F14&G14&H14 -> 業務委託費(原・製) | H14: 業務委託費(原・製) | J14: 2175130 | K14: 0 | L14: 0 | M14: 0 | N14: 0 | O14: 0 | P14: 0 | Q14: 0 | R14: 0 | S14: 0 | T14: 0 | U14: 0 | V14: 2175130
A15: {=XLOOKUP(C15, 'マスタ'!$C$2:$C$312, 'マスタ'!$D$2:$D$312, "マスタ未登録")} -> 当期商品仕入高 | B15: =IF(AND(C15<>"", COUNTIF('マスタ'!$C:$C, C15)=0), "マスタ未登録", "") | C15: =D15&D120&E15&F15&G15&H15 -> 旅費交通費(原) | H15: 旅費交通費(原) | J15: 1052365 | K15: 0 | L15: 0 | M15: 0 | N15: 0 | O15: 0 | P15: 0 | Q15: 0 | R15: 0 | S15: 0 | T15: 0 | U15: 0 | V15: 1052365
A16: {=XLOOKUP(C16, 'マスタ'!$C$2:$C$312, 'マスタ'!$D$2:$D$312, "マスタ未登録")} -> 当期商品仕入高 | B16: =IF(AND(C16<>"", COUNTIF('マスタ'!$C:$C, C16)=0), "マスタ未登録", "") | C16: =D16&D121&E16&F16&G16&H16 -> 通信費(原) | H16: 通信費(原) | J16: 75560 | K16: 0 | L16: 0 | M16: 0 | N16: 0 | O16: 0 | P16: 0 | Q16: 0 | R16: 0 | S16: 0 | T16: 0 | U16: 0 | V16: 75560
A17: {=XLOOKUP(C17, 'マスタ'!$C$2:$C$312, 'マスタ'!$D$2:$D$312, "マスタ未登録")} -> 当期商品仕入高 | B17: =IF(AND(C17<>"", COUNTIF('マスタ'!$C:$C, C17)=0), "マスタ未登録", "") | C17: =D17&D122&E17&F17&G17&H17 -> 消耗品費(原) | H17: 消耗品費(原) | J17: 132539 | K17: 0 | L17: 0 | M17: 0 | N17: 0 | O17: 0 | P17: 0 | Q17: 0 | R17: 0 | S17: 0 | T17: 0 | U17: 0 | V17: 132539
A18: {=XLOOKUP(C18, 'マスタ'!$C$2:$C$312, 'マスタ'!$D$2:$D$312, "マスタ未登録")} -> 当期商品仕入高 | B18: =IF(AND(C18<>"", COUNTIF('マスタ'!$C:$C, C18)=0), "マスタ未登録", "") | C18: =D18&D123&E18&F18&G18&H18 -> 賃借料(原) | H18: 賃借料(原) | J18: 73200 | K18: 0 | L18: 0 | M18: 0 | N18: 0 | O18: 0 | P18: 0 | Q18: 0 | R18: 0 | S18: 0 | T18: 0 | U18: 0 | V18: 73200
A19: {=XLOOKUP(C19, 'マスタ'!$C$2:$C$312, 'マスタ'!$D$2:$D$312, "マスタ未登録")} -> 他勘定振替高 | B19: =IF(AND(C19<>"", COUNTIF('マスタ'!$C:$C, C19)=0), "マスタ未登録", "") | C19: =D19&D124&E19&F19&G19&H19 -> 他勘定振替高(商) | G19: 他勘定振替高(商) | J19: 0 | K19: 0 | L19: 0 | M19: 0 | N19: 0 | O19: 0 | P19: 0 | Q19: 0 | R19: 0 | S19: 0 | T19: 0 | U19: 0 | V19: 0
A20: {=XLOOKUP(C20, 'マスタ'!$C$2:$C$312, 'マスタ'!$D$2:$D$312, "マスタ未登録")} -> マスタ未登録 | B20: =IF(AND(C20<>"", COUNTIF('マスタ'!$C:$C, C20)=0), "マスタ未登録", "") -> マスタ未登録 | C20: =D20&D125&E20&F20&G20&H20 -> 期末商品棚卸（見出し） | G20: 期末商品棚卸（見出し） | J20: -1056609 | K20: -2637698 | L20: 0 | M20: 0 | N20: 0 | O20: 0 | P20: 0 | Q20: 0 | R20: 0 | S20: 0 | T20: 0 | U20: 0 | V20: -3694307
A21: {=XLOOKUP(C21, 'マスタ'!$C$2:$C$312, 'マスタ'!$D$2:$D$312, "マスタ未登録")} -> 期末商品棚卸高 | B21: =IF(AND(C21<>"", COUNTIF('マスタ'!$C:$C, C21)=0), "マスタ未登録", "") | C21: =D21&D126&E21&F21&G21&H21 -> 期末商品棚卸高 | H21: 期末商品棚卸高 | J21: -1056609 | K21: -2637698 | L21: 0 | M21: 0 | N21: 0 | O21: 0 | P21: 0 | Q21: 0 | R21: 0 | S21: 0 | T21: 0 | U21: 0 | V21: -3694307
A22: {=XLOOKUP(C22, 'マスタ'!$C$2:$C$312, 'マスタ'!$D$2:$D$312, "マスタ未登録")} -> マスタ未登録 | B22: =IF(AND(C22<>"", COUNTIF('マスタ'!$C:$C, C22)=0), "マスタ未登録", "") -> マスタ未登録 | C22: =D22&D127&E22&F22&G22&H22 -> 商品売上原価 | F22: 商品売上原価 | J22: 48118946 | K22: 3753998 | L22: 0 | M22: 0 | N22: 0 | O22: 0 | P22: 0 | Q22: 0 | R22: 0 | S22: 0 | T22: 0 | U22: 0 | V22: 51872944
A23: {=XLOOKUP(C23, 'マスタ'!$C$2:$C$312, 'マスタ'!$D$2:$D$312, "マスタ未登録")} -> マスタ未登録 | B23: =IF(AND(C23<>"", COUNTIF('マスタ'!$C:$C, C23)=0), "マスタ未登録", "") -> マスタ未登録 | C23: =D23&D128&E23&F23&G23&H23 -> 売上総損益金額 | D23: 売上総損益金額 | J23: 28081558 | K23: -3753998 | L23: 0 | M23: 0 | N23: 0 | O23: 0 | P23: 0 | Q23: 0 | R23: 0 | S23: 0 | T23: 0 | U23: 0 | V23: 24327560
A24: {=XLOOKUP(C24, 'マスタ'!$C$2:$C$312, 'マスタ'!$D$2:$D$312, "マスタ未登録")} -> マスタ未登録 | B24: =IF(AND(C24<>"", COUNTIF('マスタ'!$C:$C, C24)=0), "マスタ未登録", "") -> マスタ未登録 | C24: =D24&D129&E24&F24&G24&H24 -> 販売管理費 | E24: 販売管理費
A25: {=XLOOKUP(C25, 'マスタ'!$C$2:$C$312, 'マスタ'!$D$2:$D$312, "マスタ未登録")} -> 販売促進費 | B25: =IF(AND(C25<>"", COUNTIF('マスタ'!$C:$C, C25)=0), "マスタ未登録", "") | C25: =D25&D130&E25&F25&G25&H25 -> 販売促進費 | F25: 販売促進費 | J25: 3109000 | K25: 0 | L25: 0 | M25: 0 | N25: 0 | O25: 0 | P25: 0 | Q25: 0 | R25: 0 | S25: 0 | T25: 0 | U25: 0 | V25: 3109000
A26: {=XLOOKUP(C26, 'マスタ'!$C$2:$C$312, 'マスタ'!$D$2:$D$312, "マスタ未登録")} -> 広告宣伝費 | B26: =IF(AND(C26<>"", COUNTIF('マスタ'!$C:$C, C26)=0), "マスタ未登録", "") | C26: =D26&D131&E26&F26&G26&H26 -> 広告宣伝費 | F26: 広告宣伝費 | J26: 117855 | K26: 0 | L26: 0 | M26: 0 | N26: 0 | O26: 0 | P26: 0 | Q26: 0 | R26: 0 | S26: 0 | T26: 0 | U26: 0 | V26: 117855
A27: {=XLOOKUP(C27, 'マスタ'!$C$2:$C$312, 'マスタ'!$D$2:$D$312, "マスタ未登録")} -> 荷造運賃 | B27: =IF(AND(C27<>"", COUNTIF('マスタ'!$C:$C, C27)=0), "マスタ未登録", "") | C27: =D27&D132&E27&F27&G27&H27 -> 荷造運賃 | F27: 荷造運賃 | J27: 2406398 | K27: 0 | L27: 0 | M27: 0 | N27: 0 | O27: 0 | P27: 0 | Q27: 0 | R27: 0 | S27: 0 | T27: 0 | U27: 0 | V27: 2406398
A28: {=XLOOKUP(C28, 'マスタ'!$C$2:$C$312, 'マスタ'!$D$2:$D$312, "マスタ未登録")} -> 支払手数料 | B28: =IF(AND(C28<>"", COUNTIF('マスタ'!$C:$C, C28)=0), "マスタ未登録", "") | C28: =D28&D133&E28&F28&G28&H28 -> 支払手数料 | F28: 支払手数料 | J28: 4149491 | K28: 0 | L28: 0 | M28: 0 | N28: 0 | O28: 0 | P28: 0 | Q28: 0 | R28: 0 | S28: 0 | T28: 0 | U28: 0 | V28: 4149491
A29: {=XLOOKUP(C29, 'マスタ'!$C$2:$C$312, 'マスタ'!$D$2:$D$312, "マスタ未登録")} -> 租税公課 | B29: =IF(AND(C29<>"", COUNTIF('マスタ'!$C:$C, C29)=0), "マスタ未登録", "") | C29: =D29&D134&E29&F29&G29&H29 -> 租税公課 | F29: 租税公課 | J29: 2450 | K29: 0 | L29: 0 | M29: 0 | N29: 0 | O29: 0 | P29: 0 | Q29: 0 | R29: 0 | S29: 0 | T29: 0 | U29: 0 | V29: 2450
A30: {=XLOOKUP(C30, 'マスタ'!$C$2:$C$312, 'マスタ'!$D$2:$D$312, "マスタ未登録")} -> マスタ未登録 | B30: =IF(AND(C30<>"", COUNTIF('マスタ'!$C:$C, C30)=0), "マスタ未登録", "") -> マスタ未登録 | C30: =D30&D135&E30&F30&G30&H30 -> 販売管理費 計 | E30: 販売管理費 計 | J30: 9785194 | K30: 0 | L30: 0 | M30: 0 | N30: 0 | O30: 0 | P30: 0 | Q30: 0 | R30: 0 | S30: 0 | T30: 0 | U30: 0 | V30: 9785194
A31: {=XLOOKUP(C31, 'マスタ'!$C$2:$C$312, 'マスタ'!$D$2:$D$312, "マスタ未登録")} -> マスタ未登録 | B31: =IF(AND(C31<>"", COUNTIF('マスタ'!$C:$C, C31)=0), "マスタ未登録", "") -> マスタ未登録 | C31: =D31&D136&E31&F31&G31&H31 -> 営業損益金額 | D31: 営業損益金額 | J31: 18296364 | K31: -3753998 | L31: 0 | M31: 0 | N31: 0 | O31: 0 | P31: 0 | Q31: 0 | R31: 0 | S31: 0 | T31: 0 | U31: 0 | V31: 14542366
A32: {=XLOOKUP(C32, 'マスタ'!$C$2:$C$312, 'マスタ'!$D$2:$D$312, "マスタ未登録")} -> マスタ未登録 | B32: =IF(AND(C32<>"", COUNTIF('マスタ'!$C:$C, C32)=0), "マスタ未登録", "") -> マスタ未登録 | C32: =D32&D137&E32&F32&G32&H32 -> 営業外収益 | E32: 営業外収益 | J32: 0 | K32: 0 | L32: 0 | M32: 0 | N32: 0 | O32: 0 | P32: 0 | Q32: 0 | R32: 0 | S32: 0 | T32: 0 | U32: 0 | V32: 0
A33: {=XLOOKUP(C33, 'マスタ'!$C$2:$C$312, 'マスタ'!$D$2:$D$312, "マスタ未登録")} -> マスタ未登録 | B33: =IF(AND(C33<>"", COUNTIF('マスタ'!$C:$C, C33)=0), "マスタ未登録", "") -> マスタ未登録 | C33: =D33&D138&E33&F33&G33&H33 -> 営業外費用 | E33: 営業外費用 | J33: 0 | K33: 0 | L33: 0 | M33: 0 | N33: 0 | O33: 0 | P33: 0 | Q33: 0 | R33: 0 | S33: 0 | T33: 0 | U33: 0 | V33: 0
A34: {=XLOOKUP(C34, 'マスタ'!$C$2:$C$312, 'マスタ'!$D$2:$D$312, "マスタ未登録")} -> マスタ未登録 | B34: =IF(AND(C34<>"", COUNTIF('マスタ'!$C:$C, C34)=0), "マスタ未登録", "") -> マスタ未登録 | C34: =D34&D139&E34&F34&G34&H34 -> 経常損益金額 | D34: 経常損益金額 | J34: 18296364 | K34: -3753998 | L34: 0 | M34: 0 | N34: 0 | O34: 0 | P34: 0 | Q34: 0 | R34: 0 | S34: 0 | T34: 0 | U34: 0 | V34: 14542366
A35: {=XLOOKUP(C35, 'マスタ'!$C$2:$C$312, 'マスタ'!$D$2:$D$312, "マスタ未登録")} -> マスタ未登録 | B35: =IF(AND(C35<>"", COUNTIF('マスタ'!$C:$C, C35)=0), "マスタ未登録", "") -> マスタ未登録 | C35: =D35&D140&E35&F35&G35&H35 -> 特別利益 | E35: 特別利益 | J35: 0 | K35: 0 | L35: 0 | M35: 0 | N35: 0 | O35: 0 | P35: 0 | Q35: 0 | R35: 0 | S35: 0 | T35: 0 | U35: 0 | V35: 0
A36: {=XLOOKUP(C36, 'マスタ'!$C$2:$C$312, 'マスタ'!$D$2:$D$312, "マスタ未登録")} -> マスタ未登録 | B36: =IF(AND(C36<>"", COUNTIF('マスタ'!$C:$C, C36)=0), "マスタ未登録", "") -> マスタ未登録 | C36: =D36&D141&E36&F36&G36&H36 -> 特別損失 | E36: 特別損失 | J36: 0 | K36: 0 | L36: 0 | M36: 0 | N36: 0 | O36: 0 | P36: 0 | Q36: 0 | R36: 0 | S36: 0 | T36: 0 | U36: 0 | V36: 0
A37: {=XLOOKUP(C37, 'マスタ'!$C$2:$C$312, 'マスタ'!$D$2:$D$312, "マスタ未登録")} -> マスタ未登録 | B37: =IF(AND(C37<>"", COUNTIF('マスタ'!$C:$C, C37)=0), "マスタ未登録", "") -> マスタ未登録 | C37: =D37&D142&E37&F37&G37&H37 -> 税引前当期純損益金額 | D37: 税引前当期純損益金額 | J37: 18296364 | K37: -3753998 | L37: 0 | M37: 0 | N37: 0 | O37: 0 | P37: 0 | Q37: 0 | R37: 0 | S37: 0 | T37: 0 | U37: 0 | V37: 14542366
A38: {=XLOOKUP(C38, 'マスタ'!$C$2:$C$312, 'マスタ'!$D$2:$D$312, "マスタ未登録")} -> 法人税等 | B38: =IF(AND(C38<>"", COUNTIF('マスタ'!$C:$C, C38)=0), "マスタ未登録", "") | C38: =D38&D143&E38&F38&G38&H38 -> 法人税等 | E38: 法人税等 | J38: 0 | K38: 0 | L38: 0 | M38: 0 | N38: 0 | O38: 0 | P38: 0 | Q38: 0 | R38: 0 | S38: 0 | T38: 0 | U38: 0 | V38: 0
A39: {=XLOOKUP(C39, 'マスタ'!$C$2:$C$312, 'マスタ'!$D$2:$D$312, "マスタ未登録")} -> 法人税等調整額 | B39: =IF(AND(C39<>"", COUNTIF('マスタ'!$C:$C, C39)=0), "マスタ未登録", "") | C39: =D39&D144&E39&F39&G39&H39 -> 法人税等調整額 | E39: 法人税等調整額 | J39: 0 | K39: 0 | L39: 0 | M39: 0 | N39: 0 | O39: 0 | P39: 0 | Q39: 0 | R39: 0 | S39: 0 | T39: 0 | U39: 0 | V39: 0
A40: {=XLOOKUP(C40, 'マスタ'!$C$2:$C$312, 'マスタ'!$D$2:$D$312, "マスタ未登録")} -> マスタ未登録 | B40: =IF(AND(C40<>"", COUNTIF('マスタ'!$C:$C, C40)=0), "マスタ未登録", "") -> マスタ未登録 | C40: =D40&D145&E40&F40&G40&H40 -> 当期純損益金額 | D40: 当期純損益金額 | J40: 18296364 | K40: -3753998 | L40: 0 | M40: 0 | N40: 0 | O40: 0 | P40: 0 | Q40: 0 | R40: 0 | S40: 0 | T40: 0 | U40: 0 | V40: 14542366
B41: =IF(AND(C41<>"", COUNTIF('マスタ'!$C:$C, C41)=0), "マスタ未登録", "") | C41: =D41&D146&E41&F41&G41&H41
B42: =IF(AND(C42<>"", COUNTIF('マスタ'!$C:$C, C42)=0), "マスタ未登録", "") | C42: =D42&D147&E42&F42&G42&H42
B43: =IF(AND(C43<>"", COUNTIF('マスタ'!$C:$C, C43)=0), "マスタ未登録", "") | C43: =D43&D148&E43&F43&G43&H43
B44: =IF(AND(C44<>"", COUNTIF('マスタ'!$C:$C, C44)=0), "マスタ未登録", "") | C44: =D44&D149&E44&F44&G44&H44
B45: =IF(AND(C45<>"", COUNTIF('マスタ'!$C:$C, C45)=0), "マスタ未登録", "") | C45: =D45&D150&E45&F45&G45&H45
B46: =IF(AND(C46<>"", COUNTIF('マスタ'!$C:$C, C46)=0), "マスタ未登録", "") | C46: =D46&D151&E46&F46&G46&H46
B47: =IF(AND(C47<>"", COUNTIF('マスタ'!$C:$C, C47)=0), "マスタ未登録", "") | C47: =D47&D152&E47&F47&G47&H47
B48: =IF(AND(C48<>"", COUNTIF('マスタ'!$C:$C, C48)=0), "マスタ未登録", "") | C48: =D48&D153&E48&F48&G48&H48
B49: =IF(AND(C49<>"", COUNTIF('マスタ'!$C:$C, C49)=0), "マスタ未登録", "") | C49: =D49&D154&E49&F49&G49&H49
B50: =IF(AND(C50<>"", COUNTIF('マスタ'!$C:$C, C50)=0), "マスタ未登録", "") | C50: =D50&D155&E50&F50&G50&H50
B51: =IF(AND(C51<>"", COUNTIF('マスタ'!$C:$C, C51)=0), "マスタ未登録", "") | C51: =D51&D156&E51&F51&G51&H51
B52: =IF(AND(C52<>"", COUNTIF('マスタ'!$C:$C, C52)=0), "マスタ未登録", "") | C52: =D52&D157&E52&F52&G52&H52
... B56: =IF(AND(C56<>"", COUNTIF('マスタ'!$C:$C, C56)=0), "マスタ未登録", "") | C56: =D56&D161&E56&F56&G56&H56

Sheet VO_PL(AIR)
B1: ②マスタ結びつけ | C1: ① | D1: 月次推移：損益計算書_株式会社VOISING（期間：2026年04月〜2027年03月、表示単位：円）
J2: 46113 | K2: 46143 | L2: 46174 | M2: 46204 | N2: 46235 | O2: 46266 | P2: 46296 | Q2: 46327 | R2: 46357 | S2: 46388 | T2: 46419 | U2: 46447 | V2: 期間累計
D3: 売上高
A4: {=XLOOKUP(C4, 'マスタ'!$C$2:$C$312, 'マスタ'!$D$2:$D$312, "マスタ未登録")} -> 売上高 | B4: =IF(AND(C4<>"", COUNTIF('マスタ'!$C:$C, C4)=0), "マスタ未登録", "") | C4: =D4&D109&E4&F4&G4&H4 -> 売上高 | E4: 売上高 | J4: 7050231 | K4: 0 | L4: 0 | M4: 0 | N4: 0 | O4: 0 | P4: 0 | Q4: 0 | R4: 0 | S4: 0 | T4: 0 | U4: 0 | V4: 7050231
A5: {=XLOOKUP(C5, 'マスタ'!$C$2:$C$312, 'マスタ'!$D$2:$D$312, "マスタ未登録")} -> 売上高 | B5: =IF(AND(C5<>"", COUNTIF('マスタ'!$C:$C, C5)=0), "マスタ未登録", "") | C5: =D5&D110&E5&F5&G5&H5 -> 委託販売売上高 | E5: 委託販売売上高 | J5: 648731 | K5: 0 | L5: 0 | M5: 0 | N5: 0 | O5: 0 | P5: 0 | Q5: 0 | R5: 0 | S5: 0 | T5: 0 | U5: 0 | V5: 648731
A6: {=XLOOKUP(C6, 'マスタ'!$C$2:$C$312, 'マスタ'!$D$2:$D$312, "マスタ未登録")} -> マスタ未登録 | B6: =IF(AND(C6<>"", COUNTIF('マスタ'!$C:$C, C6)=0), "マスタ未登録", "") -> マスタ未登録 | C6: =D6&D111&E6&F6&G6&H6 -> 売上高 計 | D6: 売上高 計 | J6: 7698962 | K6: 0 | L6: 0 | M6: 0 | N6: 0 | O6: 0 | P6: 0 | Q6: 0 | R6: 0 | S6: 0 | T6: 0 | U6: 0 | V6: 7698962
A7: {=XLOOKUP(C7, 'マスタ'!$C$2:$C$312, 'マスタ'!$D$2:$D$312, "マスタ未登録")} -> マスタ未登録 | B7: =IF(AND(C7<>"", COUNTIF('マスタ'!$C:$C, C7)=0), "マスタ未登録", "") -> マスタ未登録 | C7: =D7&D112&E7&F7&G7&H7 -> 売上原価 | E7: 売上原価
A8: {=XLOOKUP(C8, 'マスタ'!$C$2:$C$312, 'マスタ'!$D$2:$D$312, "マスタ未登録")} -> マスタ未登録 | B8: =IF(AND(C8<>"", COUNTIF('マスタ'!$C:$C, C8)=0), "マスタ未登録", "") -> マスタ未登録 | C8: =D8&D113&E8&F8&G8&H8 -> 売上原価 | E8: 売上原価 | J8: 11847579 | K8: 3467282 | L8: 0 | M8: 0 | N8: 0 | O8: 0 | P8: 0 | Q8: 0 | R8: 0 | S8: 0 | T8: 0 | U8: 0 | V8: 15314861
A9: {=XLOOKUP(C9, 'マスタ'!$C$2:$C$312, 'マスタ'!$D$2:$D$312, "マスタ未登録")} -> 期首商品棚卸高 | B9: =IF(AND(C9<>"", COUNTIF('マスタ'!$C:$C, C9)=0), "マスタ未登録", "") | C9: =D9&D114&E9&F9&G9&H9 -> 期首商品棚卸 | G9: 期首商品棚卸 | J9: 0 | K9: 0 | L9: 0 | M9: 0 | N9: 0 | O9: 0 | P9: 0 | Q9: 0 | R9: 0 | S9: 0 | T9: 0 | U9: 0 | V9: 0
A10: {=XLOOKUP(C10, 'マスタ'!$C$2:$C$312, 'マスタ'!$D$2:$D$312, "マスタ未登録")} -> マスタ未登録 | B10: =IF(AND(C10<>"", COUNTIF('マスタ'!$C:$C, C10)=0), "マスタ未登録", "") -> マスタ未登録 | C10: =D10&D115&E10&F10&G10&H10 -> 当期商品仕入（見出し） | G10: 当期商品仕入（見出し） | J10: 8794799 | K10: 185455 | L10: 0 | M10: 0 | N10: 0 | O10: 0 | P10: 0 | Q10: 0 | R10: 0 | S10: 0 | T10: 0 | U10: 0 | V10: 8980254
A11: {=XLOOKUP(C11, 'マスタ'!$C$2:$C$312, 'マスタ'!$D$2:$D$312, "マスタ未登録")} -> 当期商品仕入高 | B11: =IF(AND(C11<>"", COUNTIF('マスタ'!$C:$C, C11)=0), "マスタ未登録", "") | C11: =D11&D116&E11&F11&G11&H11 -> 外注費(原) | H11: 外注費(原) | J11: 2833010 | K11: 185455 | L11: 0 | M11: 0 | N11: 0 | O11: 0 | P11: 0 | Q11: 0 | R11: 0 | S11: 0 | T11: 0 | U11: 0 | V11: 3018465
A12: {=XLOOKUP(C12, 'マスタ'!$C$2:$C$312, 'マスタ'!$D$2:$D$312, "マスタ未登録")} -> 当期商品仕入高 | B12: =IF(AND(C12<>"", COUNTIF('マスタ'!$C:$C, C12)=0), "マスタ未登録", "") | C12: =D12&D117&E12&F12&G12&H12 -> 業務委託費(原・タレント) | H12: 業務委託費(原・タレント) | J12: 3338000 | K12: 0 | L12: 0 | M12: 0 | N12: 0 | O12: 0 | P12: 0 | Q12: 0 | R12: 0 | S12: 0 | T12: 0 | U12: 0 | V12: 3338000
A13: {=XLOOKUP(C13, 'マスタ'!$C$2:$C$312, 'マスタ'!$D$2:$D$312, "マスタ未登録")} -> 当期商品仕入高 | B13: =IF(AND(C13<>"", COUNTIF('マスタ'!$C:$C, C13)=0), "マスタ未登録", "") | C13: =D13&D118&E13&F13&G13&H13 -> 業務委託費(原・製) | H13: 業務委託費(原・製) | J13: 968613 | K13: 0 | L13: 0 | M13: 0 | N13: 0 | O13: 0 | P13: 0 | Q13: 0 | R13: 0 | S13: 0 | T13: 0 | U13: 0 | V13: 968613
A14: {=XLOOKUP(C14, 'マスタ'!$C$2:$C$312, 'マスタ'!$D$2:$D$312, "マスタ未登録")} -> 当期商品仕入高 | B14: =IF(AND(C14<>"", COUNTIF('マスタ'!$C:$C, C14)=0), "マスタ未登録", "") | C14: =D14&D119&E14&F14&G14&H14 -> 旅費交通費(原) | H14: 旅費交通費(原) | J14: 170638 | K14: 0 | L14: 0 | M14: 0 | N14: 0 | O14: 0 | P14: 0 | Q14: 0 | R14: 0 | S14: 0 | T14: 0 | U14: 0 | V14: 170638
A15: {=XLOOKUP(C15, 'マスタ'!$C$2:$C$312, 'マスタ'!$D$2:$D$312, "マスタ未登録")} -> 当期商品仕入高 | B15: =IF(AND(C15<>"", COUNTIF('マスタ'!$C:$C, C15)=0), "マスタ未登録", "") | C15: =D15&D120&E15&F15&G15&H15 -> 通信費(原) | H15: 通信費(原) | J15: 83460 | K15: 0 | L15: 0 | M15: 0 | N15: 0 | O15: 0 | P15: 0 | Q15: 0 | R15: 0 | S15: 0 | T15: 0 | U15: 0 | V15: 83460
A16: {=XLOOKUP(C16, 'マスタ'!$C$2:$C$312, 'マスタ'!$D$2:$D$312, "マスタ未登録")} -> 当期商品仕入高 | B16: =IF(AND(C16<>"", COUNTIF('マスタ'!$C:$C, C16)=0), "マスタ未登録", "") | C16: =D16&D121&E16&F16&G16&H16 -> 消耗品費(原) | H16: 消耗品費(原) | J16: 878900 | K16: 0 | L16: 0 | M16: 0 | N16: 0 | O16: 0 | P16: 0 | Q16: 0 | R16: 0 | S16: 0 | T16: 0 | U16: 0 | V16: 878900
A17: {=XLOOKUP(C17, 'マスタ'!$C$2:$C$312, 'マスタ'!$D$2:$D$312, "マスタ未登録")} -> 当期商品仕入高 | B17: =IF(AND(C17<>"", COUNTIF('マスタ'!$C:$C, C17)=0), "マスタ未登録", "") | C17: =D17&D122&E17&F17&G17&H17 -> 賃借料(原) | H17: 賃借料(原) | J17: 522178 | K17: 0 | L17: 0 | M17: 0 | N17: 0 | O17: 0 | P17: 0 | Q17: 0 | R17: 0 | S17: 0 | T17: 0 | U17: 0 | V17: 522178
A18: {=XLOOKUP(C18, 'マスタ'!$C$2:$C$312, 'マスタ'!$D$2:$D$312, "マスタ未登録")} -> 他勘定振替高 | B18: =IF(AND(C18<>"", COUNTIF('マスタ'!$C:$C, C18)=0), "マスタ未登録", "") | C18: =D18&D123&E18&F18&G18&H18 -> 他勘定振替高(商) | G18: 他勘定振替高(商) | J18: 0 | K18: 0 | L18: 0 | M18: 0 | N18: 0 | O18: 0 | P18: 0 | Q18: 0 | R18: 0 | S18: 0 | T18: 0 | U18: 0 | V18: 0
A19: {=XLOOKUP(C19, 'マスタ'!$C$2:$C$312, 'マスタ'!$D$2:$D$312, "マスタ未登録")} -> マスタ未登録 | B19: =IF(AND(C19<>"", COUNTIF('マスタ'!$C:$C, C19)=0), "マスタ未登録", "") -> マスタ未登録 | C19: =D19&D124&E19&F19&G19&H19 -> 期末商品棚卸(見出し) | G19: 期末商品棚卸(見出し) | J19: -3052780 | K19: -3281827 | L19: 0 | M19: 0 | N19: 0 | O19: 0 | P19: 0 | Q19: 0 | R19: 0 | S19: 0 | T19: 0 | U19: 0 | V19: -6334607
A20: {=XLOOKUP(C20, 'マスタ'!$C$2:$C$312, 'マスタ'!$D$2:$D$312, "マスタ未登録")} -> 期末商品棚卸高 | B20: =IF(AND(C20<>"", COUNTIF('マスタ'!$C:$C, C20)=0), "マスタ未登録", "") | C20: =D20&D125&E20&F20&G20&H20 -> 期末商品棚卸高 | H20: 期末商品棚卸高 | J20: -3052780 | K20: -3281827 | L20: 0 | M20: 0 | N20: 0 | O20: 0 | P20: 0 | Q20: 0 | R20: 0 | S20: 0 | T20: 0 | U20: 0 | V20: -6334607
A21: {=XLOOKUP(C21, 'マスタ'!$C$2:$C$312, 'マスタ'!$D$2:$D$312, "マスタ未登録")} -> マスタ未登録 | B21: =IF(AND(C21<>"", COUNTIF('マスタ'!$C:$C, C21)=0), "マスタ未登録", "") -> マスタ未登録 | C21: =D21&D126&E21&F21&G21&H21 -> 商品売上原価 | F21: 商品売上原価 | J21: 11847579 | K21: 3467282 | L21: 0 | M21: 0 | N21: 0 | O21: 0 | P21: 0 | Q21: 0 | R21: 0 | S21: 0 | T21: 0 | U21: 0 | V21: 15314861
A22: {=XLOOKUP(C22, 'マスタ'!$C$2:$C$312, 'マスタ'!$D$2:$D$312, "マスタ未登録")} -> マスタ未登録 | B22: =IF(AND(C22<>"", COUNTIF('マスタ'!$C:$C, C22)=0), "マスタ未登録", "") -> マスタ未登録 | C22: =D22&D127&E22&F22&G22&H22 -> 売上総損益金額 | D22: 売上総損益金額 | J22: -4148617 | K22: -3467282 | L22: 0 | M22: 0 | N22: 0 | O22: 0 | P22: 0 | Q22: 0 | R22: 0 | S22: 0 | T22: 0 | U22: 0 | V22: -7615899
A23: {=XLOOKUP(C23, 'マスタ'!$C$2:$C$312, 'マスタ'!$D$2:$D$312, "マスタ未登録")} -> マスタ未登録 | B23: =IF(AND(C23<>"", COUNTIF('マスタ'!$C:$C, C23)=0), "マスタ未登録", "") -> マスタ未登録 | C23: =D23&D128&E23&F23&G23&H23 -> 販売管理費 | E23: 販売管理費
A24: {=XLOOKUP(C24, 'マスタ'!$C$2:$C$312, 'マスタ'!$D$2:$D$312, "マスタ未登録")} -> 販売促進費 | B24: =IF(AND(C24<>"", COUNTIF('マスタ'!$C:$C, C24)=0), "マスタ未登録", "") | C24: =D24&D129&E24&F24&G24&H24 -> 販売促進費 | F24: 販売促進費 | J24: 391000 | K24: 0 | L24: 0 | M24: 0 | N24: 0 | O24: 0 | P24: 0 | Q24: 0 | R24: 0 | S24: 0 | T24: 0 | U24: 0 | V24: 391000
A25: {=XLOOKUP(C25, 'マスタ'!$C$2:$C$312, 'マスタ'!$D$2:$D$312, "マスタ未登録")} -> 広告宣伝費 | B25: =IF(AND(C25<>"", COUNTIF('マスタ'!$C:$C, C25)=0), "マスタ未登録", "") | C25: =D25&D130&E25&F25&G25&H25 -> 広告宣伝費 | F25: 広告宣伝費 | J25: 1414856 | K25: 0 | L25: 0 | M25: 0 | N25: 0 | O25: 0 | P25: 0 | Q25: 0 | R25: 0 | S25: 0 | T25: 0 | U25: 0 | V25: 1414856
A26: {=XLOOKUP(C26, 'マスタ'!$C$2:$C$312, 'マスタ'!$D$2:$D$312, "マスタ未登録")} -> 荷造運賃 | B26: =IF(AND(C26<>"", COUNTIF('マスタ'!$C:$C, C26)=0), "マスタ未登録", "") | C26: =D26&D131&E26&F26&G26&H26 -> 荷造運賃 | F26: 荷造運賃 | J26: 454657 | K26: 0 | L26: 0 | M26: 0 | N26: 0 | O26: 0 | P26: 0 | Q26: 0 | R26: 0 | S26: 0 | T26: 0 | U26: 0 | V26: 454657
A27: {=XLOOKUP(C27, 'マスタ'!$C$2:$C$312, 'マスタ'!$D$2:$D$312, "マスタ未登録")} -> 支払手数料 | B27: =IF(AND(C27<>"", COUNTIF('マスタ'!$C:$C, C27)=0), "マスタ未登録", "") | C27: =D27&D132&E27&F27&G27&H27 -> 支払手数料 | F27: 支払手数料 | J27: 296439 | K27: 0 | L27: 0 | M27: 0 | N27: 0 | O27: 0 | P27: 0 | Q27: 0 | R27: 0 | S27: 0 | T27: 0 | U27: 0 | V27: 296439
A28: {=XLOOKUP(C28, 'マスタ'!$C$2:$C$312, 'マスタ'!$D$2:$D$312, "マスタ未登録")} -> 接待交際費 | B28: =IF(AND(C28<>"", COUNTIF('マスタ'!$C:$C, C28)=0), "マスタ未登録", "") | C28: =D28&D133&E28&F28&G28&H28 -> 交際費（11,000円以下/人） | F28: 交際費（11,000円以下/人） | J28: 27365 | K28: 0 | L28: 0 | M28: 0 | N28: 0 | O28: 0 | P28: 0 | Q28: 0 | R28: 0 | S28: 0 | T28: 0 | U28: 0 | V28: 27365
A29: {=XLOOKUP(C29, 'マスタ'!$C$2:$C$312, 'マスタ'!$D$2:$D$312, "マスタ未登録")} -> 接待交際費 | B29: =IF(AND(C29<>"", COUNTIF('マスタ'!$C:$C, C29)=0), "マスタ未登録", "") | C29: =D29&D134&E29&F29&G29&H29 -> 交際費（11,000円超/人） | F29: 交際費（11,000円超/人） | J29: 54264 | K29: 0 | L29: 0 | M29: 0 | N29: 0 | O29: 0 | P29: 0 | Q29: 0 | R29: 0 | S29: 0 | T29: 0 | U29: 0 | V29: 54264
A30: {=XLOOKUP(C30, 'マスタ'!$C$2:$C$312, 'マスタ'!$D$2:$D$312, "マスタ未登録")} -> 会議費 | B30: =IF(AND(C30<>"", COUNTIF('マスタ'!$C:$C, C30)=0), "マスタ未登録", "") | C30: =D30&D135&E30&F30&G30&H30 -> 会議費 | F30: 会議費 | J30: 3280 | K30: 0 | L30: 0 | M30: 0 | N30: 0 | O30: 0 | P30: 0 | Q30: 0 | R30: 0 | S30: 0 | T30: 0 | U30: 0 | V30: 3280
A31: {=XLOOKUP(C31, 'マスタ'!$C$2:$C$312, 'マスタ'!$D$2:$D$312, "マスタ未登録")} -> 減価償却費 | B31: =IF(AND(C31<>"", COUNTIF('マスタ'!$C:$C, C31)=0), "マスタ未登録", "") | C31: =D31&D136&E31&F31&G31&H31 -> 減価償却費 | F31: 減価償却費 | J31: 66879 | K31: 0 | L31: 0 | M31: 0 | N31: 0 | O31: 0 | P31: 0 | Q31: 0 | R31: 0 | S31: 0 | T31: 0 | U31: 0 | V31: 66879
A32: {=XLOOKUP(C32, 'マスタ'!$C$2:$C$312, 'マスタ'!$D$2:$D$312, "マスタ未登録")} -> マスタ未登録 | B32: =IF(AND(C32<>"", COUNTIF('マスタ'!$C:$C, C32)=0), "マスタ未登録", "") -> マスタ未登録 | C32: =D32&D137&E32&F32&G32&H32 -> 販売管理費 計 | E32: 販売管理費 計 | J32: 2708740 | K32: 0 | L32: 0 | M32: 0 | N32: 0 | O32: 0 | P32: 0 | Q32: 0 | R32: 0 | S32: 0 | T32: 0 | U32: 0 | V32: 2708740
A33: {=XLOOKUP(C33, 'マスタ'!$C$2:$C$312, 'マスタ'!$D$2:$D$312, "マスタ未登録")} -> マスタ未登録 | B33: =IF(AND(C33<>"", COUNTIF('マスタ'!$C:$C, C33)=0), "マスタ未登録", "") -> マスタ未登録 | C33: =D33&D138&E33&F33&G33&H33 -> 営業損益金額 | D33: 営業損益金額 | J33: -6857357 | K33: -3467282 | L33: 0 | M33: 0 | N33: 0 | O33: 0 | P33: 0 | Q33: 0 | R33: 0 | S33: 0 | T33: 0 | U33: 0 | V33: -10324639
A34: {=XLOOKUP(C34, 'マスタ'!$C$2:$C$312, 'マスタ'!$D$2:$D$312, "マスタ未登録")} -> マスタ未登録 | B34: =IF(AND(C34<>"", COUNTIF('マスタ'!$C:$C, C34)=0), "マスタ未登録", "") -> マスタ未登録 | C34: =D34&D139&E34&F34&G34&H34 -> 営業外収益 | E34: 営業外収益 | J34: 0 | K34: 0 | L34: 0 | M34: 0 | N34: 0 | O34: 0 | P34: 0 | Q34: 0 | R34: 0 | S34: 0 | T34: 0 | U34: 0 | V34: 0
A35: {=XLOOKUP(C35, 'マスタ'!$C$2:$C$312, 'マスタ'!$D$2:$D$312, "マスタ未登録")} -> マスタ未登録 | B35: =IF(AND(C35<>"", COUNTIF('マスタ'!$C:$C, C35)=0), "マスタ未登録", "") -> マスタ未登録 | C35: =D35&D140&E35&F35&G35&H35 -> 営業外費用 | E35: 営業外費用 | J35: 0 | K35: 0 | L35: 0 | M35: 0 | N35: 0 | O35: 0 | P35: 0 | Q35: 0 | R35: 0 | S35: 0 | T35: 0 | U35: 0 | V35: 0
A36: {=XLOOKUP(C36, 'マスタ'!$C$2:$C$312, 'マスタ'!$D$2:$D$312, "マスタ未登録")} -> マスタ未登録 | B36: =IF(AND(C36<>"", COUNTIF('マスタ'!$C:$C, C36)=0), "マスタ未登録", "") -> マスタ未登録 | C36: =D36&D141&E36&F36&G36&H36 -> 経常損益金額 | D36: 経常損益金額 | J36: -6857357 | K36: -3467282 | L36: 0 | M36: 0 | N36: 0 | O36: 0 | P36: 0 | Q36: 0 | R36: 0 | S36: 0 | T36: 0 | U36: 0 | V36: -10324639
A37: {=XLOOKUP(C37, 'マスタ'!$C$2:$C$312, 'マスタ'!$D$2:$D$312, "マスタ未登録")} -> マスタ未登録 | B37: =IF(AND(C37<>"", COUNTIF('マスタ'!$C:$C, C37)=0), "マスタ未登録", "") -> マスタ未登録 | C37: =D37&D142&E37&F37&G37&H37 -> 特別利益 | E37: 特別利益 | J37: 0 | K37: 0 | L37: 0 | M37: 0 | N37: 0 | O37: 0 | P37: 0 | Q37: 0 | R37: 0 | S37: 0 | T37: 0 | U37: 0 | V37: 0
A38: {=XLOOKUP(C38, 'マスタ'!$C$2:$C$312, 'マスタ'!$D$2:$D$312, "マスタ未登録")} -> マスタ未登録 | B38: =IF(AND(C38<>"", COUNTIF('マスタ'!$C:$C, C38)=0), "マスタ未登録", "") -> マスタ未登録 | C38: =D38&D143&E38&F38&G38&H38 -> 特別損失 | E38: 特別損失 | J38: 0 | K38: 0 | L38: 0 | M38: 0 | N38: 0 | O38: 0 | P38: 0 | Q38: 0 | R38: 0 | S38: 0 | T38: 0 | U38: 0 | V38: 0
A39: {=XLOOKUP(C39, 'マスタ'!$C$2:$C$312, 'マスタ'!$D$2:$D$312, "マスタ未登録")} -> マスタ未登録 | B39: =IF(AND(C39<>"", COUNTIF('マスタ'!$C:$C, C39)=0), "マスタ未登録", "") -> マスタ未登録 | C39: =D39&D144&E39&F39&G39&H39 -> 税引前当期純損益金額 | D39: 税引前当期純損益金額 | J39: -6857357 | K39: -3467282 | L39: 0 | M39: 0 | N39: 0 | O39: 0 | P39: 0 | Q39: 0 | R39: 0 | S39: 0 | T39: 0 | U39: 0 | V39: -10324639
A40: {=XLOOKUP(C40, 'マスタ'!$C$2:$C$312, 'マスタ'!$D$2:$D$312, "マスタ未登録")} -> 法人税等 | B40: =IF(AND(C40<>"", COUNTIF('マスタ'!$C:$C, C40)=0), "マスタ未登録", "") | C40: =D40&D145&E40&F40&G40&H40 -> 法人税等 | E40: 法人税等 | J40: 0 | K40: 0 | L40: 0 | M40: 0 | N40: 0 | O40: 0 | P40: 0 | Q40: 0 | R40: 0 | S40: 0 | T40: 0 | U40: 0 | V40: 0
A41: {=XLOOKUP(C41, 'マスタ'!$C$2:$C$312, 'マスタ'!$D$2:$D$312, "マスタ未登録")} -> 法人税等調整額 | B41: =IF(AND(C41<>"", COUNTIF('マスタ'!$C:$C, C41)=0), "マスタ未登録", "") | C41: =D41&D146&E41&F41&G41&H41 -> 法人税等調整額 | E41: 法人税等調整額 | J41: 0 | K41: 0 | L41: 0 | M41: 0 | N41: 0 | O41: 0 | P41: 0 | Q41: 0 | R41: 0 | S41: 0 | T41: 0 | U41: 0 | V41: 0
A42: {=XLOOKUP(C42, 'マスタ'!$C$2:$C$312, 'マスタ'!$D$2:$D$312, "マスタ未登録")} -> マスタ未登録 | B42: =IF(AND(C42<>"", COUNTIF('マスタ'!$C:$C, C42)=0), "マスタ未登録", "") -> マスタ未登録 | C42: =D42&D147&E42&F42&G42&H42 -> 当期純損益金額 | D42: 当期純損益金額 | J42: -6857357 | K42: -3467282 | L42: 0 | M42: 0 | N42: 0 | O42: 0 | P42: 0 | Q42: 0 | R42: 0 | S42: 0 | T42: 0 | U42: 0 | V42: -10324639
B43: =IF(AND(C43<>"", COUNTIF('マスタ'!$C:$C, C43)=0), "マスタ未登録", "") | C43: =D43&D148&E43&F43&G43&H43
B44: =IF(AND(C44<>"", COUNTIF('マスタ'!$C:$C, C44)=0), "マスタ未登録", "") | C44: =D44&D149&E44&F44&G44&H44
B45: =IF(AND(C45<>"", COUNTIF('マスタ'!$C:$C, C45)=0), "マスタ未登録", "") | C45: =D45&D150&E45&F45&G45&H45
B46: =IF(AND(C46<>"", COUNTIF('マスタ'!$C:$C, C46)=0), "マスタ未登録", "") | C46: =D46&D151&E46&F46&G46&H46
B47: =IF(AND(C47<>"", COUNTIF('マスタ'!$C:$C, C47)=0), "マスタ未登録", "") | C47: =D47&D152&E47&F47&G47&H47
B48: =IF(AND(C48<>"", COUNTIF('マスタ'!$C:$C, C48)=0), "マスタ未登録", "") | C48: =D48&D153&E48&F48&G48&H48
B49: =IF(AND(C49<>"", COUNTIF('マスタ'!$C:$C, C49)=0), "マスタ未登録", "") | C49: =D49&D154&E49&F49&G49&H49
B50: =IF(AND(C50<>"", COUNTIF('マスタ'!$C:$C, C50)=0), "マスタ未登録", "") | C50: =D50&D155&E50&F50&G50&H50
B51: =IF(AND(C51<>"", COUNTIF('マスタ'!$C:$C, C51)=0), "マスタ未登録", "") | C51: =D51&D156&E51&F51&G51&H51
B52: =IF(AND(C52<>"", COUNTIF('マスタ'!$C:$C, C52)=0), "マスタ未登録", "") | C52: =D52&D157&E52&F52&G52&H52
B53: =IF(AND(C53<>"", COUNTIF('マスタ'!$C:$C, C53)=0), "マスタ未登録", "") | C53: =D53&D158&E53&F53&G53&H53
B54: =IF(AND(C54<>"", COUNTIF('マスタ'!$C:$C, C54)=0), "マスタ未登録", "") | C54: =D54&D159&E54&F54&G54&H54
... B56: =IF(AND(C56<>"", COUNTIF('マスタ'!$C:$C, C56)=0), "マスタ未登録", "") | C56: =D56&D161&E56&F56&G56&H56

Sheet VO_PL(GLASS)
A1: VO_PL(GLASS) | B1: ②マスタ結びつけ | C1: ① | D1: 月次推移：損益計算書_株式会社VOISING（期間：2026年04月〜2027年03月、表示単位：円）
J2: 46113 | K2: 46143 | L2: 46174 | M2: 46204 | N2: 46235 | O2: 46266 | P2: 46296 | Q2: 46327 | R2: 46357 | S2: 46388 | T2: 46419 | U2: 46447 | V2: 期間累計
D3: 売上高
A4: {=XLOOKUP(C4, 'マスタ'!$C$2:$C$312, 'マスタ'!$D$2:$D$312, "マスタ未登録")} -> 売上高 | B4: =IF(AND(C4<>"", COUNTIF('マスタ'!$C:$C, C4)=0), "マスタ未登録", "") | C4: =D4&D109&E4&F4&G4&H4 -> 売上高 | E4: 売上高 | J4: 46858362 | K4: 0 | L4: 0 | M4: 0 | N4: 0 | O4: 0 | P4: 0 | Q4: 0 | R4: 0 | S4: 0 | T4: 0 | U4: 0 | V4: 46858362
A5: {=XLOOKUP(C5, 'マスタ'!$C$2:$C$312, 'マスタ'!$D$2:$D$312, "マスタ未登録")} -> 売上高 | B5: =IF(AND(C5<>"", COUNTIF('マスタ'!$C:$C, C5)=0), "マスタ未登録", "") | C5: =D5&D110&E5&F5&G5&H5 -> 委託販売売上高 | E5: 委託販売売上高 | J5: 2172729 | K5: 0 | L5: 0 | M5: 0 | N5: 0 | O5: 0 | P5: 0 | Q5: 0 | R5: 0 | S5: 0 | T5: 0 | U5: 0 | V5: 2172729
A6: {=XLOOKUP(C6, 'マスタ'!$C$2:$C$312, 'マスタ'!$D$2:$D$312, "マスタ未登録")} -> マスタ未登録 | B6: =IF(AND(C6<>"", COUNTIF('マスタ'!$C:$C, C6)=0), "マスタ未登録", "") -> マスタ未登録 | C6: =D6&D111&E6&F6&G6&H6 -> 売上高 計 | D6: 売上高 計 | J6: 49031091 | K6: 0 | L6: 0 | M6: 0 | N6: 0 | O6: 0 | P6: 0 | Q6: 0 | R6: 0 | S6: 0 | T6: 0 | U6: 0 | V6: 49031091
A7: {=XLOOKUP(C7, 'マスタ'!$C$2:$C$312, 'マスタ'!$D$2:$D$312, "マスタ未登録")} -> マスタ未登録 | B7: =IF(AND(C7<>"", COUNTIF('マスタ'!$C:$C, C7)=0), "マスタ未登録", "") -> マスタ未登録 | C7: =D7&D112&E7&F7&G7&H7 -> 売上原価 | E7: 売上原価
A8: {=XLOOKUP(C8, 'マスタ'!$C$2:$C$312, 'マスタ'!$D$2:$D$312, "マスタ未登録")} -> マスタ未登録 | B8: =IF(AND(C8<>"", COUNTIF('マスタ'!$C:$C, C8)=0), "マスタ未登録", "") -> マスタ未登録 | C8: =D8&D113&E8&F8&G8&H8 -> 売上原価 | E8: 売上原価 | J8: 33447897 | K8: 1709448 | L8: 0 | M8: 0 | N8: 0 | O8: 0 | P8: 0 | Q8: 0 | R8: 0 | S8: 0 | T8: 0 | U8: 0 | V8: 35157345
A9: {=XLOOKUP(C9, 'マスタ'!$C$2:$C$312, 'マスタ'!$D$2:$D$312, "マスタ未登録")} -> 期首商品棚卸高 | B9: =IF(AND(C9<>"", COUNTIF('マスタ'!$C:$C, C9)=0), "マスタ未登録", "") | C9: =D9&D114&E9&F9&G9&H9 -> 期首商品棚卸 | G9: 期首商品棚卸 | J9: 0 | K9: 0 | L9: 0 | M9: 0 | N9: 0 | O9: 0 | P9: 0 | Q9: 0 | R9: 0 | S9: 0 | T9: 0 | U9: 0 | V9: 0
A10: {=XLOOKUP(C10, 'マスタ'!$C$2:$C$312, 'マスタ'!$D$2:$D$312, "マスタ未登録")} -> マスタ未登録 | B10: =IF(AND(C10<>"", COUNTIF('マスタ'!$C:$C, C10)=0), "マスタ未登録", "") -> マスタ未登録 | C10: =D10&D115&E10&F10&G10&H10 -> 当期商品仕入合計 | G10: 当期商品仕入合計 | J10: 33538543 | K10: 150000 | L10: 0 | M10: 0 | N10: 0 | O10: 0 | P10: 0 | Q10: 0 | R10: 0 | S10: 0 | T10: 0 | U10: 0 | V10: 33688543
A11: {=XLOOKUP(C11, 'マスタ'!$C$2:$C$312, 'マスタ'!$D$2:$D$312, "マスタ未登録")} -> 当期商品仕入高 | B11: =IF(AND(C11<>"", COUNTIF('マスタ'!$C:$C, C11)=0), "マスタ未登録", "") | C11: =D11&D116&E11&F11&G11&H11 -> 仕入高 | H11: 仕入高 | J11: 4587586 | K11: 0 | L11: 0 | M11: 0 | N11: 0 | O11: 0 | P11: 0 | Q11: 0 | R11: 0 | S11: 0 | T11: 0 | U11: 0 | V11: 4587586
A12: {=XLOOKUP(C12, 'マスタ'!$C$2:$C$312, 'マスタ'!$D$2:$D$312, "マスタ未登録")} -> 当期商品仕入高 | B12: =IF(AND(C12<>"", COUNTIF('マスタ'!$C:$C, C12)=0), "マスタ未登録", "") | C12: =D12&D117&E12&F12&G12&H12 -> 外注費(原) | H12: 外注費(原) | J12: 23641759 | K12: 150000 | L12: 0 | M12: 0 | N12: 0 | O12: 0 | P12: 0 | Q12: 0 | R12: 0 | S12: 0 | T12: 0 | U12: 0 | V12: 23791759
A13: {=XLOOKUP(C13, 'マスタ'!$C$2:$C$312, 'マスタ'!$D$2:$D$312, "マスタ未登録")} -> 当期商品仕入高 | B13: =IF(AND(C13<>"", COUNTIF('マスタ'!$C:$C, C13)=0), "マスタ未登録", "") | C13: =D13&D118&E13&F13&G13&H13 -> 業務委託費(原・タレント) | H13: 業務委託費(原・タレント) | J13: 3108000 | K13: 0 | L13: 0 | M13: 0 | N13: 0 | O13: 0 | P13: 0 | Q13: 0 | R13: 0 | S13: 0 | T13: 0 | U13: 0 | V13: 3108000
A14: {=XLOOKUP(C14, 'マスタ'!$C$2:$C$312, 'マスタ'!$D$2:$D$312, "マスタ未登録")} -> 当期商品仕入高 | B14: =IF(AND(C14<>"", COUNTIF('マスタ'!$C:$C, C14)=0), "マスタ未登録", "") | C14: =D14&D119&E14&F14&G14&H14 -> 業務委託費(原・製) | H14: 業務委託費(原・製) | J14: 1042250 | K14: 0 | L14: 0 | M14: 0 | N14: 0 | O14: 0 | P14: 0 | Q14: 0 | R14: 0 | S14: 0 | T14: 0 | U14: 0 | V14: 1042250
A15: {=XLOOKUP(C15, 'マスタ'!$C$2:$C$312, 'マスタ'!$D$2:$D$312, "マスタ未登録")} -> 当期商品仕入高 | B15: =IF(AND(C15<>"", COUNTIF('マスタ'!$C:$C, C15)=0), "マスタ未登録", "") | C15: =D15&D120&E15&F15&G15&H15 -> 旅費交通費(原) | H15: 旅費交通費(原) | J15: 282633 | K15: 0 | L15: 0 | M15: 0 | N15: 0 | O15: 0 | P15: 0 | Q15: 0 | R15: 0 | S15: 0 | T15: 0 | U15: 0 | V15: 282633
A16: {=XLOOKUP(C16, 'マスタ'!$C$2:$C$312, 'マスタ'!$D$2:$D$312, "マスタ未登録")} -> 当期商品仕入高 | B16: =IF(AND(C16<>"", COUNTIF('マスタ'!$C:$C, C16)=0), "マスタ未登録", "") | C16: =D16&D121&E16&F16&G16&H16 -> 消耗品費(原) | H16: 消耗品費(原) | J16: 33331 | K16: 0 | L16: 0 | M16: 0 | N16: 0 | O16: 0 | P16: 0 | Q16: 0 | R16: 0 | S16: 0 | T16: 0 | U16: 0 | V16: 33331
A17: {=XLOOKUP(C17, 'マスタ'!$C$2:$C$312, 'マスタ'!$D$2:$D$312, "マスタ未登録")} -> 当期商品仕入高 | B17: =IF(AND(C17<>"", COUNTIF('マスタ'!$C:$C, C17)=0), "マスタ未登録", "") | C17: =D17&D122&E17&F17&G17&H17 -> 賃借料(原) | H17: 賃借料(原) | J17: 842984 | K17: 0 | L17: 0 | M17: 0 | N17: 0 | O17: 0 | P17: 0 | Q17: 0 | R17: 0 | S17: 0 | T17: 0 | U17: 0 | V17: 842984
A18: {=XLOOKUP(C18, 'マスタ'!$C$2:$C$312, 'マスタ'!$D$2:$D$312, "マスタ未登録")} -> 他勘定振替高 | B18: =IF(AND(C18<>"", COUNTIF('マスタ'!$C:$C, C18)=0), "マスタ未登録", "") | C18: =D18&D123&E18&F18&G18&H18 -> 他勘定振替高(商) | G18: 他勘定振替高(商) | J18: 0 | K18: 0 | L18: 0 | M18: 0 | N18: 0 | O18: 0 | P18: 0 | Q18: 0 | R18: 0 | S18: 0 | T18: 0 | U18: 0 | V18: 0
A19: {=XLOOKUP(C19, 'マスタ'!$C$2:$C$312, 'マスタ'!$D$2:$D$312, "マスタ未登録")} -> マスタ未登録 | B19: =IF(AND(C19<>"", COUNTIF('マスタ'!$C:$C, C19)=0), "マスタ未登録", "") -> マスタ未登録 | C19: =D19&D124&E19&F19&G19&H19 -> 期末商品棚卸合計 | G19: 期末商品棚卸合計 | J19: 90646 | K19: -1559448 | L19: 0 | M19: 0 | N19: 0 | O19: 0 | P19: 0 | Q19: 0 | R19: 0 | S19: 0 | T19: 0 | U19: 0 | V19: -1468802
A20: {=XLOOKUP(C20, 'マスタ'!$C$2:$C$312, 'マスタ'!$D$2:$D$312, "マスタ未登録")} -> 期末商品棚卸高 | B20: =IF(AND(C20<>"", COUNTIF('マスタ'!$C:$C, C20)=0), "マスタ未登録", "") | C20: =D20&D125&E20&F20&G20&H20 -> 期末商品棚卸高 | H20: 期末商品棚卸高 | J20: 90646 | K20: -1559448 | L20: 0 | M20: 0 | N20: 0 | O20: 0 | P20: 0 | Q20: 0 | R20: 0 | S20: 0 | T20: 0 | U20: 0 | V20: -1468802
A21: {=XLOOKUP(C21, 'マスタ'!$C$2:$C$312, 'マスタ'!$D$2:$D$312, "マスタ未登録")} -> マスタ未登録 | B21: =IF(AND(C21<>"", COUNTIF('マスタ'!$C:$C, C21)=0), "マスタ未登録", "") -> マスタ未登録 | C21: =D21&D126&E21&F21&G21&H21 -> 商品売上原価 | F21: 商品売上原価 | J21: 33447897 | K21: 1709448 | L21: 0 | M21: 0 | N21: 0 | O21: 0 | P21: 0 | Q21: 0 | R21: 0 | S21: 0 | T21: 0 | U21: 0 | V21: 35157345
A22: {=XLOOKUP(C22, 'マスタ'!$C$2:$C$312, 'マスタ'!$D$2:$D$312, "マスタ未登録")} -> マスタ未登録 | B22: =IF(AND(C22<>"", COUNTIF('マスタ'!$C:$C, C22)=0), "マスタ未登録", "") -> マスタ未登録 | C22: =D22&D127&E22&F22&G22&H22 -> 売上総損益金額 | D22: 売上総損益金額 | J22: 15583194 | K22: -1709448 | L22: 0 | M22: 0 | N22: 0 | O22: 0 | P22: 0 | Q22: 0 | R22: 0 | S22: 0 | T22: 0 | U22: 0 | V22: 13873746
A23: {=XLOOKUP(C23, 'マスタ'!$C$2:$C$312, 'マスタ'!$D$2:$D$312, "マスタ未登録")} -> マスタ未登録 | B23: =IF(AND(C23<>"", COUNTIF('マスタ'!$C:$C, C23)=0), "マスタ未登録", "") -> マスタ未登録 | C23: =D23&D128&E23&F23&G23&H23 -> 販売管理費 | E23: 販売管理費
A24: {=XLOOKUP(C24, 'マスタ'!$C$2:$C$312, 'マスタ'!$D$2:$D$312, "マスタ未登録")} -> 販売促進費 | B24: =IF(AND(C24<>"", COUNTIF('マスタ'!$C:$C, C24)=0), "マスタ未登録", "") | C24: =D24&D129&E24&F24&G24&H24 -> 販売促進費 | F24: 販売促進費 | J24: 630080 | K24: 0 | L24: 0 | M24: 0 | N24: 0 | O24: 0 | P24: 0 | Q24: 0 | R24: 0 | S24: 0 | T24: 0 | U24: 0 | V24: 630080
A25: {=XLOOKUP(C25, 'マスタ'!$C$2:$C$312, 'マスタ'!$D$2:$D$312, "マスタ未登録")} -> 広告宣伝費 | B25: =IF(AND(C25<>"", COUNTIF('マスタ'!$C:$C, C25)=0), "マスタ未登録", "") | C25: =D25&D130&E25&F25&G25&H25 -> 広告宣伝費 | F25: 広告宣伝費 | J25: 89975 | K25: 0 | L25: 0 | M25: 0 | N25: 0 | O25: 0 | P25: 0 | Q25: 0 | R25: 0 | S25: 0 | T25: 0 | U25: 0 | V25: 89975
A26: {=XLOOKUP(C26, 'マスタ'!$C$2:$C$312, 'マスタ'!$D$2:$D$312, "マスタ未登録")} -> 荷造運賃 | B26: =IF(AND(C26<>"", COUNTIF('マスタ'!$C:$C, C26)=0), "マスタ未登録", "") | C26: =D26&D131&E26&F26&G26&H26 -> 荷造運賃 | F26: 荷造運賃 | J26: 1431202 | K26: 0 | L26: 0 | M26: 0 | N26: 0 | O26: 0 | P26: 0 | Q26: 0 | R26: 0 | S26: 0 | T26: 0 | U26: 0 | V26: 1431202
A27: {=XLOOKUP(C27, 'マスタ'!$C$2:$C$312, 'マスタ'!$D$2:$D$312, "マスタ未登録")} -> 支払手数料 | B27: =IF(AND(C27<>"", COUNTIF('マスタ'!$C:$C, C27)=0), "マスタ未登録", "") | C27: =D27&D132&E27&F27&G27&H27 -> 支払手数料 | F27: 支払手数料 | J27: 1273507 | K27: 0 | L27: 0 | M27: 0 | N27: 0 | O27: 0 | P27: 0 | Q27: 0 | R27: 0 | S27: 0 | T27: 0 | U27: 0 | V27: 1273507
A28: {=XLOOKUP(C28, 'マスタ'!$C$2:$C$312, 'マスタ'!$D$2:$D$312, "マスタ未登録")} -> 接待交際費 | B28: =IF(AND(C28<>"", COUNTIF('マスタ'!$C:$C, C28)=0), "マスタ未登録", "") | C28: =D28&D133&E28&F28&G28&H28 -> 交際費（11,000円超/人） | F28: 交際費（11,000円超/人） | J28: 21637 | K28: 0 | L28: 0 | M28: 0 | N28: 0 | O28: 0 | P28: 0 | Q28: 0 | R28: 0 | S28: 0 | T28: 0 | U28: 0 | V28: 21637
A29: {=XLOOKUP(C29, 'マスタ'!$C$2:$C$312, 'マスタ'!$D$2:$D$312, "マスタ未登録")} -> 減価償却費 | B29: =IF(AND(C29<>"", COUNTIF('マスタ'!$C:$C, C29)=0), "マスタ未登録", "") | C29: =D29&D134&E29&F29&G29&H29 -> 減価償却費 | F29: 減価償却費 | J29: 66480 | K29: 0 | L29: 0 | M29: 0 | N29: 0 | O29: 0 | P29: 0 | Q29: 0 | R29: 0 | S29: 0 | T29: 0 | U29: 0 | V29: 66480
A30: {=XLOOKUP(C30, 'マスタ'!$C$2:$C$312, 'マスタ'!$D$2:$D$312, "マスタ未登録")} -> マスタ未登録 | B30: =IF(AND(C30<>"", COUNTIF('マスタ'!$C:$C, C30)=0), "マスタ未登録", "") -> マスタ未登録 | C30: =D30&D135&E30&F30&G30&H30 -> 販売管理費 計 | E30: 販売管理費 計 | J30: 3512881 | K30: 0 | L30: 0 | M30: 0 | N30: 0 | O30: 0 | P30: 0 | Q30: 0 | R30: 0 | S30: 0 | T30: 0 | U30: 0 | V30: 3512881
A31: {=XLOOKUP(C31, 'マスタ'!$C$2:$C$312, 'マスタ'!$D$2:$D$312, "マスタ未登録")} -> マスタ未登録 | B31: =IF(AND(C31<>"", COUNTIF('マスタ'!$C:$C, C31)=0), "マスタ未登録", "") -> マスタ未登録 | C31: =D31&D136&E31&F31&G31&H31 -> 営業損益金額 | D31: 営業損益金額 | J31: 12070313 | K31: -1709448 | L31: 0 | M31: 0 | N31: 0 | O31: 0 | P31: 0 | Q31: 0 | R31: 0 | S31: 0 | T31: 0 | U31: 0 | V31: 10360865
A32: {=XLOOKUP(C32, 'マスタ'!$C$2:$C$312, 'マスタ'!$D$2:$D$312, "マスタ未登録")} -> マスタ未登録 | B32: =IF(AND(C32<>"", COUNTIF('マスタ'!$C:$C, C32)=0), "マスタ未登録", "") -> マスタ未登録 | C32: =D32&D137&E32&F32&G32&H32 -> 営業外収益 | E32: 営業外収益 | J32: 6701 | K32: 0 | L32: 0 | M32: 0 | N32: 0 | O32: 0 | P32: 0 | Q32: 0 | R32: 0 | S32: 0 | T32: 0 | U32: 0 | V32: 6701
A33: {=XLOOKUP(C33, 'マスタ'!$C$2:$C$312, 'マスタ'!$D$2:$D$312, "マスタ未登録")} -> 受取利息 | B33: =IF(AND(C33<>"", COUNTIF('マスタ'!$C:$C, C33)=0), "マスタ未登録", "") | C33: =D33&D138&E33&F33&G33&H33 -> 受取利息 | F33: 受取利息 | J33: 6701 | K33: 0 | L33: 0 | M33: 0 | N33: 0 | O33: 0 | P33: 0 | Q33: 0 | R33: 0 | S33: 0 | T33: 0 | U33: 0 | V33: 6701
A34: {=XLOOKUP(C34, 'マスタ'!$C$2:$C$312, 'マスタ'!$D$2:$D$312, "マスタ未登録")} -> マスタ未登録 | B34: =IF(AND(C34<>"", COUNTIF('マスタ'!$C:$C, C34)=0), "マスタ未登録", "") -> マスタ未登録 | C34: =D34&D139&E34&F34&G34&H34 -> 営業外費用 | E34: 営業外費用 | J34: 0 | K34: 0 | L34: 0 | M34: 0 | N34: 0 | O34: 0 | P34: 0 | Q34: 0 | R34: 0 | S34: 0 | T34: 0 | U34: 0 | V34: 0
A35: {=XLOOKUP(C35, 'マスタ'!$C$2:$C$312, 'マスタ'!$D$2:$D$312, "マスタ未登録")} -> マスタ未登録 | B35: =IF(AND(C35<>"", COUNTIF('マスタ'!$C:$C, C35)=0), "マスタ未登録", "") -> マスタ未登録 | C35: =D35&D140&E35&F35&G35&H35 -> 経常損益金額 | D35: 経常損益金額 | J35: 12077014 | K35: -1709448 | L35: 0 | M35: 0 | N35: 0 | O35: 0 | P35: 0 | Q35: 0 | R35: 0 | S35: 0 | T35: 0 | U35: 0 | V35: 10367566
A36: {=XLOOKUP(C36, 'マスタ'!$C$2:$C$312, 'マスタ'!$D$2:$D$312, "マスタ未登録")} -> マスタ未登録 | B36: =IF(AND(C36<>"", COUNTIF('マスタ'!$C:$C, C36)=0), "マスタ未登録", "") -> マスタ未登録 | C36: =D36&D141&E36&F36&G36&H36 -> 特別利益 | E36: 特別利益 | J36: 0 | K36: 0 | L36: 0 | M36: 0 | N36: 0 | O36: 0 | P36: 0 | Q36: 0 | R36: 0 | S36: 0 | T36: 0 | U36: 0 | V36: 0
A37: {=XLOOKUP(C37, 'マスタ'!$C$2:$C$312, 'マスタ'!$D$2:$D$312, "マスタ未登録")} -> マスタ未登録 | B37: =IF(AND(C37<>"", COUNTIF('マスタ'!$C:$C, C37)=0), "マスタ未登録", "") -> マスタ未登録 | C37: =D37&D142&E37&F37&G37&H37 -> 特別損失 | E37: 特別損失 | J37: 0 | K37: 0 | L37: 0 | M37: 0 | N37: 0 | O37: 0 | P37: 0 | Q37: 0 | R37: 0 | S37: 0 | T37: 0 | U37: 0 | V37: 0
A38: {=XLOOKUP(C38, 'マスタ'!$C$2:$C$312, 'マスタ'!$D$2:$D$312, "マスタ未登録")} -> マスタ未登録 | B38: =IF(AND(C38<>"", COUNTIF('マスタ'!$C:$C, C38)=0), "マスタ未登録", "") -> マスタ未登録 | C38: =D38&D143&E38&F38&G38&H38 -> 税引前当期純損益金額 | D38: 税引前当期純損益金額 | J38: 12077014 | K38: -1709448 | L38: 0 | M38: 0 | N38: 0 | O38: 0 | P38: 0 | Q38: 0 | R38: 0 | S38: 0 | T38: 0 | U38: 0 | V38: 10367566
A39: {=XLOOKUP(C39, 'マスタ'!$C$2:$C$312, 'マスタ'!$D$2:$D$312, "マスタ未登録")} -> 法人税等 | B39: =IF(AND(C39<>"", COUNTIF('マスタ'!$C:$C, C39)=0), "マスタ未登録", "") | C39: =D39&D144&E39&F39&G39&H39 -> 法人税等 | E39: 法人税等 | J39: 0 | K39: 0 | L39: 0 | M39: 0 | N39: 0 | O39: 0 | P39: 0 | Q39: 0 | R39: 0 | S39: 0 | T39: 0 | U39: 0 | V39: 0
A40: {=XLOOKUP(C40, 'マスタ'!$C$2:$C$312, 'マスタ'!$D$2:$D$312, "マスタ未登録")} -> 法人税等調整額 | B40: =IF(AND(C40<>"", COUNTIF('マスタ'!$C:$C, C40)=0), "マスタ未登録", "") | C40: =D40&D145&E40&F40&G40&H40 -> 法人税等調整額 | E40: 法人税等調整額 | J40: 0 | K40: 0 | L40: 0 | M40: 0 | N40: 0 | O40: 0 | P40: 0 | Q40: 0 | R40: 0 | S40: 0 | T40: 0 | U40: 0 | V40: 0
A41: {=XLOOKUP(C41, 'マスタ'!$C$2:$C$312, 'マスタ'!$D$2:$D$312, "マスタ未登録")} -> マスタ未登録 | B41: =IF(AND(C41<>"", COUNTIF('マスタ'!$C:$C, C41)=0), "マスタ未登録", "") -> マスタ未登録 | C41: =D41&D146&E41&F41&G41&H41 -> 当期純損益金額 | D41: 当期純損益金額 | J41: 12077014 | K41: -1709448 | L41: 0 | M41: 0 | N41: 0 | O41: 0 | P41: 0 | Q41: 0 | R41: 0 | S41: 0 | T41: 0 | U41: 0 | V41: 10367566
B42: =IF(AND(C42<>"", COUNTIF('マスタ'!$C:$C, C42)=0), "マスタ未登録", "") | C42: =D42&D147&E42&F42&G42&H42
B43: =IF(AND(C43<>"", COUNTIF('マスタ'!$C:$C, C43)=0), "マスタ未登録", "") | C43: =D43&D148&E43&F43&G43&H43
B44: =IF(AND(C44<>"", COUNTIF('マスタ'!$C:$C, C44)=0), "マスタ未登録", "") | C44: =D44&D149&E44&F44&G44&H44
B45: =IF(AND(C45<>"", COUNTIF('マスタ'!$C:$C, C45)=0), "マスタ未登録", "") | C45: =D45&D150&E45&F45&G45&H45
B46: =IF(AND(C46<>"", COUNTIF('マスタ'!$C:$C, C46)=0), "マスタ未登録", "") | C46: =D46&D151&E46&F46&G46&H46
B47: =IF(AND(C47<>"", COUNTIF('マスタ'!$C:$C, C47)=0), "マスタ未登録", "") | C47: =D47&D152&E47&F47&G47&H47
B48: =IF(AND(C48<>"", COUNTIF('マスタ'!$C:$C, C48)=0), "マスタ未登録", "") | C48: =D48&D153&E48&F48&G48&H48
B49: =IF(AND(C49<>"", COUNTIF('マスタ'!$C:$C, C49)=0), "マスタ未登録", "") | C49: =D49&D154&E49&F49&G49&H49
B50: =IF(AND(C50<>"", COUNTIF('マスタ'!$C:$C, C50)=0), "マスタ未登録", "") | C50: =D50&D155&E50&F50&G50&H50
B51: =IF(AND(C51<>"", COUNTIF('マスタ'!$C:$C, C51)=0), "マスタ未登録", "") | C51: =D51&D156&E51&F51&G51&H51
B52: =IF(AND(C52<>"", COUNTIF('マスタ'!$C:$C, C52)=0), "マスタ未登録", "") | C52: =D52&D157&E52&F52&G52&H52
B53: =IF(AND(C53<>"", COUNTIF('マスタ'!$C:$C, C53)=0), "マスタ未登録", "") | C53: =D53&D158&E53&F53&G53&H53
... B56: =IF(AND(C56<>"", COUNTIF('マスタ'!$C:$C, C56)=0), "マスタ未登録", "") | C56: =D56&D161&E56&F56&G56&H56

Sheet VO_PL(ABYSS)
B1: ②マスタ結びつけ | C1: ① | D1: 月次推移：損益計算書_株式会社VOISING（期間：2026年04月〜2027年03月、表示単位：円）
J2: 46113 | K2: 46143 | L2: 46174 | M2: 46204 | N2: 46235 | O2: 46266 | P2: 46296 | Q2: 46327 | R2: 46357 | S2: 46388 | T2: 46419 | U2: 46447 | V2: 期間累計
D3: 売上高
A4: {=XLOOKUP(C4, 'マスタ'!$C$2:$C$312, 'マスタ'!$D$2:$D$312, "マスタ未登録")} -> 売上高 | B4: =IF(AND(C4<>"", COUNTIF('マスタ'!$C:$C, C4)=0), "マスタ未登録", "") | C4: =D4&D109&E4&F4&G4&H4 -> 売上高 | E4: 売上高 | J4: 2696700 | K4: 0 | L4: 0 | M4: 0 | N4: 0 | O4: 0 | P4: 0 | Q4: 0 | R4: 0 | S4: 0 | T4: 0 | U4: 0 | V4: 2696700
A5: {=XLOOKUP(C5, 'マスタ'!$C$2:$C$312, 'マスタ'!$D$2:$D$312, "マスタ未登録")} -> 売上高 | B5: =IF(AND(C5<>"", COUNTIF('マスタ'!$C:$C, C5)=0), "マスタ未登録", "") | C5: =D5&D110&E5&F5&G5&H5 -> 委託販売売上高 | E5: 委託販売売上高 | J5: 240406 | K5: 0 | L5: 0 | M5: 0 | N5: 0 | O5: 0 | P5: 0 | Q5: 0 | R5: 0 | S5: 0 | T5: 0 | U5: 0 | V5: 240406
A6: {=XLOOKUP(C6, 'マスタ'!$C$2:$C$312, 'マスタ'!$D$2:$D$312, "マスタ未登録")} -> マスタ未登録 | B6: =IF(AND(C6<>"", COUNTIF('マスタ'!$C:$C, C6)=0), "マスタ未登録", "") -> マスタ未登録 | C6: =D6&D111&E6&F6&G6&H6 -> 売上高 計 | D6: 売上高 計 | J6: 2937106 | K6: 0 | L6: 0 | M6: 0 | N6: 0 | O6: 0 | P6: 0 | Q6: 0 | R6: 0 | S6: 0 | T6: 0 | U6: 0 | V6: 2937106
A7: {=XLOOKUP(C7, 'マスタ'!$C$2:$C$312, 'マスタ'!$D$2:$D$312, "マスタ未登録")} -> マスタ未登録 | B7: =IF(AND(C7<>"", COUNTIF('マスタ'!$C:$C, C7)=0), "マスタ未登録", "") -> マスタ未登録 | C7: =D7&D112&E7&F7&G7&H7 -> 売上原価 | E7: 売上原価
A8: {=XLOOKUP(C8, 'マスタ'!$C$2:$C$312, 'マスタ'!$D$2:$D$312, "マスタ未登録")} -> マスタ未登録 | B8: =IF(AND(C8<>"", COUNTIF('マスタ'!$C:$C, C8)=0), "マスタ未登録", "") -> マスタ未登録 | C8: =D8&D113&E8&F8&G8&H8 -> 売上原価 | E8: 売上原価 | J8: 7044937 | K8: 0 | L8: 0 | M8: 0 | N8: 0 | O8: 0 | P8: 0 | Q8: 0 | R8: 0 | S8: 0 | T8: 0 | U8: 0 | V8: 7044937
A9: {=XLOOKUP(C9, 'マスタ'!$C$2:$C$312, 'マスタ'!$D$2:$D$312, "マスタ未登録")} -> 期首商品棚卸高 | B9: =IF(AND(C9<>"", COUNTIF('マスタ'!$C:$C, C9)=0), "マスタ未登録", "") | C9: =D9&D114&E9&F9&G9&H9 -> 期首商品棚卸 | G9: 期首商品棚卸 | J9: 0 | K9: 0 | L9: 0 | M9: 0 | N9: 0 | O9: 0 | P9: 0 | Q9: 0 | R9: 0 | S9: 0 | T9: 0 | U9: 0 | V9: 0
A10: {=XLOOKUP(C10, 'マスタ'!$C$2:$C$312, 'マスタ'!$D$2:$D$312, "マスタ未登録")} -> マスタ未登録 | B10: =IF(AND(C10<>"", COUNTIF('マスタ'!$C:$C, C10)=0), "マスタ未登録", "") -> マスタ未登録 | C10: =D10&D115&E10&F10&G10&H10 -> 当期商品仕入合計額 | G10: 当期商品仕入合計額 | J10: 6774413 | K10: 0 | L10: 0 | M10: 0 | N10: 0 | O10: 0 | P10: 0 | Q10: 0 | R10: 0 | S10: 0 | T10: 0 | U10: 0 | V10: 6774413
A11: {=XLOOKUP(C11, 'マスタ'!$C$2:$C$312, 'マスタ'!$D$2:$D$312, "マスタ未登録")} -> 当期商品仕入高 | B11: =IF(AND(C11<>"", COUNTIF('マスタ'!$C:$C, C11)=0), "マスタ未登録", "") | C11: =D11&D116&E11&F11&G11&H11 -> 仕入高 | H11: 仕入高 | J11: 0 | K11: 0 | L11: 0 | M11: 0 | N11: 0 | O11: 0 | P11: 0 | Q11: 0 | R11: 0 | S11: 0 | T11: 0 | U11: 0 | V11: 0
A12: {=XLOOKUP(C12, 'マスタ'!$C$2:$C$312, 'マスタ'!$D$2:$D$312, "マスタ未登録")} -> 当期商品仕入高 | B12: =IF(AND(C12<>"", COUNTIF('マスタ'!$C:$C, C12)=0), "マスタ未登録", "") | C12: =D12&D117&E12&F12&G12&H12 -> 外注費(原) | H12: 外注費(原) | J12: 2477324 | K12: 0 | L12: 0 | M12: 0 | N12: 0 | O12: 0 | P12: 0 | Q12: 0 | R12: 0 | S12: 0 | T12: 0 | U12: 0 | V12: 2477324
A13: {=XLOOKUP(C13, 'マスタ'!$C$2:$C$312, 'マスタ'!$D$2:$D$312, "マスタ未登録")} -> 当期商品仕入高 | B13: =IF(AND(C13<>"", COUNTIF('マスタ'!$C:$C, C13)=0), "マスタ未登録", "") | C13: =D13&D118&E13&F13&G13&H13 -> 業務委託費(原・タレント) | H13: 業務委託費(原・タレント) | J13: 2353140 | K13: 0 | L13: 0 | M13: 0 | N13: 0 | O13: 0 | P13: 0 | Q13: 0 | R13: 0 | S13: 0 | T13: 0 | U13: 0 | V13: 2353140
A14: {=XLOOKUP(C14, 'マスタ'!$C$2:$C$312, 'マスタ'!$D$2:$D$312, "マスタ未登録")} -> 当期商品仕入高 | B14: =IF(AND(C14<>"", COUNTIF('マスタ'!$C:$C, C14)=0), "マスタ未登録", "") | C14: =D14&D119&E14&F14&G14&H14 -> 業務委託費(原・製) | H14: 業務委託費(原・製) | J14: 1246168 | K14: 0 | L14: 0 | M14: 0 | N14: 0 | O14: 0 | P14: 0 | Q14: 0 | R14: 0 | S14: 0 | T14: 0 | U14: 0 | V14: 1246168
A15: {=XLOOKUP(C15, 'マスタ'!$C$2:$C$312, 'マスタ'!$D$2:$D$312, "マスタ未登録")} -> 当期商品仕入高 | B15: =IF(AND(C15<>"", COUNTIF('マスタ'!$C:$C, C15)=0), "マスタ未登録", "") | C15: =D15&D120&E15&F15&G15&H15 -> 旅費交通費(原) | H15: 旅費交通費(原) | J15: 257617 | K15: 0 | L15: 0 | M15: 0 | N15: 0 | O15: 0 | P15: 0 | Q15: 0 | R15: 0 | S15: 0 | T15: 0 | U15: 0 | V15: 257617
A16: {=XLOOKUP(C16, 'マスタ'!$C$2:$C$312, 'マスタ'!$D$2:$D$312, "マスタ未登録")} -> 当期商品仕入高 | B16: =IF(AND(C16<>"", COUNTIF('マスタ'!$C:$C, C16)=0), "マスタ未登録", "") | C16: =D16&D121&E16&F16&G16&H16 -> 通信費(原) | H16: 通信費(原) | J16: 72106 | K16: 0 | L16: 0 | M16: 0 | N16: 0 | O16: 0 | P16: 0 | Q16: 0 | R16: 0 | S16: 0 | T16: 0 | U16: 0 | V16: 72106
A17: {=XLOOKUP(C17, 'マスタ'!$C$2:$C$312, 'マスタ'!$D$2:$D$312, "マスタ未登録")} -> 当期商品仕入高 | B17: =IF(AND(C17<>"", COUNTIF('マスタ'!$C:$C, C17)=0), "マスタ未登録", "") | C17: =D17&D122&E17&F17&G17&H17 -> 消耗品費(原) | H17: 消耗品費(原) | J17: 254219 | K17: 0 | L17: 0 | M17: 0 | N17: 0 | O17: 0 | P17: 0 | Q17: 0 | R17: 0 | S17: 0 | T17: 0 | U17: 0 | V17: 254219
A18: {=XLOOKUP(C18, 'マスタ'!$C$2:$C$312, 'マスタ'!$D$2:$D$312, "マスタ未登録")} -> 当期商品仕入高 | B18: =IF(AND(C18<>"", COUNTIF('マスタ'!$C:$C, C18)=0), "マスタ未登録", "") | C18: =D18&D123&E18&F18&G18&H18 -> 賃借料(原) | H18: 賃借料(原) | J18: 113839 | K18: 0 | L18: 0 | M18: 0 | N18: 0 | O18: 0 | P18: 0 | Q18: 0 | R18: 0 | S18: 0 | T18: 0 | U18: 0 | V18: 113839
A19: {=XLOOKUP(C19, 'マスタ'!$C$2:$C$312, 'マスタ'!$D$2:$D$312, "マスタ未登録")} -> 他勘定振替高 | B19: =IF(AND(C19<>"", COUNTIF('マスタ'!$C:$C, C19)=0), "マスタ未登録", "") | C19: =D19&D124&E19&F19&G19&H19 -> 他勘定振替高(商) | G19: 他勘定振替高(商) | J19: 0 | K19: 0 | L19: 0 | M19: 0 | N19: 0 | O19: 0 | P19: 0 | Q19: 0 | R19: 0 | S19: 0 | T19: 0 | U19: 0 | V19: 0
A20: {=XLOOKUP(C20, 'マスタ'!$C$2:$C$312, 'マスタ'!$D$2:$D$312, "マスタ未登録")} -> マスタ未登録 | B20: =IF(AND(C20<>"", COUNTIF('マスタ'!$C:$C, C20)=0), "マスタ未登録", "") -> マスタ未登録 | C20: =D20&D125&E20&F20&G20&H20 -> 期末商品棚卸合計額 | G20: 期末商品棚卸合計額 | J20: -270524 | K20: 0 | L20: 0 | M20: 0 | N20: 0 | O20: 0 | P20: 0 | Q20: 0 | R20: 0 | S20: 0 | T20: 0 | U20: 0 | V20: -270524
A21: {=XLOOKUP(C21, 'マスタ'!$C$2:$C$312, 'マスタ'!$D$2:$D$312, "マスタ未登録")} -> 期末商品棚卸高 | B21: =IF(AND(C21<>"", COUNTIF('マスタ'!$C:$C, C21)=0), "マスタ未登録", "") | C21: =D21&D126&E21&F21&G21&H21 -> 期末商品棚卸高 | H21: 期末商品棚卸高 | J21: -270524 | K21: 0 | L21: 0 | M21: 0 | N21: 0 | O21: 0 | P21: 0 | Q21: 0 | R21: 0 | S21: 0 | T21: 0 | U21: 0 | V21: -270524
A22: {=XLOOKUP(C22, 'マスタ'!$C$2:$C$312, 'マスタ'!$D$2:$D$312, "マスタ未登録")} -> マスタ未登録 | B22: =IF(AND(C22<>"", COUNTIF('マスタ'!$C:$C, C22)=0), "マスタ未登録", "") -> マスタ未登録 | C22: =D22&D127&E22&F22&G22&H22 -> 商品売上原価 | F22: 商品売上原価 | J22: 7044937 | K22: 0 | L22: 0 | M22: 0 | N22: 0 | O22: 0 | P22: 0 | Q22: 0 | R22: 0 | S22: 0 | T22: 0 | U22: 0 | V22: 7044937
A23: {=XLOOKUP(C23, 'マスタ'!$C$2:$C$312, 'マスタ'!$D$2:$D$312, "マスタ未登録")} -> マスタ未登録 | B23: =IF(AND(C23<>"", COUNTIF('マスタ'!$C:$C, C23)=0), "マスタ未登録", "") -> マスタ未登録 | C23: =D23&D128&E23&F23&G23&H23 -> 売上総損益金額 | D23: 売上総損益金額 | J23: -4107831 | K23: 0 | L23: 0 | M23: 0 | N23: 0 | O23: 0 | P23: 0 | Q23: 0 | R23: 0 | S23: 0 | T23: 0 | U23: 0 | V23: -4107831
A24: {=XLOOKUP(C24, 'マスタ'!$C$2:$C$312, 'マスタ'!$D$2:$D$312, "マスタ未登録")} -> マスタ未登録 | B24: =IF(AND(C24<>"", COUNTIF('マスタ'!$C:$C, C24)=0), "マスタ未登録", "") -> マスタ未登録 | C24: =D24&D129&E24&F24&G24&H24 -> 販売管理費 | E24: 販売管理費
A25: {=XLOOKUP(C25, 'マスタ'!$C$2:$C$312, 'マスタ'!$D$2:$D$312, "マスタ未登録")} -> 通信費 | B25: =IF(AND(C25<>"", COUNTIF('マスタ'!$C:$C, C25)=0), "マスタ未登録", "") | C25: =D25&D130&E25&F25&G25&H25 -> 通信費 | F25: 通信費 | J25: 2346 | K25: 0 | L25: 0 | M25: 0 | N25: 0 | O25: 0 | P25: 0 | Q25: 0 | R25: 0 | S25: 0 | T25: 0 | U25: 0 | V25: 2346
A26: {=XLOOKUP(C26, 'マスタ'!$C$2:$C$312, 'マスタ'!$D$2:$D$312, "マスタ未登録")} -> 広告宣伝費 | B26: =IF(AND(C26<>"", COUNTIF('マスタ'!$C:$C, C26)=0), "マスタ未登録", "") | C26: =D26&D131&E26&F26&G26&H26 -> 広告宣伝費 | F26: 広告宣伝費 | J26: 17469 | K26: 0 | L26: 0 | M26: 0 | N26: 0 | O26: 0 | P26: 0 | Q26: 0 | R26: 0 | S26: 0 | T26: 0 | U26: 0 | V26: 17469
A27: {=XLOOKUP(C27, 'マスタ'!$C$2:$C$312, 'マスタ'!$D$2:$D$312, "マスタ未登録")} -> 荷造運賃 | B27: =IF(AND(C27<>"", COUNTIF('マスタ'!$C:$C, C27)=0), "マスタ未登録", "") | C27: =D27&D132&E27&F27&G27&H27 -> 荷造運賃 | F27: 荷造運賃 | J27: 286140 | K27: 0 | L27: 0 | M27: 0 | N27: 0 | O27: 0 | P27: 0 | Q27: 0 | R27: 0 | S27: 0 | T27: 0 | U27: 0 | V27: 286140
A28: {=XLOOKUP(C28, 'マスタ'!$C$2:$C$312, 'マスタ'!$D$2:$D$312, "マスタ未登録")} -> 支払手数料 | B28: =IF(AND(C28<>"", COUNTIF('マスタ'!$C:$C, C28)=0), "マスタ未登録", "") | C28: =D28&D133&E28&F28&G28&H28 -> 支払手数料 | F28: 支払手数料 | J28: 145924 | K28: 5000 | L28: 0 | M28: 0 | N28: 0 | O28: 0 | P28: 0 | Q28: 0 | R28: 0 | S28: 0 | T28: 0 | U28: 0 | V28: 150924
A29: {=XLOOKUP(C29, 'マスタ'!$C$2:$C$312, 'マスタ'!$D$2:$D$312, "マスタ未登録")} -> 接待交際費 | B29: =IF(AND(C29<>"", COUNTIF('マスタ'!$C:$C, C29)=0), "マスタ未登録", "") | C29: =D29&D134&E29&F29&G29&H29 -> 交際費（11,000円超/人） | F29: 交際費（11,000円超/人） | J29: 27819 | K29: 0 | L29: 0 | M29: 0 | N29: 0 | O29: 0 | P29: 0 | Q29: 0 | R29: 0 | S29: 0 | T29: 0 | U29: 0 | V29: 27819
A30: {=XLOOKUP(C30, 'マスタ'!$C$2:$C$312, 'マスタ'!$D$2:$D$312, "マスタ未登録")} -> マスタ未登録 | B30: =IF(AND(C30<>"", COUNTIF('マスタ'!$C:$C, C30)=0), "マスタ未登録", "") -> マスタ未登録 | C30: =D30&D135&E30&F30&G30&H30 -> 販売管理費 計 | E30: 販売管理費 計 | J30: 479698 | K30: 5000 | L30: 0 | M30: 0 | N30: 0 | O30: 0 | P30: 0 | Q30: 0 | R30: 0 | S30: 0 | T30: 0 | U30: 0 | V30: 484698
A31: {=XLOOKUP(C31, 'マスタ'!$C$2:$C$312, 'マスタ'!$D$2:$D$312, "マスタ未登録")} -> マスタ未登録 | B31: =IF(AND(C31<>"", COUNTIF('マスタ'!$C:$C, C31)=0), "マスタ未登録", "") -> マスタ未登録 | C31: =D31&D136&E31&F31&G31&H31 -> 営業損益金額 | D31: 営業損益金額 | J31: -4587529 | K31: -5000 | L31: 0 | M31: 0 | N31: 0 | O31: 0 | P31: 0 | Q31: 0 | R31: 0 | S31: 0 | T31: 0 | U31: 0 | V31: -4592529
A32: {=XLOOKUP(C32, 'マスタ'!$C$2:$C$312, 'マスタ'!$D$2:$D$312, "マスタ未登録")} -> マスタ未登録 | B32: =IF(AND(C32<>"", COUNTIF('マスタ'!$C:$C, C32)=0), "マスタ未登録", "") -> マスタ未登録 | C32: =D32&D137&E32&F32&G32&H32 -> 営業外収益 | E32: 営業外収益 | J32: 610 | K32: 0 | L32: 0 | M32: 0 | N32: 0 | O32: 0 | P32: 0 | Q32: 0 | R32: 0 | S32: 0 | T32: 0 | U32: 0 | V32: 610
A33: {=XLOOKUP(C33, 'マスタ'!$C$2:$C$312, 'マスタ'!$D$2:$D$312, "マスタ未登録")} -> 受取利息 | B33: =IF(AND(C33<>"", COUNTIF('マスタ'!$C:$C, C33)=0), "マスタ未登録", "") | C33: =D33&D138&E33&F33&G33&H33 -> 受取利息 | F33: 受取利息 | J33: 610 | K33: 0 | L33: 0 | M33: 0 | N33: 0 | O33: 0 | P33: 0 | Q33: 0 | R33: 0 | S33: 0 | T33: 0 | U33: 0 | V33: 610
A34: {=XLOOKUP(C34, 'マスタ'!$C$2:$C$312, 'マスタ'!$D$2:$D$312, "マスタ未登録")} -> マスタ未登録 | B34: =IF(AND(C34<>"", COUNTIF('マスタ'!$C:$C, C34)=0), "マスタ未登録", "") -> マスタ未登録 | C34: =D34&D139&E34&F34&G34&H34 -> 営業外費用 | E34: 営業外費用 | J34: 0 | K34: 0 | L34: 0 | M34: 0 | N34: 0 | O34: 0 | P34: 0 | Q34: 0 | R34: 0 | S34: 0 | T34: 0 | U34: 0 | V34: 0
A35: {=XLOOKUP(C35, 'マスタ'!$C$2:$C$312, 'マスタ'!$D$2:$D$312, "マスタ未登録")} -> マスタ未登録 | B35: =IF(AND(C35<>"", COUNTIF('マスタ'!$C:$C, C35)=0), "マスタ未登録", "") -> マスタ未登録 | C35: =D35&D140&E35&F35&G35&H35 -> 経常損益金額 | D35: 経常損益金額 | J35: -4586919 | K35: -5000 | L35: 0 | M35: 0 | N35: 0 | O35: 0 | P35: 0 | Q35: 0 | R35: 0 | S35: 0 | T35: 0 | U35: 0 | V35: -4591919
A36: {=XLOOKUP(C36, 'マスタ'!$C$2:$C$312, 'マスタ'!$D$2:$D$312, "マスタ未登録")} -> マスタ未登録 | B36: =IF(AND(C36<>"", COUNTIF('マスタ'!$C:$C, C36)=0), "マスタ未登録", "") -> マスタ未登録 | C36: =D36&D141&E36&F36&G36&H36 -> 特別利益 | E36: 特別利益 | J36: 0 | K36: 0 | L36: 0 | M36: 0 | N36: 0 | O36: 0 | P36: 0 | Q36: 0 | R36: 0 | S36: 0 | T36: 0 | U36: 0 | V36: 0
A37: {=XLOOKUP(C37, 'マスタ'!$C$2:$C$312, 'マスタ'!$D$2:$D$312, "マスタ未登録")} -> マスタ未登録 | B37: =IF(AND(C37<>"", COUNTIF('マスタ'!$C:$C, C37)=0), "マスタ未登録", "") -> マスタ未登録 | C37: =D37&D142&E37&F37&G37&H37 -> 特別損失 | E37: 特別損失 | J37: 0 | K37: 0 | L37: 0 | M37: 0 | N37: 0 | O37: 0 | P37: 0 | Q37: 0 | R37: 0 | S37: 0 | T37: 0 | U37: 0 | V37: 0
A38: {=XLOOKUP(C38, 'マスタ'!$C$2:$C$312, 'マスタ'!$D$2:$D$312, "マスタ未登録")} -> マスタ未登録 | B38: =IF(AND(C38<>"", COUNTIF('マスタ'!$C:$C, C38)=0), "マスタ未登録", "") -> マスタ未登録 | C38: =D38&D143&E38&F38&G38&H38 -> 税引前当期純損益金額 | D38: 税引前当期純損益金額 | J38: -4586919 | K38: -5000 | L38: 0 | M38: 0 | N38: 0 | O38: 0 | P38: 0 | Q38: 0 | R38: 0 | S38: 0 | T38: 0 | U38: 0 | V38: -4591919
A39: {=XLOOKUP(C39, 'マスタ'!$C$2:$C$312, 'マスタ'!$D$2:$D$312, "マスタ未登録")} -> 法人税等 | B39: =IF(AND(C39<>"", COUNTIF('マスタ'!$C:$C, C39)=0), "マスタ未登録", "") | C39: =D39&D144&E39&F39&G39&H39 -> 法人税等 | E39: 法人税等 | J39: 0 | K39: 0 | L39: 0 | M39: 0 | N39: 0 | O39: 0 | P39: 0 | Q39: 0 | R39: 0 | S39: 0 | T39: 0 | U39: 0 | V39: 0
A40: {=XLOOKUP(C40, 'マスタ'!$C$2:$C$312, 'マスタ'!$D$2:$D$312, "マスタ未登録")} -> 法人税等調整額 | B40: =IF(AND(C40<>"", COUNTIF('マスタ'!$C:$C, C40)=0), "マスタ未登録", "") | C40: =D40&D145&E40&F40&G40&H40 -> 法人税等調整額 | E40: 法人税等調整額 | J40: 0 | K40: 0 | L40: 0 | M40: 0 | N40: 0 | O40: 0 | P40: 0 | Q40: 0 | R40: 0 | S40: 0 | T40: 0 | U40: 0 | V40: 0
A41: {=XLOOKUP(C41, 'マスタ'!$C$2:$C$312, 'マスタ'!$D$2:$D$312, "マスタ未登録")} -> マスタ未登録 | B41: =IF(AND(C41<>"", COUNTIF('マスタ'!$C:$C, C41)=0), "マスタ未登録", "") -> マスタ未登録 | C41: =D41&D146&E41&F41&G41&H41 -> 当期純損益金額 | D41: 当期純損益金額 | J41: -4586919 | K41: -5000 | L41: 0 | M41: 0 | N41: 0 | O41: 0 | P41: 0 | Q41: 0 | R41: 0 | S41: 0 | T41: 0 | U41: 0 | V41: -4591919
B42: =IF(AND(C42<>"", COUNTIF('マスタ'!$C:$C, C42)=0), "マスタ未登録", "") | C42: =D42&D147&E42&F42&G42&H42
B43: =IF(AND(C43<>"", COUNTIF('マスタ'!$C:$C, C43)=0), "マスタ未登録", "") | C43: =D43&D148&E43&F43&G43&H43
B44: =IF(AND(C44<>"", COUNTIF('マスタ'!$C:$C, C44)=0), "マスタ未登録", "") | C44: =D44&D149&E44&F44&G44&H44
B45: =IF(AND(C45<>"", COUNTIF('マスタ'!$C:$C, C45)=0), "マスタ未登録", "") | C45: =D45&D150&E45&F45&G45&H45
B46: =IF(AND(C46<>"", COUNTIF('マスタ'!$C:$C, C46)=0), "マスタ未登録", "") | C46: =D46&D151&E46&F46&G46&H46
B47: =IF(AND(C47<>"", COUNTIF('マスタ'!$C:$C, C47)=0), "マスタ未登録", "") | C47: =D47&D152&E47&F47&G47&H47
B48: =IF(AND(C48<>"", COUNTIF('マスタ'!$C:$C, C48)=0), "マスタ未登録", "") | C48: =D48&D153&E48&F48&G48&H48
B49: =IF(AND(C49<>"", COUNTIF('マスタ'!$C:$C, C49)=0), "マスタ未登録", "") | C49: =D49&D154&E49&F49&G49&H49
B50: =IF(AND(C50<>"", COUNTIF('マスタ'!$C:$C, C50)=0), "マスタ未登録", "") | C50: =D50&D155&E50&F50&G50&H50
B51: =IF(AND(C51<>"", COUNTIF('マスタ'!$C:$C, C51)=0), "マスタ未登録", "") | C51: =D51&D156&E51&F51&G51&H51
B52: =IF(AND(C52<>"", COUNTIF('マスタ'!$C:$C, C52)=0), "マスタ未登録", "") | C52: =D52&D157&E52&F52&G52&H52
B53: =IF(AND(C53<>"", COUNTIF('マスタ'!$C:$C, C53)=0), "マスタ未登録", "") | C53: =D53&D158&E53&F53&G53&H53
... B56: =IF(AND(C56<>"", COUNTIF('マスタ'!$C:$C, C56)=0), "マスタ未登録", "") | C56: =D56&D161&E56&F56&G56&H56

Sheet VO_PL(CANON)
B1: ②マスタ結びつけ | C1: ① | D1: 月次推移：損益計算書_株式会社VOISING（期間：2026年04月〜2027年03月、表示単位：円）
J2: 46113 | K2: 46143 | L2: 46174 | M2: 46204 | N2: 46235 | O2: 46266 | P2: 46296 | Q2: 46327 | R2: 46357 | S2: 46388 | T2: 46419 | U2: 46447 | V2: 期間累計
D3: 売上高
A4: {=XLOOKUP(C4, 'マスタ'!$C$2:$C$312, 'マスタ'!$D$2:$D$312, "マスタ未登録")} -> マスタ未登録 | B4: =IF(AND(C4<>"", COUNTIF('マスタ'!$C:$C, C4)=0), "マスタ未登録", "") -> マスタ未登録 | C4: =D4&D109&E4&F4&G4&H4 -> 売上高 計 | D4: 売上高 計 | J4: 0 | K4: 0 | L4: 0 | M4: 0 | N4: 0 | O4: 0 | P4: 0 | Q4: 0 | R4: 0 | S4: 0 | T4: 0 | U4: 0 | V4: 0
A5: {=XLOOKUP(C5, 'マスタ'!$C$2:$C$312, 'マスタ'!$D$2:$D$312, "マスタ未登録")} -> マスタ未登録 | B5: =IF(AND(C5<>"", COUNTIF('マスタ'!$C:$C, C5)=0), "マスタ未登録", "") -> マスタ未登録 | C5: =D5&D110&E5&F5&G5&H5 -> 売上原価 | E5: 売上原価
A6: {=XLOOKUP(C6, 'マスタ'!$C$2:$C$312, 'マスタ'!$D$2:$D$312, "マスタ未登録")} -> マスタ未登録 | B6: =IF(AND(C6<>"", COUNTIF('マスタ'!$C:$C, C6)=0), "マスタ未登録", "") -> マスタ未登録 | C6: =D6&D111&E6&F6&G6&H6 -> 売上原価 | E6: 売上原価 | J6: 2272468 | K6: 0 | L6: 0 | M6: 0 | N6: 0 | O6: 0 | P6: 0 | Q6: 0 | R6: 0 | S6: 0 | T6: 0 | U6: 0 | V6: 2272468
A7: {=XLOOKUP(C7, 'マスタ'!$C$2:$C$312, 'マスタ'!$D$2:$D$312, "マスタ未登録")} -> 期首商品棚卸高 | B7: =IF(AND(C7<>"", COUNTIF('マスタ'!$C:$C, C7)=0), "マスタ未登録", "") | C7: =D7&D112&E7&F7&G7&H7 -> 期首商品棚卸 | G7: 期首商品棚卸 | J7: 0 | K7: 0 | L7: 0 | M7: 0 | N7: 0 | O7: 0 | P7: 0 | Q7: 0 | R7: 0 | S7: 0 | T7: 0 | U7: 0 | V7: 0
A8: {=XLOOKUP(C8, 'マスタ'!$C$2:$C$312, 'マスタ'!$D$2:$D$312, "マスタ未登録")} -> マスタ未登録 | B8: =IF(AND(C8<>"", COUNTIF('マスタ'!$C:$C, C8)=0), "マスタ未登録", "") -> マスタ未登録 | C8: =D8&D113&E8&F8&G8&H8 -> 当期商品仕入合計額 | G8: 当期商品仕入合計額 | J8: 2272468 | K8: 0 | L8: 0 | M8: 0 | N8: 0 | O8: 0 | P8: 0 | Q8: 0 | R8: 0 | S8: 0 | T8: 0 | U8: 0 | V8: 2272468
A9: {=XLOOKUP(C9, 'マスタ'!$C$2:$C$312, 'マスタ'!$D$2:$D$312, "マスタ未登録")} -> 当期商品仕入高 | B9: =IF(AND(C9<>"", COUNTIF('マスタ'!$C:$C, C9)=0), "マスタ未登録", "") | C9: =D9&D114&E9&F9&G9&H9 -> 外注費(原) | H9: 外注費(原) | J9: 2040228 | K9: 0 | L9: 0 | M9: 0 | N9: 0 | O9: 0 | P9: 0 | Q9: 0 | R9: 0 | S9: 0 | T9: 0 | U9: 0 | V9: 2040228
A10: {=XLOOKUP(C10, 'マスタ'!$C$2:$C$312, 'マスタ'!$D$2:$D$312, "マスタ未登録")} -> 当期商品仕入高 | B10: =IF(AND(C10<>"", COUNTIF('マスタ'!$C:$C, C10)=0), "マスタ未登録", "") | C10: =D10&D115&E10&F10&G10&H10 -> 業務委託費(原・製) | H10: 業務委託費(原・製) | J10: 232240 | K10: 0 | L10: 0 | M10: 0 | N10: 0 | O10: 0 | P10: 0 | Q10: 0 | R10: 0 | S10: 0 | T10: 0 | U10: 0 | V10: 232240
A11: {=XLOOKUP(C11, 'マスタ'!$C$2:$C$312, 'マスタ'!$D$2:$D$312, "マスタ未登録")} -> 他勘定振替高 | B11: =IF(AND(C11<>"", COUNTIF('マスタ'!$C:$C, C11)=0), "マスタ未登録", "") | C11: =D11&D116&E11&F11&G11&H11 -> 他勘定振替高(商) | G11: 他勘定振替高(商) | J11: 0 | K11: 0 | L11: 0 | M11: 0 | N11: 0 | O11: 0 | P11: 0 | Q11: 0 | R11: 0 | S11: 0 | T11: 0 | U11: 0 | V11: 0
A12: {=XLOOKUP(C12, 'マスタ'!$C$2:$C$312, 'マスタ'!$D$2:$D$312, "マスタ未登録")} -> 期末商品棚卸高 | B12: =IF(AND(C12<>"", COUNTIF('マスタ'!$C:$C, C12)=0), "マスタ未登録", "") | C12: =D12&D117&E12&F12&G12&H12 -> 期末商品棚卸 | G12: 期末商品棚卸 | J12: 0 | K12: 0 | L12: 0 | M12: 0 | N12: 0 | O12: 0 | P12: 0 | Q12: 0 | R12: 0 | S12: 0 | T12: 0 | U12: 0 | V12: 0
A13: {=XLOOKUP(C13, 'マスタ'!$C$2:$C$312, 'マスタ'!$D$2:$D$312, "マスタ未登録")} -> マスタ未登録 | B13: =IF(AND(C13<>"", COUNTIF('マスタ'!$C:$C, C13)=0), "マスタ未登録", "") -> マスタ未登録 | C13: =D13&D118&E13&F13&G13&H13 -> 商品売上原価 | F13: 商品売上原価 | J13: 2272468 | K13: 0 | L13: 0 | M13: 0 | N13: 0 | O13: 0 | P13: 0 | Q13: 0 | R13: 0 | S13: 0 | T13: 0 | U13: 0 | V13: 2272468
A14: {=XLOOKUP(C14, 'マスタ'!$C$2:$C$312, 'マスタ'!$D$2:$D$312, "マスタ未登録")} -> マスタ未登録 | B14: =IF(AND(C14<>"", COUNTIF('マスタ'!$C:$C, C14)=0), "マスタ未登録", "") -> マスタ未登録 | C14: =D14&D119&E14&F14&G14&H14 -> 売上総損益金額 | D14: 売上総損益金額 | J14: -2272468 | K14: 0 | L14: 0 | M14: 0 | N14: 0 | O14: 0 | P14: 0 | Q14: 0 | R14: 0 | S14: 0 | T14: 0 | U14: 0 | V14: -2272468
A15: {=XLOOKUP(C15, 'マスタ'!$C$2:$C$312, 'マスタ'!$D$2:$D$312, "マスタ未登録")} -> マスタ未登録 | B15: =IF(AND(C15<>"", COUNTIF('マスタ'!$C:$C, C15)=0), "マスタ未登録", "") -> マスタ未登録 | C15: =D15&D120&E15&F15&G15&H15 -> 販売管理費 | E15: 販売管理費
A16: {=XLOOKUP(C16, 'マスタ'!$C$2:$C$312, 'マスタ'!$D$2:$D$312, "マスタ未登録")} -> マスタ未登録 | B16: =IF(AND(C16<>"", COUNTIF('マスタ'!$C:$C, C16)=0), "マスタ未登録", "") -> マスタ未登録 | C16: =D16&D121&E16&F16&G16&H16 -> 販売管理費 計 | E16: 販売管理費 計 | J16: 0 | K16: 0 | L16: 0 | M16: 0 | N16: 0 | O16: 0 | P16: 0 | Q16: 0 | R16: 0 | S16: 0 | T16: 0 | U16: 0 | V16: 0
A17: {=XLOOKUP(C17, 'マスタ'!$C$2:$C$312, 'マスタ'!$D$2:$D$312, "マスタ未登録")} -> マスタ未登録 | B17: =IF(AND(C17<>"", COUNTIF('マスタ'!$C:$C, C17)=0), "マスタ未登録", "") -> マスタ未登録 | C17: =D17&D122&E17&F17&G17&H17 -> 営業損益金額 | D17: 営業損益金額 | J17: -2272468 | K17: 0 | L17: 0 | M17: 0 | N17: 0 | O17: 0 | P17: 0 | Q17: 0 | R17: 0 | S17: 0 | T17: 0 | U17: 0 | V17: -2272468
A18: {=XLOOKUP(C18, 'マスタ'!$C$2:$C$312, 'マスタ'!$D$2:$D$312, "マスタ未登録")} -> マスタ未登録 | B18: =IF(AND(C18<>"", COUNTIF('マスタ'!$C:$C, C18)=0), "マスタ未登録", "") -> マスタ未登録 | C18: =D18&D123&E18&F18&G18&H18 -> 営業外収益 | E18: 営業外収益 | J18: 0 | K18: 0 | L18: 0 | M18: 0 | N18: 0 | O18: 0 | P18: 0 | Q18: 0 | R18: 0 | S18: 0 | T18: 0 | U18: 0 | V18: 0
A19: {=XLOOKUP(C19, 'マスタ'!$C$2:$C$312, 'マスタ'!$D$2:$D$312, "マスタ未登録")} -> マスタ未登録 | B19: =IF(AND(C19<>"", COUNTIF('マスタ'!$C:$C, C19)=0), "マスタ未登録", "") -> マスタ未登録 | C19: =D19&D124&E19&F19&G19&H19 -> 営業外費用 | E19: 営業外費用 | J19: 0 | K19: 0 | L19: 0 | M19: 0 | N19: 0 | O19: 0 | P19: 0 | Q19: 0 | R19: 0 | S19: 0 | T19: 0 | U19: 0 | V19: 0
A20: {=XLOOKUP(C20, 'マスタ'!$C$2:$C$312, 'マスタ'!$D$2:$D$312, "マスタ未登録")} -> マスタ未登録 | B20: =IF(AND(C20<>"", COUNTIF('マスタ'!$C:$C, C20)=0), "マスタ未登録", "") -> マスタ未登録 | C20: =D20&D125&E20&F20&G20&H20 -> 経常損益金額 | D20: 経常損益金額 | J20: -2272468 | K20: 0 | L20: 0 | M20: 0 | N20: 0 | O20: 0 | P20: 0 | Q20: 0 | R20: 0 | S20: 0 | T20: 0 | U20: 0 | V20: -2272468
A21: {=XLOOKUP(C21, 'マスタ'!$C$2:$C$312, 'マスタ'!$D$2:$D$312, "マスタ未登録")} -> マスタ未登録 | B21: =IF(AND(C21<>"", COUNTIF('マスタ'!$C:$C, C21)=0), "マスタ未登録", "") -> マスタ未登録 | C21: =D21&D126&E21&F21&G21&H21 -> 特別利益 | E21: 特別利益 | J21: 0 | K21: 0 | L21: 0 | M21: 0 | N21: 0 | O21: 0 | P21: 0 | Q21: 0 | R21: 0 | S21: 0 | T21: 0 | U21: 0 | V21: 0
A22: {=XLOOKUP(C22, 'マスタ'!$C$2:$C$312, 'マスタ'!$D$2:$D$312, "マスタ未登録")} -> マスタ未登録 | B22: =IF(AND(C22<>"", COUNTIF('マスタ'!$C:$C, C22)=0), "マスタ未登録", "") -> マスタ未登録 | C22: =D22&D127&E22&F22&G22&H22 -> 特別損失 | E22: 特別損失 | J22: 0 | K22: 0 | L22: 0 | M22: 0 | N22: 0 | O22: 0 | P22: 0 | Q22: 0 | R22: 0 | S22: 0 | T22: 0 | U22: 0 | V22: 0
A23: {=XLOOKUP(C23, 'マスタ'!$C$2:$C$312, 'マスタ'!$D$2:$D$312, "マスタ未登録")} -> マスタ未登録 | B23: =IF(AND(C23<>"", COUNTIF('マスタ'!$C:$C, C23)=0), "マスタ未登録", "") -> マスタ未登録 | C23: =D23&D128&E23&F23&G23&H23 -> 税引前当期純損益金額 | D23: 税引前当期純損益金額 | J23: -2272468 | K23: 0 | L23: 0 | M23: 0 | N23: 0 | O23: 0 | P23: 0 | Q23: 0 | R23: 0 | S23: 0 | T23: 0 | U23: 0 | V23: -2272468
A24: {=XLOOKUP(C24, 'マスタ'!$C$2:$C$312, 'マスタ'!$D$2:$D$312, "マスタ未登録")} -> 法人税等 | B24: =IF(AND(C24<>"", COUNTIF('マスタ'!$C:$C, C24)=0), "マスタ未登録", "") | C24: =D24&D129&E24&F24&G24&H24 -> 法人税等 | E24: 法人税等 | J24: 0 | K24: 0 | L24: 0 | M24: 0 | N24: 0 | O24: 0 | P24: 0 | Q24: 0 | R24: 0 | S24: 0 | T24: 0 | U24: 0 | V24: 0
A25: {=XLOOKUP(C25, 'マスタ'!$C$2:$C$312, 'マスタ'!$D$2:$D$312, "マスタ未登録")} -> 法人税等調整額 | B25: =IF(AND(C25<>"", COUNTIF('マスタ'!$C:$C, C25)=0), "マスタ未登録", "") | C25: =D25&D130&E25&F25&G25&H25 -> 法人税等調整額 | E25: 法人税等調整額 | J25: 0 | K25: 0 | L25: 0 | M25: 0 | N25: 0 | O25: 0 | P25: 0 | Q25: 0 | R25: 0 | S25: 0 | T25: 0 | U25: 0 | V25: 0
A26: {=XLOOKUP(C26, 'マスタ'!$C$2:$C$312, 'マスタ'!$D$2:$D$312, "マスタ未登録")} -> マスタ未登録 | B26: =IF(AND(C26<>"", COUNTIF('マスタ'!$C:$C, C26)=0), "マスタ未登録", "") -> マスタ未登録 | C26: =D26&D131&E26&F26&G26&H26 -> 当期純損益金額 | D26: 当期純損益金額 | J26: -2272468 | K26: 0 | L26: 0 | M26: 0 | N26: 0 | O26: 0 | P26: 0 | Q26: 0 | R26: 0 | S26: 0 | T26: 0 | U26: 0 | V26: -2272468
B27: =IF(AND(C27<>"", COUNTIF('マスタ'!$C:$C, C27)=0), "マスタ未登録", "") | C27: =D27&D132&E27&F27&G27&H27
B28: =IF(AND(C28<>"", COUNTIF('マスタ'!$C:$C, C28)=0), "マスタ未登録", "") | C28: =D28&D133&E28&F28&G28&H28
B29: =IF(AND(C29<>"", COUNTIF('マスタ'!$C:$C, C29)=0), "マスタ未登録", "") | C29: =D29&D134&E29&F29&G29&H29
B30: =IF(AND(C30<>"", COUNTIF('マスタ'!$C:$C, C30)=0), "マスタ未登録", "") | C30: =D30&D135&E30&F30&G30&H30
B31: =IF(AND(C31<>"", COUNTIF('マスタ'!$C:$C, C31)=0), "マスタ未登録", "") | C31: =D31&D136&E31&F31&G31&H31
B32: =IF(AND(C32<>"", COUNTIF('マスタ'!$C:$C, C32)=0), "マスタ未登録", "") | C32: =D32&D137&E32&F32&G32&H32
B33: =IF(AND(C33<>"", COUNTIF('マスタ'!$C:$C, C33)=0), "マスタ未登録", "") | C33: =D33&D138&E33&F33&G33&H33
B34: =IF(AND(C34<>"", COUNTIF('マスタ'!$C:$C, C34)=0), "マスタ未登録", "") | C34: =D34&D139&E34&F34&G34&H34
B35: =IF(AND(C35<>"", COUNTIF('マスタ'!$C:$C, C35)=0), "マスタ未登録", "") | C35: =D35&D140&E35&F35&G35&H35
B36: =IF(AND(C36<>"", COUNTIF('マスタ'!$C:$C, C36)=0), "マスタ未登録", "") | C36: =D36&D141&E36&F36&G36&H36
B37: =IF(AND(C37<>"", COUNTIF('マスタ'!$C:$C, C37)=0), "マスタ未登録", "") | C37: =D37&D142&E37&F37&G37&H37
B38: =IF(AND(C38<>"", COUNTIF('マスタ'!$C:$C, C38)=0), "マスタ未登録", "") | C38: =D38&D143&E38&F38&G38&H38
... B56: =IF(AND(C56<>"", COUNTIF('マスタ'!$C:$C, C56)=0), "マスタ未登録", "") | C56: =D56&D161&E56&F56&G56&H56

Sheet VO_PL(共通)
B1: ②マスタ結びつけ | C1: ① | D1: 月次推移：損益計算書_株式会社VOISING（期間：2026年04月〜2027年03月、表示単位：円）
J2: 46113 | K2: 46143 | L2: 46174 | M2: 46204 | N2: 46235 | O2: 46266 | P2: 46296 | Q2: 46327 | R2: 46357 | S2: 46388 | T2: 46419 | U2: 46447 | V2: 期間累計
D3: 売上高
A4: {=XLOOKUP(C4, 'マスタ'!$C$2:$C$312, 'マスタ'!$D$2:$D$312, "マスタ未登録")} -> 売上高 | B4: =IF(AND(C4<>"", COUNTIF('マスタ'!$C:$C, C4)=0), "マスタ未登録", "") | C4: =D4&D109&E4&F4&G4&H4 -> 売上高 | E4: 売上高 | J4: 51653 | K4: 0 | L4: 0 | M4: 0 | N4: 0 | O4: 0 | P4: 0 | Q4: 0 | R4: 0 | S4: 0 | T4: 0 | U4: 0 | V4: 51653
A5: {=XLOOKUP(C5, 'マスタ'!$C$2:$C$312, 'マスタ'!$D$2:$D$312, "マスタ未登録")} -> 売上高 | B5: =IF(AND(C5<>"", COUNTIF('マスタ'!$C:$C, C5)=0), "マスタ未登録", "") | C5: =D5&D110&E5&F5&G5&H5 -> 委託販売売上高 | E5: 委託販売売上高 | J5: 143843 | K5: 0 | L5: 0 | M5: 0 | N5: 0 | O5: 0 | P5: 0 | Q5: 0 | R5: 0 | S5: 0 | T5: 0 | U5: 0 | V5: 143843
A6: {=XLOOKUP(C6, 'マスタ'!$C$2:$C$312, 'マスタ'!$D$2:$D$312, "マスタ未登録")} -> マスタ未登録 | B6: =IF(AND(C6<>"", COUNTIF('マスタ'!$C:$C, C6)=0), "マスタ未登録", "") -> マスタ未登録 | C6: =D6&D111&E6&F6&G6&H6 -> 売上高 計 | D6: 売上高 計 | J6: 195496 | K6: 0 | L6: 0 | M6: 0 | N6: 0 | O6: 0 | P6: 0 | Q6: 0 | R6: 0 | S6: 0 | T6: 0 | U6: 0 | V6: 195496
A7: {=XLOOKUP(C7, 'マスタ'!$C$2:$C$312, 'マスタ'!$D$2:$D$312, "マスタ未登録")} -> マスタ未登録 | B7: =IF(AND(C7<>"", COUNTIF('マスタ'!$C:$C, C7)=0), "マスタ未登録", "") -> マスタ未登録 | C7: =D7&D112&E7&F7&G7&H7 -> 売上原価 | E7: 売上原価
A8: {=XLOOKUP(C8, 'マスタ'!$C$2:$C$312, 'マスタ'!$D$2:$D$312, "マスタ未登録")} -> マスタ未登録 | B8: =IF(AND(C8<>"", COUNTIF('マスタ'!$C:$C, C8)=0), "マスタ未登録", "") -> マスタ未登録 | C8: =D8&D113&E8&F8&G8&H8 -> 売上原価 | E8: 売上原価 | J8: 56777489 | K8: 903439 | L8: 0 | M8: 0 | N8: 0 | O8: 0 | P8: 0 | Q8: 0 | R8: 0 | S8: 0 | T8: 0 | U8: 0 | V8: 57680928
A9: {=XLOOKUP(C9, 'マスタ'!$C$2:$C$312, 'マスタ'!$D$2:$D$312, "マスタ未登録")} -> 期首商品棚卸高 | B9: =IF(AND(C9<>"", COUNTIF('マスタ'!$C:$C, C9)=0), "マスタ未登録", "") | C9: =D9&D114&E9&F9&G9&H9 -> 期首商品棚卸 | G9: 期首商品棚卸 | J9: 0 | K9: 0 | L9: 0 | M9: 0 | N9: 0 | O9: 0 | P9: 0 | Q9: 0 | R9: 0 | S9: 0 | T9: 0 | U9: 0 | V9: 0
A10: {=XLOOKUP(C10, 'マスタ'!$C$2:$C$312, 'マスタ'!$D$2:$D$312, "マスタ未登録")} -> マスタ未登録 | B10: =IF(AND(C10<>"", COUNTIF('マスタ'!$C:$C, C10)=0), "マスタ未登録", "") -> マスタ未登録 | C10: =D10&D115&E10&F10&G10&H10 -> 当期商品仕入合計額 | G10: 当期商品仕入合計額 | J10: 56777489 | K10: 903439 | L10: 0 | M10: 0 | N10: 0 | O10: 0 | P10: 0 | Q10: 0 | R10: 0 | S10: 0 | T10: 0 | U10: 0 | V10: 57680928
A11: {=XLOOKUP(C11, 'マスタ'!$C$2:$C$312, 'マスタ'!$D$2:$D$312, "マスタ未登録")} -> 当期商品仕入高 | B11: =IF(AND(C11<>"", COUNTIF('マスタ'!$C:$C, C11)=0), "マスタ未登録", "") | C11: =D11&D116&E11&F11&G11&H11 -> 給料手当(原・ビ) | H11: 給料手当(原・ビ) | J11: 8052485 | K11: 0 | L11: 0 | M11: 0 | N11: 0 | O11: 0 | P11: 0 | Q11: 0 | R11: 0 | S11: 0 | T11: 0 | U11: 0 | V11: 8052485
A12: {=XLOOKUP(C12, 'マスタ'!$C$2:$C$312, 'マスタ'!$D$2:$D$312, "マスタ未登録")} -> 当期商品仕入高 | B12: =IF(AND(C12<>"", COUNTIF('マスタ'!$C:$C, C12)=0), "マスタ未登録", "") | C12: =D12&D117&E12&F12&G12&H12 -> 給料手当(原・製) | H12: 給料手当(原・製) | J12: 27763461 | K12: 0 | L12: 0 | M12: 0 | N12: 0 | O12: 0 | P12: 0 | Q12: 0 | R12: 0 | S12: 0 | T12: 0 | U12: 0 | V12: 27763461
A13: {=XLOOKUP(C13, 'マスタ'!$C$2:$C$312, 'マスタ'!$D$2:$D$312, "マスタ未登録")} -> 当期商品仕入高 | B13: =IF(AND(C13<>"", COUNTIF('マスタ'!$C:$C, C13)=0), "マスタ未登録", "") | C13: =D13&D118&E13&F13&G13&H13 -> 法定福利費(原・ビ) | H13: 法定福利費(原・ビ) | J13: 1179172 | K13: 0 | L13: 0 | M13: 0 | N13: 0 | O13: 0 | P13: 0 | Q13: 0 | R13: 0 | S13: 0 | T13: 0 | U13: 0 | V13: 1179172
A14: {=XLOOKUP(C14, 'マスタ'!$C$2:$C$312, 'マスタ'!$D$2:$D$312, "マスタ未登録")} -> 当期商品仕入高 | B14: =IF(AND(C14<>"", COUNTIF('マスタ'!$C:$C, C14)=0), "マスタ未登録", "") | C14: =D14&D119&E14&F14&G14&H14 -> 法定福利費(原・製) | H14: 法定福利費(原・製) | J14: 4588449 | K14: 0 | L14: 0 | M14: 0 | N14: 0 | O14: 0 | P14: 0 | Q14: 0 | R14: 0 | S14: 0 | T14: 0 | U14: 0 | V14: 4588449
A15: {=XLOOKUP(C15, 'マスタ'!$C$2:$C$312, 'マスタ'!$D$2:$D$312, "マスタ未登録")} -> 当期商品仕入高 | B15: =IF(AND(C15<>"", COUNTIF('マスタ'!$C:$C, C15)=0), "マスタ未登録", "") | C15: =D15&D120&E15&F15&G15&H15 -> 外注費(原) | H15: 外注費(原) | J15: 1331768 | K15: 0 | L15: 0 | M15: 0 | N15: 0 | O15: 0 | P15: 0 | Q15: 0 | R15: 0 | S15: 0 | T15: 0 | U15: 0 | V15: 1331768
A16: {=XLOOKUP(C16, 'マスタ'!$C$2:$C$312, 'マスタ'!$D$2:$D$312, "マスタ未登録")} -> 当期商品仕入高 | B16: =IF(AND(C16<>"", COUNTIF('マスタ'!$C:$C, C16)=0), "マスタ未登録", "") | C16: =D16&D121&E16&F16&G16&H16 -> 業務委託費(原・タレント) | H16: 業務委託費(原・タレント) | J16: 545238 | K16: 0 | L16: 0 | M16: 0 | N16: 0 | O16: 0 | P16: 0 | Q16: 0 | R16: 0 | S16: 0 | T16: 0 | U16: 0 | V16: 545238
A17: {=XLOOKUP(C17, 'マスタ'!$C$2:$C$312, 'マスタ'!$D$2:$D$312, "マスタ未登録")} -> 当期商品仕入高 | B17: =IF(AND(C17<>"", COUNTIF('マスタ'!$C:$C, C17)=0), "マスタ未登録", "") | C17: =D17&D122&E17&F17&G17&H17 -> 業務委託費(原・製) | H17: 業務委託費(原・製) | J17: 9781170 | K17: 0 | L17: 0 | M17: 0 | N17: 0 | O17: 0 | P17: 0 | Q17: 0 | R17: 0 | S17: 0 | T17: 0 | U17: 0 | V17: 9781170
A18: {=XLOOKUP(C18, 'マスタ'!$C$2:$C$312, 'マスタ'!$D$2:$D$312, "マスタ未登録")} -> 当期商品仕入高 | B18: =IF(AND(C18<>"", COUNTIF('マスタ'!$C:$C, C18)=0), "マスタ未登録", "") | C18: =D18&D123&E18&F18&G18&H18 -> 業務委託費(原・ビ) | H18: 業務委託費(原・ビ) | J18: 1138039 | K18: 0 | L18: 0 | M18: 0 | N18: 0 | O18: 0 | P18: 0 | Q18: 0 | R18: 0 | S18: 0 | T18: 0 | U18: 0 | V18: 1138039
A19: {=XLOOKUP(C19, 'マスタ'!$C$2:$C$312, 'マスタ'!$D$2:$D$312, "マスタ未登録")} -> 当期商品仕入高 | B19: =IF(AND(C19<>"", COUNTIF('マスタ'!$C:$C, C19)=0), "マスタ未登録", "") | C19: =D19&D124&E19&F19&G19&H19 -> 旅費交通費(原) | H19: 旅費交通費(原) | J19: 980607 | K19: 0 | L19: 0 | M19: 0 | N19: 0 | O19: 0 | P19: 0 | Q19: 0 | R19: 0 | S19: 0 | T19: 0 | U19: 0 | V19: 980607
A20: {=XLOOKUP(C20, 'マスタ'!$C$2:$C$312, 'マスタ'!$D$2:$D$312, "マスタ未登録")} -> 当期商品仕入高 | B20: =IF(AND(C20<>"", COUNTIF('マスタ'!$C:$C, C20)=0), "マスタ未登録", "") | C20: =D20&D125&E20&F20&G20&H20 -> 通信費(原) | H20: 通信費(原) | J20: 1415281 | K20: 903439 | L20: 0 | M20: 0 | N20: 0 | O20: 0 | P20: 0 | Q20: 0 | R20: 0 | S20: 0 | T20: 0 | U20: 0 | V20: 2318720
A21: {=XLOOKUP(C21, 'マスタ'!$C$2:$C$312, 'マスタ'!$D$2:$D$312, "マスタ未登録")} -> 当期商品仕入高 | B21: =IF(AND(C21<>"", COUNTIF('マスタ'!$C:$C, C21)=0), "マスタ未登録", "") | C21: =D21&D126&E21&F21&G21&H21 -> 消耗品費(原) | H21: 消耗品費(原) | J21: 1819 | K21: 0 | L21: 0 | M21: 0 | N21: 0 | O21: 0 | P21: 0 | Q21: 0 | R21: 0 | S21: 0 | T21: 0 | U21: 0 | V21: 1819
A22: {=XLOOKUP(C22, 'マスタ'!$C$2:$C$312, 'マスタ'!$D$2:$D$312, "マスタ未登録")} -> 他勘定振替高 | B22: =IF(AND(C22<>"", COUNTIF('マスタ'!$C:$C, C22)=0), "マスタ未登録", "") | C22: =D22&D127&E22&F22&G22&H22 -> 他勘定振替高(商) | G22: 他勘定振替高(商) | J22: 0 | K22: 0 | L22: 0 | M22: 0 | N22: 0 | O22: 0 | P22: 0 | Q22: 0 | R22: 0 | S22: 0 | T22: 0 | U22: 0 | V22: 0
A23: {=XLOOKUP(C23, 'マスタ'!$C$2:$C$312, 'マスタ'!$D$2:$D$312, "マスタ未登録")} -> 期末商品棚卸高 | B23: =IF(AND(C23<>"", COUNTIF('マスタ'!$C:$C, C23)=0), "マスタ未登録", "") | C23: =D23&D128&E23&F23&G23&H23 -> 期末商品棚卸 | G23: 期末商品棚卸 | J23: 0 | K23: 0 | L23: 0 | M23: 0 | N23: 0 | O23: 0 | P23: 0 | Q23: 0 | R23: 0 | S23: 0 | T23: 0 | U23: 0 | V23: 0
A24: {=XLOOKUP(C24, 'マスタ'!$C$2:$C$312, 'マスタ'!$D$2:$D$312, "マスタ未登録")} -> マスタ未登録 | B24: =IF(AND(C24<>"", COUNTIF('マスタ'!$C:$C, C24)=0), "マスタ未登録", "") -> マスタ未登録 | C24: =D24&D129&E24&F24&G24&H24 -> 商品売上原価 | F24: 商品売上原価 | J24: 56777489 | K24: 903439 | L24: 0 | M24: 0 | N24: 0 | O24: 0 | P24: 0 | Q24: 0 | R24: 0 | S24: 0 | T24: 0 | U24: 0 | V24: 57680928
A25: {=XLOOKUP(C25, 'マスタ'!$C$2:$C$312, 'マスタ'!$D$2:$D$312, "マスタ未登録")} -> マスタ未登録 | B25: =IF(AND(C25<>"", COUNTIF('マスタ'!$C:$C, C25)=0), "マスタ未登録", "") -> マスタ未登録 | C25: =D25&D130&E25&F25&G25&H25 -> 売上総損益金額 | D25: 売上総損益金額 | J25: -56581993 | K25: -903439 | L25: 0 | M25: 0 | N25: 0 | O25: 0 | P25: 0 | Q25: 0 | R25: 0 | S25: 0 | T25: 0 | U25: 0 | V25: -57485432
A26: {=XLOOKUP(C26, 'マスタ'!$C$2:$C$312, 'マスタ'!$D$2:$D$312, "マスタ未登録")} -> マスタ未登録 | B26: =IF(AND(C26<>"", COUNTIF('マスタ'!$C:$C, C26)=0), "マスタ未登録", "") -> マスタ未登録 | C26: =D26&D131&E26&F26&G26&H26 -> 販売管理費 | E26: 販売管理費
A27: {=XLOOKUP(C27, 'マスタ'!$C$2:$C$312, 'マスタ'!$D$2:$D$312, "マスタ未登録")} -> 給料手当 | B27: =IF(AND(C27<>"", COUNTIF('マスタ'!$C:$C, C27)=0), "マスタ未登録", "") | C27: =D27&D132&E27&F27&G27&H27 -> 給料手当 | F27: 給料手当 | J27: 9286900 | K27: 0 | L27: 0 | M27: 0 | N27: 0 | O27: 0 | P27: 0 | Q27: 0 | R27: 0 | S27: 0 | T27: 0 | U27: 0 | V27: 9286900
A28: {=XLOOKUP(C28, 'マスタ'!$C$2:$C$312, 'マスタ'!$D$2:$D$312, "マスタ未登録")} -> 法定福利費 | B28: =IF(AND(C28<>"", COUNTIF('マスタ'!$C:$C, C28)=0), "マスタ未登録", "") | C28: =D28&D133&E28&F28&G28&H28 -> 法定福利費 | F28: 法定福利費 | J28: 966320 | K28: 0 | L28: 0 | M28: 0 | N28: 0 | O28: 0 | P28: 0 | Q28: 0 | R28: 0 | S28: 0 | T28: 0 | U28: 0 | V28: 966320
A29: {=XLOOKUP(C29, 'マスタ'!$C$2:$C$312, 'マスタ'!$D$2:$D$312, "マスタ未登録")} -> 福利厚生費 | B29: =IF(AND(C29<>"", COUNTIF('マスタ'!$C:$C, C29)=0), "マスタ未登録", "") | C29: =D29&D134&E29&F29&G29&H29 -> 福利厚生費 | F29: 福利厚生費 | J29: 432775 | K29: 35630 | L29: 0 | M29: 0 | N29: 0 | O29: 0 | P29: 0 | Q29: 0 | R29: 0 | S29: 0 | T29: 0 | U29: 0 | V29: 468405
A30: {=XLOOKUP(C30, 'マスタ'!$C$2:$C$312, 'マスタ'!$D$2:$D$312, "マスタ未登録")} -> 旅費交通費 | B30: =IF(AND(C30<>"", COUNTIF('マスタ'!$C:$C, C30)=0), "マスタ未登録", "") | C30: =D30&D135&E30&F30&G30&H30 -> 旅費交通費 | F30: 旅費交通費 | J30: 136176 | K30: 0 | L30: 0 | M30: 0 | N30: 0 | O30: 0 | P30: 0 | Q30: 0 | R30: 0 | S30: 0 | T30: 0 | U30: 0 | V30: 136176
A31: {=XLOOKUP(C31, 'マスタ'!$C$2:$C$312, 'マスタ'!$D$2:$D$312, "マスタ未登録")} -> 通信費 | B31: =IF(AND(C31<>"", COUNTIF('マスタ'!$C:$C, C31)=0), "マスタ未登録", "") | C31: =D31&D136&E31&F31&G31&H31 -> 通信費 | F31: 通信費 | J31: 2881969 | K31: 1908278 | L31: 0 | M31: 0 | N31: 0 | O31: 0 | P31: 0 | Q31: 0 | R31: 0 | S31: 0 | T31: 0 | U31: 0 | V31: 4790247
A32: {=XLOOKUP(C32, 'マスタ'!$C$2:$C$312, 'マスタ'!$D$2:$D$312, "マスタ未登録")} -> 採用教育費 | B32: =IF(AND(C32<>"", COUNTIF('マスタ'!$C:$C, C32)=0), "マスタ未登録", "") | C32: =D32&D137&E32&F32&G32&H32 -> 採用教育費 | F32: 採用教育費 | J32: 72000 | K32: 45000 | L32: 0 | M32: 0 | N32: 0 | O32: 0 | P32: 0 | Q32: 0 | R32: 0 | S32: 0 | T32: 0 | U32: 0 | V32: 117000
A33: {=XLOOKUP(C33, 'マスタ'!$C$2:$C$312, 'マスタ'!$D$2:$D$312, "マスタ未登録")} -> 業務委託費 | B33: =IF(AND(C33<>"", COUNTIF('マスタ'!$C:$C, C33)=0), "マスタ未登録", "") | C33: =D33&D138&E33&F33&G33&H33 -> 業務委託費 | F33: 業務委託費 | J33: 10327403 | K33: 0 | L33: 0 | M33: 0 | N33: 0 | O33: 0 | P33: 0 | Q33: 0 | R33: 0 | S33: 0 | T33: 0 | U33: 0 | V33: 10327403
A34: {=XLOOKUP(C34, 'マスタ'!$C$2:$C$312, 'マスタ'!$D$2:$D$312, "マスタ未登録")} -> 支払報酬 | B34: =IF(AND(C34<>"", COUNTIF('マスタ'!$C:$C, C34)=0), "マスタ未登録", "") | C34: =D34&D139&E34&F34&G34&H34 -> 支払報酬料 | F34: 支払報酬料 | J34: 580000 | K34: 360000 | L34: 0 | M34: 0 | N34: 0 | O34: 0 | P34: 0 | Q34: 0 | R34: 0 | S34: 0 | T34: 0 | U34: 0 | V34: 940000
A35: {=XLOOKUP(C35, 'マスタ'!$C$2:$C$312, 'マスタ'!$D$2:$D$312, "マスタ未登録")} -> 広告宣伝費 | B35: =IF(AND(C35<>"", COUNTIF('マスタ'!$C:$C, C35)=0), "マスタ未登録", "") | C35: =D35&D140&E35&F35&G35&H35 -> 広告宣伝費 | F35: 広告宣伝費 | J35: 213775 | K35: 0 | L35: 0 | M35: 0 | N35: 0 | O35: 0 | P35: 0 | Q35: 0 | R35: 0 | S35: 0 | T35: 0 | U35: 0 | V35: 213775
A36: {=XLOOKUP(C36, 'マスタ'!$C$2:$C$312, 'マスタ'!$D$2:$D$312, "マスタ未登録")} -> 荷造運賃 | B36: =IF(AND(C36<>"", COUNTIF('マスタ'!$C:$C, C36)=0), "マスタ未登録", "") | C36: =D36&D141&E36&F36&G36&H36 -> 荷造運賃 | F36: 荷造運賃 | J36: 7070 | K36: 0 | L36: 0 | M36: 0 | N36: 0 | O36: 0 | P36: 0 | Q36: 0 | R36: 0 | S36: 0 | T36: 0 | U36: 0 | V36: 7070
A37: {=XLOOKUP(C37, 'マスタ'!$C$2:$C$312, 'マスタ'!$D$2:$D$312, "マスタ未登録")} -> 水道光熱費 | B37: =IF(AND(C37<>"", COUNTIF('マスタ'!$C:$C, C37)=0), "マスタ未登録", "") | C37: =D37&D142&E37&F37&G37&H37 -> 水道光熱費 | F37: 水道光熱費 | J37: 367893 | K37: 0 | L37: 0 | M37: 0 | N37: 0 | O37: 0 | P37: 0 | Q37: 0 | R37: 0 | S37: 0 | T37: 0 | U37: 0 | V37: 367893
A38: {=XLOOKUP(C38, 'マスタ'!$C$2:$C$312, 'マスタ'!$D$2:$D$312, "マスタ未登録")} -> 支払手数料 | B38: =IF(AND(C38<>"", COUNTIF('マスタ'!$C:$C, C38)=0), "マスタ未登録", "") | C38: =D38&D143&E38&F38&G38&H38 -> 支払手数料 | F38: 支払手数料 | J38: 2527153 | K38: 0 | L38: 0 | M38: 0 | N38: 0 | O38: 0 | P38: 0 | Q38: 0 | R38: 0 | S38: 0 | T38: 0 | U38: 0 | V38: 2527153
... A45: {=XLOOKUP(C45, 'マスタ'!$C$2:$C$312, 'マスタ'!$D$2:$D$312, "マスタ未登録")} -> 減価償却費 | B45: =IF(AND(C45<>"", COUNTIF('マスタ'!$C:$C, C45)=0), "マスタ未登録", "") | C45: =D45&D150&E45&F45&G45&H45 -> 減価償却費 | F45: 減価償却費 | J45: 1604637 | K45: 0 | L45: 0 | M45: 0 | N45: 0 | O45: 0 | P45: 0 | Q45: 0 | R45: 0 | S45: 0 | T45: 0 | U45: 0 | V45: 1604637
A46: {=XLOOKUP(C46, 'マスタ'!$C$2:$C$312, 'マスタ'!$D$2:$D$312, "マスタ未登録")} -> マスタ未登録 | B46: =IF(AND(C46<>"", COUNTIF('マスタ'!$C:$C, C46)=0), "マスタ未登録", "") -> マスタ未登録 | C46: =D46&D151&E46&F46&G46&H46 -> 販売管理費 計 | E46: 販売管理費 計 | J46: 39385617 | K46: 11044427 | L46: 0 | M46: 0 | N46: 0 | O46: 0 | P46: 0 | Q46: 0 | R46: 0 | S46: 0 | T46: 0 | U46: 0 | V46: 50430044
A47: {=XLOOKUP(C47, 'マスタ'!$C$2:$C$312, 'マスタ'!$D$2:$D$312, "マスタ未登録")} -> マスタ未登録 | B47: =IF(AND(C47<>"", COUNTIF('マスタ'!$C:$C, C47)=0), "マスタ未登録", "") -> マスタ未登録 | C47: =D47&D152&E47&F47&G47&H47 -> 営業損益金額 | D47: 営業損益金額 | J47: -95967610 | K47: -11947866 | L47: 0 | M47: 0 | N47: 0 | O47: 0 | P47: 0 | Q47: 0 | R47: 0 | S47: 0 | T47: 0 | U47: 0 | V47: -107915476
A48: {=XLOOKUP(C48, 'マスタ'!$C$2:$C$312, 'マスタ'!$D$2:$D$312, "マスタ未登録")} -> マスタ未登録 | B48: =IF(AND(C48<>"", COUNTIF('マスタ'!$C:$C, C48)=0), "マスタ未登録", "") -> マスタ未登録 | C48: =D48&D153&E48&F48&G48&H48 -> 営業外収益 | E48: 営業外収益 | J48: 94903 | K48: 30147 | L48: 0 | M48: 0 | N48: 0 | O48: 0 | P48: 0 | Q48: 0 | R48: 0 | S48: 0 | T48: 0 | U48: 0 | V48: 125050
A49: {=XLOOKUP(C49, 'マスタ'!$C$2:$C$312, 'マスタ'!$D$2:$D$312, "マスタ未登録")} -> 受取利息 | B49: =IF(AND(C49<>"", COUNTIF('マスタ'!$C:$C, C49)=0), "マスタ未登録", "") | C49: =D49&D154&E49&F49&G49&H49 -> 受取利息 | F49: 受取利息 | J49: 24774 | K49: 0 | L49: 0 | M49: 0 | N49: 0 | O49: 0 | P49: 0 | Q49: 0 | R49: 0 | S49: 0 | T49: 0 | U49: 0 | V49: 24774
A50: {=XLOOKUP(C50, 'マスタ'!$C$2:$C$312, 'マスタ'!$D$2:$D$312, "マスタ未登録")} -> 雑収入 | B50: =IF(AND(C50<>"", COUNTIF('マスタ'!$C:$C, C50)=0), "マスタ未登録", "") | C50: =D50&D155&E50&F50&G50&H50 -> 雑収入 | F50: 雑収入 | J50: 70129 | K50: 30147 | L50: 0 | M50: 0 | N50: 0 | O50: 0 | P50: 0 | Q50: 0 | R50: 0 | S50: 0 | T50: 0 | U50: 0 | V50: 100276
A51: {=XLOOKUP(C51, 'マスタ'!$C$2:$C$312, 'マスタ'!$D$2:$D$312, "マスタ未登録")} -> マスタ未登録 | B51: =IF(AND(C51<>"", COUNTIF('マスタ'!$C:$C, C51)=0), "マスタ未登録", "") -> マスタ未登録 | C51: =D51&D156&E51&F51&G51&H51 -> 営業外費用 | E51: 営業外費用 | J51: 139716 | K51: 0 | L51: 0 | M51: 0 | N51: 0 | O51: 0 | P51: 0 | Q51: 0 | R51: 0 | S51: 0 | T51: 0 | U51: 0 | V51: 139716
A52: {=XLOOKUP(C52, 'マスタ'!$C$2:$C$312, 'マスタ'!$D$2:$D$312, "マスタ未登録")} -> 支払利息 | B52: =IF(AND(C52<>"", COUNTIF('マスタ'!$C:$C, C52)=0), "マスタ未登録", "") | C52: =D52&D157&E52&F52&G52&H52 -> 支払利息 | F52: 支払利息 | J52: 139716 | K52: 0 | L52: 0 | M52: 0 | N52: 0 | O52: 0 | P52: 0 | Q52: 0 | R52: 0 | S52: 0 | T52: 0 | U52: 0 | V52: 139716
A53: {=XLOOKUP(C53, 'マスタ'!$C$2:$C$312, 'マスタ'!$D$2:$D$312, "マスタ未登録")} -> マスタ未登録 | B53: =IF(AND(C53<>"", COUNTIF('マスタ'!$C:$C, C53)=0), "マスタ未登録", "") -> マスタ未登録 | C53: =D53&D158&E53&F53&G53&H53 -> 経常損益金額 | D53: 経常損益金額 | J53: -96012423 | K53: -11917719 | L53: 0 | M53: 0 | N53: 0 | O53: 0 | P53: 0 | Q53: 0 | R53: 0 | S53: 0 | T53: 0 | U53: 0 | V53: -107930142
A54: {=XLOOKUP(C54, 'マスタ'!$C$2:$C$312, 'マスタ'!$D$2:$D$312, "マスタ未登録")} -> マスタ未登録 | B54: =IF(AND(C54<>"", COUNTIF('マスタ'!$C:$C, C54)=0), "マスタ未登録", "") -> マスタ未登録 | C54: =D54&D159&E54&F54&G54&H54 -> 特別利益 | E54: 特別利益 | J54: 0 | K54: 0 | L54: 0 | M54: 0 | N54: 0 | O54: 0 | P54: 0 | Q54: 0 | R54: 0 | S54: 0 | T54: 0 | U54: 0 | V54: 0
A55: {=XLOOKUP(C55, 'マスタ'!$C$2:$C$312, 'マスタ'!$D$2:$D$312, "マスタ未登録")} -> マスタ未登録 | B55: =IF(AND(C55<>"", COUNTIF('マスタ'!$C:$C, C55)=0), "マスタ未登録", "") -> マスタ未登録 | C55: =D55&D160&E55&F55&G55&H55 -> 特別損失 | E55: 特別損失 | J55: 0 | K55: 0 | L55: 0 | M55: 0 | N55: 0 | O55: 0 | P55: 0 | Q55: 0 | R55: 0 | S55: 0 | T55: 0 | U55: 0 | V55: 0
A56: {=XLOOKUP(C56, 'マスタ'!$C$2:$C$312, 'マスタ'!$D$2:$D$312, "マスタ未登録")} -> マスタ未登録 | B56: =IF(AND(C56<>"", COUNTIF('マスタ'!$C:$C, C56)=0), "マスタ未登録", "") -> マスタ未登録 | C56: =D56&D161&E56&F56&G56&H56 -> 税引前当期純損益金額 | D56: 税引前当期純損益金額 | J56: -96012423 | K56: -11917719 | L56: 0 | M56: 0 | N56: 0 | O56: 0 | P56: 0 | Q56: 0 | R56: 0 | S56: 0 | T56: 0 | U56: 0 | V56: -107930142
E57: 法人税等 | J57: 0 | K57: 0 | L57: 0 | M57: 0 | N57: 0 | O57: 0 | P57: 0 | Q57: 0 | R57: 0 | S57: 0 | T57: 0 | U57: 0 | V57: 0
